Workbook
Name CLIENTE: [1]CADASTRO!$E$5:$E$154
Name PROJETO: [1]CADASTRO!$C$5:$C$154
Name RESPONSAVEL: [1]CADASTRO!$D$5:$D$154

Sheet GRAF % ATEND
L2: GRÁFICO DE GESTÃO DE REFUGO QUALIDADE | AJ2: REVISÃO: | AM2: 01
AJ3: PÁGINA: | AM3: 01/01
AJ4: EMISSÃO: | AM4: JAN/2024
C7: ACUMULADO - ANO - (%) | O7: TOTAL - MÊS - (%) | AH7: EVOLUÇÃO - SEM - (%)
C20: DIÁRIO: | F20: 46023 | L20: A | N20: 46053
C46: PPM ACUMULADO - ANO
C59: PPM - DIÁRIO
B84: Analise dos maiores impactos
B125: Analise dos maiores impactos - Por modo de Falha

Sheet RESULTADO
C2: Real | N2: Projeção | U2: QTD | Z2: Valor Fechamento (Controladoria)
C3: Ref SPR | D3: Ref SCI | E3: Fat | F3: % | G3: Obj | H3: Aceitavél | I3: SPR | J3: SCI | K3: Total | L3: Média/dia | N3: WD | O3: Ref | P3: Fat | Q3: SPR | R3: SCI | S3: Total | T3: % | U3: Produzido | V3: Ref. | W3: PPM | X3: Meta | Z3: SPR | AA3: SCI | AB3: Total
A4: 1 | B4: Jan | C4: =SUMIF(DADOS_GRAF!$L:$L,$A4,DADOS_GRAF!$W:$W) -> #N/A | D4: =SUMIF(DADOS_GRAF!$L:$L,$A4,DADOS_GRAF!$X:$X) -> 0 | E4: =SUMIF(DADOS_GRAF!$L:$L,$A4,DADOS_GRAF!$Y:$Y) -> 34589820 | F4: =IFERROR(C4/E4,#N/A) -> #N/A | G4: 0.0028 | H4: 0.003 | I4: =IF(Z4="",SUMIF(DADOS_GRAF!$L:$L,$A4,DADOS_GRAF!$W:$W)/$E4,Z4) -> #N/A | J4: =IF(AA4="",SUMIF(DADOS_GRAF!$L:$L,$A4,DADOS_GRAF!$X:$X)/$E4,AA4) -> 0 | K4: =I4+J4 -> #N/A | L4: =(C4+D4)/COUNTIFS(DADOS_GRAF!AC:AC,"x",DADOS_GRAF!L:L,A4) -> #N/A | M4: Jan | N4: 20 | O4: =((C4+D4)/COUNTIFS(DADOS_GRAF!AC:AC,"x",DADOS_GRAF!L:L,A4))*N4 -> #N/A | Q4: =IFERROR(VLOOKUP(A4,$A$4:$C$15,3,FALSE)/P4,0) -> 0 | R4: =VLOOKUP(A4,$A$4:$D$15,4,FALSE)/P4 -> #DIV/0! | S4: =R4+Q4 -> #DIV/0! | T4: =O4/P4 -> #N/A | U4: =SUM(DADOS_GRAF!T3:T33) -> 874567 | V4: =SUMIF(DADOS_GRAF!L3:L155,A4,DADOS_GRAF!R3:R155)+SUMIF(DADOS_GRAF!L3:L155,A4,DADOS_GRAF!S3:S155) -> 24680.6 | W4: =(V4/U4)*1000000 -> 28220.365 | X4: 4600 | Y4: Jan | AB4: =SUM(Z4:AA4) -> 0
A5: =A4+1 -> 2 | B5: Fev | C5: =SUMIF(DADOS_GRAF!$L:$L,$A5,DADOS_GRAF!$W:$W) -> 0 | D5: =SUMIF(DADOS_GRAF!$L:$L,$A5,DADOS_GRAF!$X:$X) -> 0 | E5: =SUMIF(DADOS_GRAF!$L:$L,$A5,DADOS_GRAF!$Y:$Y) -> 0 | F5: =IFERROR(C5/E5,"") | G5: 0.0028 | H5: 0.003 | M5: Fev | N5: 20 | O5: =((C5+D5)/COUNTIFS(DADOS_GRAF!AC:AC,"x",DADOS_GRAF!L:L,A5))*N5 -> #DIV/0! | Q5: =IFERROR(VLOOKUP(A5,$A$4:$C$15,3,FALSE)/P5,0) -> 0 | R5: =VLOOKUP(A5,$A$4:$D$15,4,FALSE)/P5 -> #DIV/0! | S5: =R5+Q5 -> #DIV/0! | T5: =O5/P5 -> #DIV/0! | V5: =SUMIF(DADOS_GRAF!L4:L155,A5,DADOS_GRAF!R4:R155)+SUMIF(DADOS_GRAF!L4:L155,A5,DADOS_GRAF!S4:S155) -> 24462.8 | W5: =V5/U5*10^6 -> #DIV/0! | X5: 4600 | Y5: Fev | AB5: =SUM(Z5:AA5) -> 0
A6: =A5+1 -> 3 | B6: Mar | C6: =SUMIF(DADOS_GRAF!$L:$L,$A6,DADOS_GRAF!$W:$W) -> 0 | D6: =SUMIF(DADOS_GRAF!$L:$L,$A6,DADOS_GRAF!$X:$X) -> 0 | E6: =SUMIF(DADOS_GRAF!$L:$L,$A6,DADOS_GRAF!$Y:$Y) -> 0 | F6: =IFERROR(C6/E6,"") | G6: 0.0028 | H6: 0.003 | M6: Mar | N6: 21 | O6: =((C6+D6)/COUNTIFS(DADOS_GRAF!AC:AC,"x",DADOS_GRAF!L:L,A6))*N6 -> #DIV/0! | Q6: =IFERROR(VLOOKUP(A6,$A$4:$C$15,3,FALSE)/P6,0) -> 0 | R6: =VLOOKUP(A6,$A$4:$D$15,4,FALSE)/P6 -> #DIV/0! | S6: =R6+Q6 -> #DIV/0! | T6: =O6/P6 -> #DIV/0! | V6: =SUMIF(DADOS_GRAF!L5:L155,A6,DADOS_GRAF!R5:R155)+SUMIF(DADOS_GRAF!L5:L155,A6,DADOS_GRAF!S5:S155) -> 2789 | W6: =V6/U6*10^6 -> #DIV/0! | X6: 4600 | Y6: Mar | AB6: =SUM(Z6:AA6) -> 0
A7: =A6+1 -> 4 | B7: Abr | C7: =SUMIF(DADOS_GRAF!$L:$L,$A7,DADOS_GRAF!$W:$W) -> 0 | D7: =SUMIF(DADOS_GRAF!$L:$L,$A7,DADOS_GRAF!$X:$X) -> 0 | E7: =SUMIF(DADOS_GRAF!$L:$L,$A7,DADOS_GRAF!$Y:$Y) -> 0 | F7: =IFERROR(C7/E7,"") | G7: 0.0028 | H7: 0.003 | M7: Abr | N7: 20 | O7: =((C7+D7)/COUNTIFS(DADOS_GRAF!AC:AC,"x",DADOS_GRAF!L:L,A7))*N7 -> #DIV/0! | Q7: =IFERROR(VLOOKUP(A7,$A$4:$C$15,3,FALSE)/P7,0) -> 0 | R7: =VLOOKUP(A7,$A$4:$D$15,4,FALSE)/P7 -> #DIV/0! | S7: =R7+Q7 -> #DIV/0! | T7: =O7/P7 -> #DIV/0! | V7: =SUM(DADOS_GRAF!S93:S122) -> 0 | W7: =V7/U7*10^6 -> #DIV/0! | X7: 4600 | Y7: Abr | AB7: =SUM(Z7:AA7) -> 0
A8: =A7+1 -> 5 | B8: Mai | C8: =SUMIF(DADOS_GRAF!$L:$L,$A8,DADOS_GRAF!$W:$W) -> 0 | D8: =SUMIF(DADOS_GRAF!$L:$L,$A8,DADOS_GRAF!$X:$X) -> 0 | E8: =SUMIF(DADOS_GRAF!$L:$L,$A8,DADOS_GRAF!$Y:$Y) -> 0 | F8: =IFERROR(C8/E8,"") | G8: 0.0028 | H8: 0.003 | M8: Mai | N8: 21 | O8: =((C8+D8)/COUNTIFS(DADOS_GRAF!AC:AC,"x",DADOS_GRAF!L:L,A8))*N8 -> #DIV/0! | Q8: =IFERROR(VLOOKUP(A8,$A$4:$C$15,3,FALSE)/P8,0) -> 0 | R8: =VLOOKUP(A8,$A$4:$D$15,4,FALSE)/P8 -> #DIV/0! | S8: =R8+Q8 -> #DIV/0! | T8: =O8/P8 -> #DIV/0! | V8: =SUMIF(DADOS_GRAF!L7:L155,A8,DADOS_GRAF!R7:R155)+SUMIF(DADOS_GRAF!L7:L155,A8,DADOS_GRAF!S7:S155) -> 0 | W8: =V8/U8*10^6 -> #DIV/0! | X8: 4600 | Y8: Mai | AB8: =SUM(Z8:AA8) -> 0
A9: =A8+1 -> 6 | B9: Jun | C9: =SUMIF(DADOS_GRAF!$L:$L,$A9,DADOS_GRAF!$W:$W) -> 0 | D9: =SUMIF(DADOS_GRAF!$L:$L,$A9,DADOS_GRAF!$X:$X) -> 0 | E9: =SUMIF(DADOS_GRAF!$L:$L,$A9,DADOS_GRAF!$Y:$Y) -> 0 | F9: =IFERROR(C9/E9,"") | G9: 0.0028 | H9: 0.003 | M9: Jun | N9: 20 | O9: =((C9+D9)/COUNTIFS(DADOS_GRAF!AC:AC,"x",DADOS_GRAF!L:L,A9))*N9 -> #DIV/0! | Q9: =IFERROR(VLOOKUP(A9,$A$4:$C$15,3,FALSE)/P9,0) -> 0 | R9: =VLOOKUP(A9,$A$4:$D$15,4,FALSE)/P9 -> #DIV/0! | S9: =R9+Q9 -> #DIV/0! | T9: =O9/P9 -> #DIV/0! | V9: =SUMIF(DADOS_GRAF!L8:L155,A9,DADOS_GRAF!R8:R155)+SUMIF(DADOS_GRAF!L8:L155,A9,DADOS_GRAF!S8:S155) -> 0 | W9: =V9/U9*10^6 -> #DIV/0! | X9: 4600 | Y9: Jun | AB9: =SUM(Z9:AA9) -> 0
A10: =A9+1 -> 7 | B10: Jul | C10: =SUMIF(DADOS_GRAF!$L:$L,$A10,DADOS_GRAF!$W:$W) -> 0 | D10: =SUMIF(DADOS_GRAF!$L:$L,$A10,DADOS_GRAF!$X:$X) -> 0 | E10: =SUMIF(DADOS_GRAF!$L:$L,$A10,DADOS_GRAF!$Y:$Y) -> 0 | F10: =IFERROR(C10/E10,"") | G10: 0.0028 | H10: 0.003 | M10: Jul | N10: 22 | O10: =((C10+D10)/COUNTIFS(DADOS_GRAF!AC:AC,"x",DADOS_GRAF!L:L,A10))*N10 -> #DIV/0! | Q10: =IFERROR(VLOOKUP(A10,$A$4:$C$15,3,FALSE)/P10,0) -> 0 | R10: =VLOOKUP(A10,$A$4:$D$15,4,FALSE)/P10 -> #DIV/0! | S10: =R10+Q10 -> #DIV/0! | T10: =O10/P10 -> #DIV/0! | V10: =SUMIF(DADOS_GRAF!L9:L155,A10,DADOS_GRAF!R9:R155)+SUMIF(DADOS_GRAF!L9:L155,A10,DADOS_GRAF!S9:S155) -> 0 | W10: =V10/U10*10^6 -> #DIV/0! | X10: 4600 | Y10: Jul | AB10: =SUM(Z10:AA10) -> 0
A11: =A10+1 -> 8 | B11: Ago | C11: =SUMIF(DADOS_GRAF!$L:$L,$A11,DADOS_GRAF!$W:$W) -> 0 | D11: =SUMIF(DADOS_GRAF!$L:$L,$A11,DADOS_GRAF!$X:$X) -> 0 | E11: =SUMIF(DADOS_GRAF!$L:$L,$A11,DADOS_GRAF!$Y:$Y) -> 0 | G11: 0.0028 | H11: 0.003 | M11: Ago | N11: 21 | O11: =((C11+D11)/COUNTIFS(DADOS_GRAF!AC:AC,"x",DADOS_GRAF!L:L,A11))*N11 -> #DIV/0! | Q11: =IFERROR(VLOOKUP(A11,$A$4:$C$15,3,FALSE)/P11,0) -> 0 | R11: =VLOOKUP(A11,$A$4:$D$15,4,FALSE)/P11 -> #DIV/0! | S11: =R11+Q11 -> #DIV/0! | T11: =O11/P11 -> #DIV/0! | V11: =SUMIF(DADOS_GRAF!L10:L156,A11,DADOS_GRAF!R10:R156)+SUMIF(DADOS_GRAF!L10:L156,A11,DADOS_GRAF!S10:S156) -> 0 | W11: =V11/U11*10^6 -> #DIV/0! | X11: 4600 | Y11: Ago | AB11: =SUM(Z11:AA11) -> 0
A12: =A11+1 -> 9 | B12: Set | C12: =SUMIF(DADOS_GRAF!$L:$L,$A12,DADOS_GRAF!$W:$W) -> 0 | D12: =SUMIF(DADOS_GRAF!$L:$L,$A12,DADOS_GRAF!$X:$X) -> 0 | E12: =SUMIF(DADOS_GRAF!$L:$L,$A12,DADOS_GRAF!$Y:$Y) -> 0 | F12: =IFERROR(C12/E12,"") | G12: 0.0028 | H12: 0.003 | M12: Set | N12: 21 | O12: =((C12+D12)/COUNTIFS(DADOS_GRAF!AC:AC,"x",DADOS_GRAF!L:L,A12))*N12 -> #DIV/0! | Q12: =IFERROR(VLOOKUP(A12,$A$4:$C$15,3,FALSE)/P12,0) -> 0 | R12: =VLOOKUP(A12,$A$4:$D$15,4,FALSE)/P12 -> #DIV/0! | S12: =R12+Q12 -> #DIV/0! | T12: =O12/P12 -> #DIV/0! | V12: =SUMIF(DADOS_GRAF!L11:L155,A12,DADOS_GRAF!R11:R155)+SUMIF(DADOS_GRAF!L11:L155,A12,DADOS_GRAF!S11:S155) -> 0 | W12: =V12/U12*10^6 -> #DIV/0! | X12: 4600 | Y12: Set | AB12: =SUM(Z12:AA12) -> 0
A13: =A12+1 -> 10 | B13: Out | C13: =SUMIF(DADOS_GRAF!$L:$L,$A13,DADOS_GRAF!$W:$W) -> 0 | D13: =SUMIF(DADOS_GRAF!$L:$L,$A13,DADOS_GRAF!$X:$X) -> 0 | E13: =SUMIF(DADOS_GRAF!$L:$L,$A13,DADOS_GRAF!$Y:$Y) -> 0 | F13: =IFERROR(C13/E13,"") | G13: 0.0028 | H13: 0.003 | M13: Out | N13: 23 | O13: =((C13+D13)/COUNTIFS(DADOS_GRAF!AC:AC,"x",DADOS_GRAF!L:L,A13))*N13 -> #DIV/0! | Q13: =IFERROR(VLOOKUP(A13,$A$4:$C$15,3,FALSE)/P13,0) -> 0 | R13: =VLOOKUP(A13,$A$4:$D$15,4,FALSE)/P13 -> #DIV/0! | S13: =R13+Q13 -> #DIV/0! | T13: =O13/P13 -> #DIV/0! | V13: =SUMIF(DADOS_GRAF!L12:L155,A13,DADOS_GRAF!R12:R155)+SUMIF(DADOS_GRAF!L12:L155,A13,DADOS_GRAF!S12:S155) -> 0 | W13: =V13/U13*10^6 -> #DIV/0! | X13: 4600 | Y13: Out | AB13: =SUM(Z13:AA13) -> 0
A14: =A13+1 -> 11 | B14: Nov | C14: =SUMIF(DADOS_GRAF!$L:$L,$A14,DADOS_GRAF!$W:$W) -> 0 | D14: =SUMIF(DADOS_GRAF!$L:$L,$A14,DADOS_GRAF!$X:$X) -> 0 | E14: =SUMIF(DADOS_GRAF!$L:$L,$A14,DADOS_GRAF!$Y:$Y) -> 0 | F14: =IFERROR(C14/E14,"") | G14: 0.0028 | H14: 0.003 | M14: Nov | N14: 19 | O14: =((C14+D14)/COUNTIFS(DADOS_GRAF!AC:AC,"x",DADOS_GRAF!L:L,A14))*N14 -> #DIV/0! | Q14: =IFERROR(VLOOKUP(A14,$A$4:$C$15,3,FALSE)/P14,0) -> 0 | R14: =VLOOKUP(A14,$A$4:$D$15,4,FALSE)/P14 -> #DIV/0! | S14: =R14+Q14 -> #DIV/0! | T14: =O14/P14 -> #DIV/0! | V14: =SUMIF(DADOS_GRAF!L13:L155,A14,DADOS_GRAF!R13:R155)+SUMIF(DADOS_GRAF!L13:L155,A14,DADOS_GRAF!S13:S155) -> 0 | W14: =V14/U14*10^6 -> #DIV/0! | X14: 4600 | Y14: Nov | AB14: =SUM(Z14:AA14) -> 0
A15: =A14+1 -> 12 | B15: Dez | C15: =SUMIF(DADOS_GRAF!$L:$L,$A15,DADOS_GRAF!$W:$W) -> 0 | D15: =SUMIF(DADOS_GRAF!$L:$L,$A15,DADOS_GRAF!$X:$X) -> 0 | E15: =SUMIF(DADOS_GRAF!$L:$L,$A15,DADOS_GRAF!$Y:$Y) -> 0 | F15: =IFERROR(C15/E15,"") | G15: 0.0028 | H15: 0.003 | M15: Dez | N15: 20 | O15: =((C15+D15)/COUNTIFS(DADOS_GRAF!AC:AC,"x",DADOS_GRAF!L:L,A15))*N15 -> #DIV/0! | Q15: =IFERROR(VLOOKUP(A15,$A$4:$C$15,3,FALSE)/P15,0) -> 0 | R15: =VLOOKUP(A15,$A$4:$D$15,4,FALSE)/P15 -> #DIV/0! | S15: =R15+Q15 -> #DIV/0! | T15: =O15/P15 -> #DIV/0! | V15: =SUMIF(DADOS_GRAF!L14:L155,A15,DADOS_GRAF!R14:R155)+SUMIF(DADOS_GRAF!L14:L155,A15,DADOS_GRAF!S14:S155) -> 0 | W15: =V15/U15*10^6 -> #DIV/0! | X15: 4600 | Y15: Dez | AB15: =SUM(Z15:AA15) -> 0
N16: =SUM(N4:N15) -> 248 | U16: =SUM(U4:U15) -> 874567 | V16: =SUM(V4:V15) -> 51932.4 | W16: =V16/(U16+V16)*10^6 -> 56052.276 | X16: 4600
C19: Ano | J19: Semana | P19: PPM _ Ano | V19: Semana
C20: % | D20: 2023 | E20: 2024 | F20: 2025 | I20: =TODAY() -> 46088 | J20: =K20-1 -> 7 | K20: =L20-1 -> 8 | L20: =M20-1 -> 9 | M20: =WEEKNUM(I20) -> 10 | P20: N. | Q20: 2023 | R20: 2024 | S20: 2025 | U20: =TODAY() -> 46088 | V20: =W20-1 -> 7 | W20: =X20-1 -> 8 | X20: =Y20-1 -> 9 | Y20: =WEEKNUM(U20) -> 10
C21: SPR | D21: 1067811 | E21: 686772.24 | F21: =SUMIF(DADOS_GRAF!M:M,F20,DADOS_GRAF!W:W) -> 0 | I21: SPR | J21: =SUMIF(DADOS_GRAF!$N:$N,J$20,DADOS_GRAF!$W:$W) -> 0 | K21: =SUMIF(DADOS_GRAF!$N:$N,K$20,DADOS_GRAF!$W:$W) -> 0 | L21: =SUMIF(DADOS_GRAF!$N:$N,L$20,DADOS_GRAF!$W:$W) -> 0 | M21: =SUMIF(DADOS_GRAF!$N:$N,M$20,DADOS_GRAF!$W:$W) -> 0 | P21: Produzido | R21: 19895189 | S21: =U16 -> 874567 | U21: Produção | V21: =SUMIF(DADOS_GRAF!$N:$N,V$20,DADOS_GRAF!$T:$T) -> 0 | W21: =SUMIF(DADOS_GRAF!$N:$N,W$20,DADOS_GRAF!$T:$T) -> 0 | X21: =SUMIF(DADOS_GRAF!$N:$N,X$20,DADOS_GRAF!$T:$T) -> 0 | Y21: =SUMIF(DADOS_GRAF!$N:$N,Y$20,DADOS_GRAF!$T:$T) -> 0
C22: SCI | D22: 89555.854 | E22: 103639.3 | F22: =SUMIF(DADOS_GRAF!M:M,F20,DADOS_GRAF!X:X) -> 0 | I22: SCI | J22: =SUMIF(DADOS_GRAF!$N:$N,J$20,DADOS_GRAF!$X:$X) -> 0 | K22: =SUMIF(DADOS_GRAF!$N:$N,K$20,DADOS_GRAF!$X:$X) -> 0 | L22: =SUMIF(DADOS_GRAF!$N:$N,L$20,DADOS_GRAF!$X:$X) -> 0 | M22: =SUMIF(DADOS_GRAF!$N:$N,M$20,DADOS_GRAF!$X:$X) -> 0 | P22: Refugado | R22: 104611.99 | S22: =V16 -> 51932.4 | U22: Refugo | V22: =SUMIF(DADOS_GRAF!$N:$N,V$20,DADOS_GRAF!$S:$S) -> 4324 | W22: =SUMIF(DADOS_GRAF!$N:$N,W$20,DADOS_GRAF!$S:$S) -> 4176.5 | X22: =SUMIF(DADOS_GRAF!$N:$N,X$20,DADOS_GRAF!$S:$S) -> 3486.4 | Y22: =SUMIF(DADOS_GRAF!$N:$N,Y$20,DADOS_GRAF!$S:$S) -> 2434.5
C23: Fat | D23: 2.4357079e+08 | E23: 2.3582263e+08 | F23: =SUMIF(DADOS_GRAF!M:M,F20,DADOS_GRAF!Y:Y) -> 0 | I23: Fat (R$) | J23: =SUMIF(DADOS_GRAF!$N:$N,J$20,DADOS_GRAF!$Y:$Y) -> 0 | K23: =SUMIF(DADOS_GRAF!$N:$N,K$20,DADOS_GRAF!$Y:$Y) -> 0 | L23: =SUMIF(DADOS_GRAF!$N:$N,L$20,DADOS_GRAF!$Y:$Y) -> 0 | M23: =SUMIF(DADOS_GRAF!$N:$N,M$20,DADOS_GRAF!$Y:$Y) -> 0 | P23: PPM | Q23: =SUM(Q25:Q25) -> 0 | R23: =R22/R21*1000000 -> 5258.1552 | S23: =S22/S21*10^6 -> 59380.699 | U23: PPM | V23: =V22/V21*1000000 -> #DIV/0! | W23: =W22/W21*1000000 -> #DIV/0! | X23: =X22/X21*1000000 -> #DIV/0! | Y23: =Y22/Y21*1000000 -> #DIV/0!
C24: SPR | D24: =D21/D23 -> 0.0043839863 | E24: =E21/E23 -> 0.0029122406 | F24: =F21/F23 -> #DIV/0! | I24: Total | J24: =IFERROR(J21/J23,#N/A) -> #N/A | K24: =IFERROR(K21/K23,#N/A) -> #N/A | L24: =IFERROR(L21/L23,#N/A) -> #N/A | M24: =IFERROR(M21/M23,#N/A) -> #N/A | P24: Obj | R24: 4600 | U24: Obj | V24: 4600 | W24: 4600 | X24: 4600 | Y24: 4600
C25: SCI | D25: =D22/D23 -> 0.00036767896 | E25: =E22/E23 -> 0.00043947986 | F25: =F22/F23 -> #DIV/0! | I25: SPR | J25: =J21/J23 -> #DIV/0! | K25: =K21/K23 -> #DIV/0! | L25: =L21/L23 -> #DIV/0! | M25: =M21/M23 -> #DIV/0!
C26: Total | D26: =SUM(D24:D25) -> 0.0047516653 | E26: =SUM(E24:E25) -> 0.0033517205 | F26: =SUM(F24:F25) -> #DIV/0! | I26: SCI | J26: =J22/J23 -> #DIV/0! | K26: =K22/K23 -> #DIV/0! | L26: =L22/L23 -> #DIV/0! | M26: =M22/M23 -> #DIV/0!
C27: Obj | D27: 0.0048 | E27: 0.0035 | F27: 0.0025 | I27: Total | J27: =SUM(J25:J26) -> #DIV/0! | K27: =SUM(K25:K26) -> #DIV/0! | L27: =SUM(L25:L26) -> #DIV/0! | M27: =SUM(M25:M26) -> #DIV/0!
I28: Obj | J28: 0.0025 | K28: 0.0025 | L28: 0.0025 | M28: 0.0025

Sheet DADOS_GRAF
L1: Dados de Ref.
C2: Dia | D2: Ref | E2: Fat | F2: % | G2: Obj | H2: SPR | I2: SCI | J2: Total | L2: Mês | M2: Ano | N2: Sem | O2: Data | P2: Dia | Q2: SPR (Qtde) | R2: SCI (Qtde) | S2: Refugo (Tol) | T2: Prod. Dia | U2: Meta (PPM) | V2: PPM (Dia) | W2: SPR (R$) | X2: SCI (R$) | Y2: Fat | Z2: Total | AA2: SPR | AB2: SCI | AC2: Dias | AE2: Fat. ACM | AH2: Ano | AN2: Semana | AU2: Real
B3: =TEXT(WEEKDAY(C3),"ddd") -> qui | C3: =O3 -> 46023 | D3: =IFERROR(SUMIF(O:O,C3,W:W),#N/A) -> 0 | E3: =IFERROR(SUMIF(O:O,C3,Y:Y),#N/A) -> 0 | F3: =IFERROR(D3/E3,#N/A) -> #N/A | G3: 0.0035 | H3: =IF(E3=0,#N/A,IFERROR(SUMIF(O:O,C3,W:W),#N/A)/E3) -> #N/A | I3: =IF(E3=0,#N/A,IFERROR(SUMIF(O:O,C3,X:X),#N/A)/E3) -> #N/A | J3: =SUM(H3:I3) -> #N/A | L3: =MONTH(O3) -> 1 | M3: =YEAR(O3) -> 2026 | N3: =WEEKNUM(O3) -> 1 | O3: 46023 | P3: =TEXT(WEEKDAY(O3),"ddd") -> qui | Q3: =SUMIF('SPR - QTD'!$A:$A,DADOS_GRAF!O3,'SPR - QTD'!$H:$H) -> 0 | R3: =SUMIF('SCI - QTD'!$A:$A,DADOS_GRAF!O3,'SCI - QTD'!$H:$H) -> 0 | S3: =SUM(Q3:R3) -> 0 | U3: 4600 | V3: =(S3/T3)*10^6 -> #DIV/0! | W3: =SUMIF('SPR - QTD'!$A:$A,DADOS_GRAF!O3,'SPR - QTD'!$M:$M) -> 0 | X3: =SUMIF('SCI - QTD'!$A:$A,DADOS_GRAF!O3,'SCI - QTD'!$L:$L) -> 0 | AH3: % | AI3: 2021 | AJ3: 2022 | AK3: 2023 | AN3: 22 | AO3: =AN3+1 -> 23 | AP3: =AO3+1 -> 24 | AQ3: =AP3+1 -> 25 | AU3: Ref | AV3: Fat | AW3: % | AX3: Obj | AY3: SPR | AZ3: SCI | BA3: Total | BB3: Média/dia
B4: =TEXT(WEEKDAY(C4),"ddd") -> sex | C4: =O4 -> 46024 | D4: =IFERROR(SUMIF(O:O,C4,W:W),#N/A) -> 0 | E4: =IFERROR(SUMIF(O:O,C4,Y:Y),#N/A) -> 0 | F4: =IFERROR(D4/E4,#N/A) -> #N/A | G4: 0.0035 | H4: =IF(E4=0,#N/A,IFERROR(SUMIF(O:O,C4,W:W),#N/A)/E4) -> #N/A | I4: =IF(E4=0,#N/A,IFERROR(SUMIF(O:O,C4,X:X),#N/A)/E4) -> #N/A | J4: =SUM(H4:I4) -> #N/A | L4: =MONTH(O4) -> 1 | M4: =YEAR(O4) -> 2026 | N4: =WEEKNUM(O4) -> 1 | O4: 46024 | P4: =TEXT(WEEKDAY(O4),"ddd") -> sex | Q4: =SUMIF('SPR - QTD'!$A:$A,DADOS_GRAF!O4,'SPR - QTD'!$H:$H) -> 0 | R4: =SUMIF('SCI - QTD'!$A:$A,DADOS_GRAF!O4,'SCI - QTD'!$H:$H) -> 0 | S4: =SUM(Q4:R4) -> 0 | U4: 4600 | V4: =(S4/T4)*10^6 -> #DIV/0! | W4: =SUMIF('SPR - QTD'!$A:$A,DADOS_GRAF!O4,'SPR - QTD'!$M:$M) -> 0 | X4: =SUMIF('SCI - QTD'!$A:$A,DADOS_GRAF!O4,'SCI - QTD'!$L:$L) -> 0 | AH4: SPR | AK4: =SUMIF(M:M,AK3,W:W) -> 0 | AM4: SPR | AN4: =SUMIF($N:$N,AN$3,W:W) -> 0 | AO4: =SUMIF($N:$N,AO$3,W:W) -> 0 | AP4: =SUMIF($N:$N,AP$3,W:W) -> 0 | AQ4: =SUMIF($N:$N,AQ$3,W:W) -> 0 | AS4: 1 | AT4: Jan | AU4: =SUMIF($L:$L,$AS4,$W:$W) -> #N/A | AW4: =IFERROR(AU4/AV4,#N/A) -> #N/A | AX4: 0.0048 | AY4: =IF(AV20="",SUMIF(L:L,$AS4,W:W)/$AV4,AV20) -> 0.0082 | AZ4: =IF(AW20="",SUMIF(L:L,$AS4,X:X)/$AV4,AW20) -> 0.0002 | BA4: =AY4+AZ4 -> 0.0084
B5: =TEXT(WEEKDAY(C5),"ddd") -> sáb | C5: =O5 -> 46025 | D5: =IFERROR(SUMIF(O:O,C5,W:W),#N/A) -> 1388.1498 | E5: =IFERROR(SUMIF(O:O,C5,Y:Y),#N/A) -> 0 | F5: =IFERROR(D5/E5,#N/A) -> #N/A | G5: 0.0035 | H5: =IF(E5=0,#N/A,IFERROR(SUMIF(O:O,C5,W:W),#N/A)/E5) -> #N/A | I5: =IF(E5=0,#N/A,IFERROR(SUMIF(O:O,C5,X:X),#N/A)/E5) -> #N/A | J5: =SUM(H5:I5) -> #N/A | L5: =MONTH(O5) -> 1 | M5: =YEAR(O5) -> 2026 | N5: =WEEKNUM(O5) -> 1 | O5: 46025 | P5: =TEXT(WEEKDAY(O5),"ddd") -> sáb | Q5: =SUMIF('SPR - QTD'!$A:$A,DADOS_GRAF!O5,'SPR - QTD'!$H:$H) -> 64 | R5: =SUMIF('SCI - QTD'!$A:$A,DADOS_GRAF!O5,'SCI - QTD'!$H:$H) -> 0 | S5: =SUM(Q5:R5) -> 64 | U5: 4600 | V5: =(S5/T5)*10^6 -> #DIV/0! | W5: =SUMIF('SPR - QTD'!$A:$A,DADOS_GRAF!O5,'SPR - QTD'!$M:$M) -> 1388.1498 | X5: =SUMIF('SCI - QTD'!$A:$A,DADOS_GRAF!O5,'SCI - QTD'!$L:$L) -> 0 | AH5: SCI | AK5: =SUMIF(M:M,AK3,X:X) -> 0 | AM5: SCI | AN5: =SUMIF($N:$N,AN$3,X:X) -> 0 | AO5: =SUMIF($N:$N,AO$3,$X:$X) -> 0 | AP5: =SUMIF($N:$N,AP$3,$X:$X) -> 0 | AQ5: =SUMIF($N:$N,AQ$3,$X:$X) -> 0 | AS5: =AS4+1 -> 2 | AT5: Fev | AU5: =SUMIF($L:$L,$AS5,$W:$W) -> 0 | AW5: =IFERROR(AU5/AV5,#N/A) -> #N/A | AX5: 0.0048 | AY5: =IF(AV21="",SUMIF(L:L,$AS5,W:W)/$AV5,AV21) -> 0.0085 | AZ5: =IF(AW21="",SUMIF(L:L,$AS5,X:X)/$AV5,AW21) -> 0.0008 | BA5: =AY5+AZ5 -> 0.0093
B6: =TEXT(WEEKDAY(C6),"ddd") -> dom | C6: =O6 -> 46026 | D6: =IFERROR(SUMIF(O:O,C6,W:W),#N/A) -> 0 | E6: =IFERROR(SUMIF(O:O,C6,Y:Y),#N/A) -> 0 | F6: =IFERROR(D6/E6,#N/A) -> #N/A | G6: 0.0035 | H6: =IF(E6=0,#N/A,IFERROR(SUMIF(O:O,C6,W:W),#N/A)/E6) -> #N/A | I6: =IF(E6=0,#N/A,IFERROR(SUMIF(O:O,C6,X:X),#N/A)/E6) -> #N/A | J6: =SUM(H6:I6) -> #N/A | L6: =MONTH(O6) -> 1 | M6: =YEAR(O6) -> 2026 | N6: =WEEKNUM(O6) -> 2 | O6: 46026 | P6: =TEXT(WEEKDAY(O6),"ddd") -> dom | Q6: =SUMIF('SPR - QTD'!$A:$A,DADOS_GRAF!O6,'SPR - QTD'!$H:$H) -> 0 | R6: =SUMIF('SCI - QTD'!$A:$A,DADOS_GRAF!O6,'SCI - QTD'!$H:$H) -> 0 | S6: =SUM(Q6:R6) -> 0 | U6: 4600 | V6: =(S6/T6)*10^6 -> #DIV/0! | W6: =SUMIF('SPR - QTD'!$A:$A,DADOS_GRAF!O6,'SPR - QTD'!$M:$M) -> 0 | X6: =SUMIF('SCI - QTD'!$A:$A,DADOS_GRAF!O6,'SCI - QTD'!$L:$L) -> 0 | AH6: Fat | AK6: =SUMIF(M:M,AK3,Y:Y)+19384943.75+17112096.0589364+21975693.13 -> 58472733 | AM6: Fat (R$) | AN6: =SUMIF($N:$N,AN$3,Y:Y) -> 0 | AO6: =SUMIF($N:$N,AO$3,Y:Y) -> 0 | AP6: =SUMIF($N:$N,AP$3,Y:Y) -> 0 | AQ6: =SUMIF($N:$N,AQ$3,Y:Y) -> 0 | AS6: =AS5+1 -> 3 | AT6: Mar | AU6: =SUMIF($L:$L,$AS6,$W:$W) -> 0 | AW6: 0.0082 | AX6: 0.0048 | AY6: =IF(AV22="",SUMIF(L:L,$AS6,W:W)/$AV6,AV22) -> 0.0069 | AZ6: =IF(AW22="",SUMIF(L:L,$AS6,X:X)/$AV6,AW22) -> 0.0005 | BA6: =AY6+AZ6 -> 0.0074
B7: =TEXT(WEEKDAY(C7),"ddd") -> seg | C7: =O7 -> 46027 | D7: =IFERROR(SUMIF(O:O,C7,W:W),#N/A) -> 2401.7793 | E7: =IFERROR(SUMIF(O:O,C7,Y:Y),#N/A) -> 480505.16 | F7: =IFERROR(D7/E7,#N/A) -> 0.0049984464 | G7: 0.0035 | H7: =IF(E7=0,#N/A,IFERROR(SUMIF(O:O,C7,W:W),#N/A)/E7) -> 0.0049984464 | I7: =IF(E7=0,#N/A,IFERROR(SUMIF(O:O,C7,X:X),#N/A)/E7) -> 0 | J7: =SUM(H7:I7) -> 0.0049984464 | L7: =MONTH(O7) -> 1 | M7: =YEAR(O7) -> 2026 | N7: =WEEKNUM(O7) -> 2 | O7: 46027 | P7: =TEXT(WEEKDAY(O7),"ddd") -> seg | Q7: =SUMIF('SPR - QTD'!$A:$A,DADOS_GRAF!O7,'SPR - QTD'!$H:$H) -> 329 | R7: =SUMIF('SCI - QTD'!$A:$A,DADOS_GRAF!O7,'SCI - QTD'!$H:$H) -> 248.5 | S7: =SUM(Q7:R7) -> 577.5 | T7: 25253 | U7: 4600 | V7: =(S7/T7)*10^6 -> 22868.57 | W7: =SUMIF('SPR - QTD'!$A:$A,DADOS_GRAF!O7,'SPR - QTD'!$M:$M) -> 2401.7793 | X7: =SUMIF('SCI - QTD'!$A:$A,DADOS_GRAF!O7,'SCI - QTD'!$L:$L) -> 0 | Y7: =AE7-AE4 -> 480505.16 | Z7: =IFERROR((W7+X7)/Y7,#N/A) -> 0.0049984464 | AA7: =IF(Y7="",#N/A,W7/Y7) -> 0.0049984464 | AB7: =IF(Y7="",#N/A,X7/Y7) -> 0 | AC7: X | AE7: 480505.16 | AH7: SPR | AI7: 0.0051 | AJ7: 0.0051 | AK7: =AK4/AK6 -> 0 | AM7: Total | AN7: =IFERROR(AN4/AN6,#N/A) -> #N/A | AO7: =IFERROR(AO4/AO6,#N/A) -> #N/A | AP7: =IFERROR(AP4/AP6,#N/A) -> #N/A | AQ7: =IFERROR(AQ4/AQ6,#N/A) -> #N/A | AS7: =AS6+1 -> 4 | AT7: Abr | AU7: =ABS(SUMIF($L:$L,$AS7,$W:$W))+ABS(SUMIF($L:$L,$AS7,$X:$X)) -> 0 | AW7: =IFERROR(AU7/AV7,#N/A) -> #N/A | AX7: 0.0048 | AY7: =IF(AV23="",SUMIF(L:L,$AS7,W:W)/$AV7,AV23) -> 0.0037442268 | AZ7: =IF(AW23="",SUMIF(L:L,$AS7,X:X)/$AV7,AW23) -> 0.00023653866 | BA7: =AY7+AZ7 -> 0.0039807654
B8: =TEXT(WEEKDAY(C8),"ddd") -> ter | C8: =O8 -> 46028 | D8: =IFERROR(SUMIF(O:O,C8,W:W),#N/A) -> 3268.8147 | E8: =IFERROR(SUMIF(O:O,C8,Y:Y),#N/A) -> 467023.42 | F8: =IFERROR(D8/E8,#N/A) -> 0.0069992523 | G8: 0.0035 | H8: =IF(E8=0,#N/A,IFERROR(SUMIF(O:O,C8,W:W),#N/A)/E8) -> 0.0069992523 | I8: =IF(E8=0,#N/A,IFERROR(SUMIF(O:O,C8,X:X),#N/A)/E8) -> 0 | J8: =SUM(H8:I8) -> 0.0069992523 | L8: =MONTH(O8) -> 1 | M8: =YEAR(O8) -> 2026 | N8: =WEEKNUM(O8) -> 2 | O8: 46028 | P8: =TEXT(WEEKDAY(O8),"ddd") -> ter | Q8: =SUMIF('SPR - QTD'!$A:$A,DADOS_GRAF!O8,'SPR - QTD'!$H:$H) -> 308 | R8: =SUMIF('SCI - QTD'!$A:$A,DADOS_GRAF!O8,'SCI - QTD'!$H:$H) -> 243 | S8: =SUM(Q8:R8) -> 551 | T8: 63514 | U8: 4600 | V8: =(S8/T8)*10^6 -> 8675.2527 | W8: =SUMIF('SPR - QTD'!$A:$A,DADOS_GRAF!O8,'SPR - QTD'!$M:$M) -> 3268.8147 | X8: =SUMIF('SCI - QTD'!$A:$A,DADOS_GRAF!O8,'SCI - QTD'!$L:$L) -> 0 | Y8: =AE8-AE7 -> 467023.42 | Z8: =IFERROR((W8+X8)/Y8,#N/A) -> 0.0069992523 | AA8: =IF(Y8="",#N/A,W8/Y8) -> 0.0069992523 | AB8: =IF(Y8="",#N/A,X8/Y8) -> 0 | AC8: X | AE8: 947528.58 | AH8: SCI | AI8: 0.0023 | AJ8: 0.0014 | AK8: =AK5/AK6 -> 0 | AM8: SPR | AN8: =AN4/AN6 -> #DIV/0! | AO8: =AO4/AO6 -> #DIV/0! | AP8: =AP4/AP6 -> #DIV/0! | AQ8: =AQ4/AQ6 -> #DIV/0! | AS8: =AS7+1 -> 5 | AT8: Mai | AU8: =SUMIF($L:$L,$AS8,$W:$W) -> 0 | AW8: =IFERROR(AU8/AV8,#N/A) -> #N/A | AX8: 0.0048 | AY8: =IF(AV24="",SUMIF(L:L,$AS8,W:W)/$AV8,AV24) -> 0.0029463182 | AZ8: =IF(AW24="",SUMIF(L:L,$AS8,X:X)/$AV8,AW24) -> 0.00024788385 | BA8: =AY8+AZ8 -> 0.0031942021
B9: =TEXT(WEEKDAY(C9),"ddd") -> qua | C9: =O9 -> 46029 | D9: =IFERROR(SUMIF(O:O,C9,W:W),#N/A) -> 2147.0155 | E9: =IFERROR(SUMIF(O:O,C9,Y:Y),#N/A) -> 529521.11 | F9: =IFERROR(D9/E9,#N/A) -> 0.0040546362 | G9: 0.0035 | H9: =IF(E9=0,#N/A,IFERROR(SUMIF(O:O,C9,W:W),#N/A)/E9) -> 0.0040546362 | I9: =IF(E9=0,#N/A,IFERROR(SUMIF(O:O,C9,X:X),#N/A)/E9) -> 0 | J9: =SUM(H9:I9) -> 0.0040546362 | L9: =MONTH(O9) -> 1 | M9: =YEAR(O9) -> 2026 | N9: =WEEKNUM(O9) -> 2 | O9: 46029 | P9: =TEXT(WEEKDAY(O9),"ddd") -> qua | Q9: =SUMIF('SPR - QTD'!$A:$A,DADOS_GRAF!O9,'SPR - QTD'!$H:$H) -> 389 | R9: =SUMIF('SCI - QTD'!$A:$A,DADOS_GRAF!O9,'SCI - QTD'!$H:$H) -> 201.5 | S9: =SUM(Q9:R9) -> 590.5 | T9: 276112 | U9: 4600 | V9: =(S9/T9)*10^6 -> 2138.6249 | W9: =SUMIF('SPR - QTD'!$A:$A,DADOS_GRAF!O9,'SPR - QTD'!$M:$M) -> 2147.0155 | X9: =SUMIF('SCI - QTD'!$A:$A,DADOS_GRAF!O9,'SCI - QTD'!$L:$L) -> 0 | Y9: =AE9-AE8 -> 529521.11 | Z9: =IFERROR((W9+X9)/Y9,#N/A) -> 0.0040546362 | AA9: =IF(Y9="",#N/A,W9/Y9) -> 0.0040546362 | AB9: =IF(Y9="",#N/A,X9/Y9) -> 0 | AC9: X | AE9: 1477049.7 | AH9: Total | AI9: =SUM(AI7:AI8) -> 0.0074 | AJ9: =SUM(AJ7:AJ8) -> 0.0065 | AK9: =SUM(AK7:AK8) -> 0 | AM9: SCI | AN9: =AN5/AN6 -> #DIV/0! | AO9: =AO5/AO6 -> #DIV/0! | AP9: =AP5/AP6 -> #DIV/0! | AQ9: =AQ5/AQ6 -> #DIV/0! | AS9: =AS8+1 -> 6 | AT9: Jun | AU9: =SUMIF($L:$L,$AS9,$W:$W) -> 0 | AW9: =IFERROR(AU9/AV9,#N/A) -> #N/A | AX9: 0.0048 | AY9: =IF(AV25="",SUMIF(L:L,$AS9,W:W)/$AV9,AV25) -> #DIV/0! | AZ9: =IF(AW25="",SUMIF(L:L,$AS9,X:X)/$AV9,AW25) -> #DIV/0! | BA9: =AY9+AZ9 -> #DIV/0!
B10: =TEXT(WEEKDAY(C10),"ddd") -> qui | C10: =O10 -> 46030 | D10: =IFERROR(SUMIF(O:O,C10,W:W),#N/A) -> 2154.4435 | E10: =IFERROR(SUMIF(O:O,C10,Y:Y),#N/A) -> 665487.78 | F10: =IFERROR(D10/E10,#N/A) -> 0.0032373901 | G10: 0.0035 | H10: =IF(E10=0,#N/A,IFERROR(SUMIF(O:O,C10,W:W),#N/A)/E10) -> 0.0032373901 | I10: =IF(E10=0,#N/A,IFERROR(SUMIF(O:O,C10,X:X),#N/A)/E10) -> 0 | J10: =SUM(H10:I10) -> 0.0032373901 | L10: =MONTH(O10) -> 1 | M10: =YEAR(O10) -> 2026 | N10: =WEEKNUM(O10) -> 2 | O10: 46030 | P10: =TEXT(WEEKDAY(O10),"ddd") -> qui | Q10: =SUMIF('SPR - QTD'!$A:$A,DADOS_GRAF!O10,'SPR - QTD'!$H:$H) -> 268 | R10: =SUMIF('SCI - QTD'!$A:$A,DADOS_GRAF!O10,'SCI - QTD'!$H:$H) -> 205 | S10: =SUM(Q10:R10) -> 473 | T10: 197504 | U10: 4600 | V10: =(S10/T10)*10^6 -> 2394.8882 | W10: =SUMIF('SPR - QTD'!$A:$A,DADOS_GRAF!O10,'SPR - QTD'!$M:$M) -> 2154.4435 | X10: =SUMIF('SCI - QTD'!$A:$A,DADOS_GRAF!O10,'SCI - QTD'!$L:$L) -> 0 | Y10: =AE10-AE9 -> 665487.78 | Z10: =IFERROR((W10+X10)/Y10,#N/A) -> 0.0032373901 | AA10: =IF(Y10="",#N/A,W10/Y10) -> 0.0032373901 | AB10: =IF(Y10="",#N/A,X10/Y10) -> 0 | AC10: X | AE10: 2142537.5 | AH10: Obj | AI10: 0.0048 | AJ10: 0.0048 | AK10: 0.0048 | AM10: Total | AN10: =SUM(AN8:AN9) -> #DIV/0! | AO10: =SUM(AO8:AO9) -> #DIV/0! | AP10: =SUM(AP8:AP9) -> #DIV/0! | AQ10: =SUM(AQ8:AQ9) -> #DIV/0! | AS10: =AS9+1 -> 7 | AT10: Jul | AU10: =SUMIF($L:$L,$AS10,$W:$W) -> 0 | AW10: =IFERROR(AU10/AV10,#N/A) -> #N/A | AX10: 0.0048
B11: =TEXT(WEEKDAY(C11),"ddd") -> sex | C11: =O11 -> 46031 | D11: =IFERROR(SUMIF(O:O,C11,W:W),#N/A) -> 4601.8529 | E11: =IFERROR(SUMIF(O:O,C11,Y:Y),#N/A) -> 827610.04 | F11: =IFERROR(D11/E11,#N/A) -> 0.0055604121 | G11: 0.0035 | H11: =IF(E11=0,#N/A,IFERROR(SUMIF(O:O,C11,W:W),#N/A)/E11) -> 0.0055604121 | I11: =IF(E11=0,#N/A,IFERROR(SUMIF(O:O,C11,X:X),#N/A)/E11) -> 0 | J11: =SUM(H11:I11) -> 0.0055604121 | L11: =MONTH(O11) -> 1 | M11: =YEAR(O11) -> 2026 | N11: =WEEKNUM(O11) -> 2 | O11: 46031 | P11: =TEXT(WEEKDAY(O11),"ddd") -> sex | Q11: =SUMIF('SPR - QTD'!$A:$A,DADOS_GRAF!O11,'SPR - QTD'!$H:$H) -> 506 | R11: =SUMIF('SCI - QTD'!$A:$A,DADOS_GRAF!O11,'SCI - QTD'!$H:$H) -> 105 | S11: =SUM(Q11:R11) -> 611 | T11: 167915 | U11: 4600 | V11: =(S11/T11)*10^6 -> 3638.7458 | W11: =SUMIF('SPR - QTD'!$A:$A,DADOS_GRAF!O11,'SPR - QTD'!$M:$M) -> 4601.8529 | X11: =SUMIF('SCI - QTD'!$A:$A,DADOS_GRAF!O11,'SCI - QTD'!$L:$L) -> 0 | Y11: =AE11-AE10 -> 827610.04 | Z11: =IFERROR((W11+X11)/Y11,#N/A) -> 0.0055604121 | AA11: =IF(Y11="",#N/A,W11/Y11) -> 0.0055604121 | AB11: =IF(Y11="",#N/A,X11/Y11) -> 0 | AC11: X | AE11: 2970147.5 | AM11: Obj | AN11: 0.0048 | AO11: 0.0048 | AP11: 0.0048 | AQ11: 0.0048 | AS11: =AS10+1 -> 8 | AT11: Ago | AU11: =SUMIF($L:$L,$AS11,$W:$W) -> 0 | AW11: =IFERROR(AU11/AV11,#N/A) -> #N/A | AX11: 0.0048
B12: =TEXT(WEEKDAY(C12),"ddd") -> sáb | C12: =O12 -> 46032 | D12: =IFERROR(SUMIF(O:O,C12,W:W),#N/A) -> 14.964262 | E12: =IFERROR(SUMIF(O:O,C12,Y:Y),#N/A) -> 0 | F12: =IFERROR(D12/E12,#N/A) -> #N/A | G12: 0.0035 | H12: =IF(E12=0,#N/A,IFERROR(SUMIF(O:O,C12,W:W),#N/A)/E12) -> #N/A | I12: =IF(E12=0,#N/A,IFERROR(SUMIF(O:O,C12,X:X),#N/A)/E12) -> #N/A | J12: =SUM(H12:I12) -> #N/A | L12: =MONTH(O12) -> 1 | M12: =YEAR(O12) -> 2026 | N12: =WEEKNUM(O12) -> 2 | O12: 46032 | P12: =TEXT(WEEKDAY(O12),"ddd") -> sáb | Q12: =SUMIF('SPR - QTD'!$A:$A,DADOS_GRAF!O12,'SPR - QTD'!$H:$H) -> 2 | R12: =SUMIF('SCI - QTD'!$A:$A,DADOS_GRAF!O12,'SCI - QTD'!$H:$H) -> 0 | S12: =SUM(Q12:R12) -> 2 | U12: 4600 | V12: =(S12/T12)*10^6 -> #DIV/0! | W12: =SUMIF('SPR - QTD'!$A:$A,DADOS_GRAF!O12,'SPR - QTD'!$M:$M) -> 14.964262 | X12: =SUMIF('SCI - QTD'!$A:$A,DADOS_GRAF!O12,'SCI - QTD'!$L:$L) -> 0 | AS12: =AS11+1 -> 9 | AT12: Set | AU12: =SUMIF($L:$L,$AS12,$W:$W) -> 0 | AW12: =IFERROR(AU12/AV12,#N/A) -> #N/A | AX12: 0.0048
B13: =TEXT(WEEKDAY(C13),"ddd") -> dom | C13: =O13 -> 46033 | D13: =IFERROR(SUMIF(O:O,C13,W:W),#N/A) -> 0 | E13: =IFERROR(SUMIF(O:O,C13,Y:Y),#N/A) -> 0 | F13: =IFERROR(D13/E13,#N/A) -> #N/A | G13: 0.0035 | H13: =IF(E13=0,#N/A,IFERROR(SUMIF(O:O,C13,W:W),#N/A)/E13) -> #N/A | I13: =IF(E13=0,#N/A,IFERROR(SUMIF(O:O,C13,X:X),#N/A)/E13) -> #N/A | J13: =SUM(H13:I13) -> #N/A | L13: =MONTH(O13) -> 1 | M13: =YEAR(O13) -> 2026 | N13: =WEEKNUM(O13) -> 3 | O13: 46033 | P13: =TEXT(WEEKDAY(O13),"ddd") -> dom | Q13: =SUMIF('SPR - QTD'!$A:$A,DADOS_GRAF!O13,'SPR - QTD'!$H:$H) -> 0 | R13: =SUMIF('SCI - QTD'!$A:$A,DADOS_GRAF!O13,'SCI - QTD'!$H:$H) -> 0 | S13: =SUM(Q13:R13) -> 0 | U13: 4600 | V13: =(S13/T13)*10^6 -> #DIV/0! | W13: =SUMIF('SPR - QTD'!$A:$A,DADOS_GRAF!O13,'SPR - QTD'!$M:$M) -> 0 | X13: =SUMIF('SCI - QTD'!$A:$A,DADOS_GRAF!O13,'SCI - QTD'!$L:$L) -> 0 | AS13: =AS12+1 -> 10 | AT13: Out | AU13: =SUMIF($L:$L,$AS13,$W:$W) -> 0 | AW13: =IFERROR(AU13/AV13,#N/A) -> #N/A | AX13: 0.0048
B14: =TEXT(WEEKDAY(C14),"ddd") -> seg | C14: =O14 -> 46034 | D14: =IFERROR(SUMIF(O:O,C14,W:W),#N/A) -> 26000 | E14: =IFERROR(SUMIF(O:O,C14,Y:Y),#N/A) -> 597891.73 | F14: =IFERROR(D14/E14,#N/A) -> 0.043486134 | G14: 0.0035 | H14: =IF(E14=0,#N/A,IFERROR(SUMIF(O:O,C14,W:W),#N/A)/E14) -> 0.043486134 | I14: =IF(E14=0,#N/A,IFERROR(SUMIF(O:O,C14,X:X),#N/A)/E14) -> 0 | J14: =SUM(H14:I14) -> 0.043486134 | L14: =MONTH(O14) -> 1 | M14: =YEAR(O14) -> 2026 | N14: =WEEKNUM(O14) -> 3 | O14: 46034 | P14: =TEXT(WEEKDAY(O14),"ddd") -> seg | Q14: =SUMIF('SPR - QTD'!$A:$A,DADOS_GRAF!O14,'SPR - QTD'!$H:$H) -> 107 | R14: =SUMIF('SCI - QTD'!$A:$A,DADOS_GRAF!O14,'SCI - QTD'!$H:$H) -> 125 | S14: =SUM(Q14:R14) -> 232 | T14: 144269 | U14: 4600 | V14: =(S14/T14)*10^6 -> 1608.1071 | W14: 26000 | X14: =SUMIF('SCI - QTD'!$A:$A,DADOS_GRAF!O14,'SCI - QTD'!$L:$L) -> 0 | Y14: =AE14-AE11 -> 597891.73 | Z14: =IFERROR((W14+X14)/Y14,#N/A) -> 0.043486134 | AA14: =IF(Y14="",#N/A,W14/Y14) -> 0.043486134 | AB14: =IF(Y14="",#N/A,X14/Y14) -> 0 | AC14: X | AE14: 3568039.2 | AG14: 18803636 | AS14: =AS13+1 -> 11 | AT14: Nov | AU14: =SUMIF($L:$L,$AS14,$W:$W) -> 0 | AW14: =IFERROR(AU14/AV14,#N/A) -> #N/A | AX14: 0.0048
B15: =TEXT(WEEKDAY(C15),"ddd") -> ter | C15: =O15 -> 46035 | D15: =IFERROR(SUMIF(O:O,C15,W:W),#N/A) -> 12000 | E15: =IFERROR(SUMIF(O:O,C15,Y:Y),#N/A) -> 1088922.2 | F15: =IFERROR(D15/E15,#N/A) -> 0.011020071 | G15: 0.0035 | H15: =IF(E15=0,#N/A,IFERROR(SUMIF(O:O,C15,W:W),#N/A)/E15) -> 0.011020071 | I15: =IF(E15=0,#N/A,IFERROR(SUMIF(O:O,C15,X:X),#N/A)/E15) -> 0 | J15: =SUM(H15:I15) -> 0.011020071 | L15: =MONTH(O15) -> 1 | M15: =YEAR(O15) -> 2026 | N15: =WEEKNUM(O15) -> 3 | O15: 46035 | P15: =TEXT(WEEKDAY(O15),"ddd") -> ter | Q15: =SUMIF('SPR - QTD'!$A:$A,DADOS_GRAF!O15,'SPR - QTD'!$H:$H) -> 343 | R15: =SUMIF('SCI - QTD'!$A:$A,DADOS_GRAF!O15,'SCI - QTD'!$H:$H) -> 392.3 | S15: =SUM(Q15:R15) -> 735.3 | U15: 4600 | V15: =(S15/T15)*10^6 -> #DIV/0! | W15: 12000 | X15: =SUMIF('SCI - QTD'!$A:$A,DADOS_GRAF!O15,'SCI - QTD'!$L:$L) -> 0 | Y15: =AE15-AE14 -> 1088922.2 | Z15: =IFERROR((W15+X15)/Y15,#N/A) -> 0.011020071 | AA15: =IF(Y15="",#N/A,W15/Y15) -> 0.011020071 | AB15: =IF(Y15="",#N/A,X15/Y15) -> 0 | AC15: X | AE15: 4656961.5 | AS15: =AS14+1 -> 12 | AT15: Dez | AU15: =SUMIF($L:$L,$AS15,$W:$W) -> 0 | AW15: =IFERROR(AU15/AV15,#N/A) -> #N/A | AX15: 0.0048
B16: =TEXT(WEEKDAY(C16),"ddd") -> qua | C16: =O16 -> 46036 | D16: =IFERROR(SUMIF(O:O,C16,W:W),#N/A) -> 23577.688 | E16: =IFERROR(SUMIF(O:O,C16,Y:Y),#N/A) -> 1088922.2 | F16: =IFERROR(D16/E16,#N/A) -> 0.021652316 | G16: 0.0035 | H16: =IF(E16=0,#N/A,IFERROR(SUMIF(O:O,C16,W:W),#N/A)/E16) -> 0.021652316 | I16: =IF(E16=0,#N/A,IFERROR(SUMIF(O:O,C16,X:X),#N/A)/E16) -> 0 | J16: =SUM(H16:I16) -> 0.021652316 | L16: =MONTH(O16) -> 1 | M16: =YEAR(O16) -> 2026 | N16: =WEEKNUM(O16) -> 3 | O16: 46036 | P16: =TEXT(WEEKDAY(O16),"ddd") -> qua | Q16: =SUMIF('SPR - QTD'!$A:$A,DADOS_GRAF!O16,'SPR - QTD'!$H:$H) -> 2781 | R16: =SUMIF('SCI - QTD'!$A:$A,DADOS_GRAF!O16,'SCI - QTD'!$H:$H) -> 318.5 | S16: =SUM(Q16:R16) -> 3099.5 | U16: 4600 | V16: =(S16/T16)*10^6 -> #DIV/0! | W16: =SUMIF('SPR - QTD'!$A:$A,DADOS_GRAF!O16,'SPR - QTD'!$M:$M) -> 23577.688 | X16: =SUMIF('SCI - QTD'!$A:$A,DADOS_GRAF!O16,'SCI - QTD'!$L:$L) -> 0 | Y16: =AE16-AE15 -> 1088922.2 | Z16: =IFERROR((W16+X16)/Y16,#N/A) -> 0.021652316 | AA16: =IF(Y16="",#N/A,W16/Y16) -> 0.021652316 | AB16: =IF(Y16="",#N/A,X16/Y16) -> 0 | AC16: X | AE16: 5745883.7
B17: =TEXT(WEEKDAY(C17),"ddd") -> qui | C17: =O17 -> 46037 | D17: =IFERROR(SUMIF(O:O,C17,W:W),#N/A) -> 2443.3886 | E17: =IFERROR(SUMIF(O:O,C17,Y:Y),#N/A) -> 1242418 | F17: =IFERROR(D17/E17,#N/A) -> 0.0019666397 | G17: 0.0035 | H17: =IF(E17=0,#N/A,IFERROR(SUMIF(O:O,C17,W:W),#N/A)/E17) -> 0.0019666397 | I17: =IF(E17=0,#N/A,IFERROR(SUMIF(O:O,C17,X:X),#N/A)/E17) -> 0 | J17: =SUM(H17:I17) -> 0.0019666397 | L17: =MONTH(O17) -> 1 | M17: =YEAR(O17) -> 2026 | N17: =WEEKNUM(O17) -> 3 | O17: 46037 | P17: =TEXT(WEEKDAY(O17),"ddd") -> qui | Q17: =SUMIF('SPR - QTD'!$A:$A,DADOS_GRAF!O17,'SPR - QTD'!$H:$H) -> 467 | R17: =SUMIF('SCI - QTD'!$A:$A,DADOS_GRAF!O17,'SCI - QTD'!$H:$H) -> 209.5 | S17: =SUM(Q17:R17) -> 676.5 | U17: 4600 | V17: =(S17/T17)*10^6 -> #DIV/0! | W17: =SUMIF('SPR - QTD'!$A:$A,DADOS_GRAF!O17,'SPR - QTD'!$M:$M) -> 2443.3886 | X17: =SUMIF('SCI - QTD'!$A:$A,DADOS_GRAF!O17,'SCI - QTD'!$L:$L) -> 0 | Y17: =AE17-AE16 -> 1242418 | Z17: =IFERROR((W17+X17)/Y17,#N/A) -> 0.0019666397 | AA17: =IF(Y17="",#N/A,W17/Y17) -> 0.0019666397 | AB17: =IF(Y17="",#N/A,X17/Y17) -> 0 | AC17: X | AE17: =AE16+$AG$30 -> 6988301.7 | AV17: Valor Fechamento (Controladoria)
B18: =TEXT(WEEKDAY(C18),"ddd") -> sex | C18: =O18 -> 46038 | D18: =IFERROR(SUMIF(O:O,C18,W:W),#N/A) -> 2244.1407 | E18: =IFERROR(SUMIF(O:O,C18,Y:Y),#N/A) -> 1242418 | F18: =IFERROR(D18/E18,#N/A) -> 0.0018062686 | G18: 0.0035 | H18: =IF(E18=0,#N/A,IFERROR(SUMIF(O:O,C18,W:W),#N/A)/E18) -> 0.0018062686 | I18: =IF(E18=0,#N/A,IFERROR(SUMIF(O:O,C18,X:X),#N/A)/E18) -> 0 | J18: =SUM(H18:I18) -> 0.0018062686 | L18: =MONTH(O18) -> 1 | M18: =YEAR(O18) -> 2026 | N18: =WEEKNUM(O18) -> 3 | O18: 46038 | P18: =TEXT(WEEKDAY(O18),"ddd") -> sex | Q18: =SUMIF('SPR - QTD'!$A:$A,DADOS_GRAF!O18,'SPR - QTD'!$H:$H) -> 513 | R18: =SUMIF('SCI - QTD'!$A:$A,DADOS_GRAF!O18,'SCI - QTD'!$H:$H) -> 264.2 | S18: =SUM(Q18:R18) -> 777.2 | U18: 4600 | V18: =(S18/T18)*10^6 -> #DIV/0! | W18: =SUMIF('SPR - QTD'!$A:$A,DADOS_GRAF!O18,'SPR - QTD'!$M:$M) -> 2244.1407 | X18: =SUMIF('SCI - QTD'!$A:$A,DADOS_GRAF!O18,'SCI - QTD'!$L:$L) -> 0 | Y18: =AE18-AE17 -> 1242418 | Z18: =IFERROR((W18+X18)/Y18,#N/A) -> 0.0018062686 | AA18: =IF(Y18="",#N/A,W18/Y18) -> 0.0018062686 | AB18: =IF(Y18="",#N/A,X18/Y18) -> 0 | AC18: X | AE18: =AE17+$AG$30 -> 8230719.8 | AK18: Projeção | AQ18: QTD | BA18: Ano
B19: =TEXT(WEEKDAY(C19),"ddd") -> sáb | C19: =O19 -> 46039 | D19: =IFERROR(SUMIF(O:O,C19,W:W),#N/A) -> 0 | E19: =IFERROR(SUMIF(O:O,C19,Y:Y),#N/A) -> 0 | F19: =IFERROR(D19/E19,#N/A) -> #N/A | G19: 0.0035 | H19: =IF(E19=0,#N/A,IFERROR(SUMIF(O:O,C19,W:W),#N/A)/E19) -> #N/A | I19: =IF(E19=0,#N/A,IFERROR(SUMIF(O:O,C19,X:X),#N/A)/E19) -> #N/A | J19: =SUM(H19:I19) -> #N/A | L19: =MONTH(O19) -> 1 | M19: =YEAR(O19) -> 2026 | N19: =WEEKNUM(O19) -> 3 | O19: 46039 | P19: =TEXT(WEEKDAY(O19),"ddd") -> sáb | Q19: =SUMIF('SPR - QTD'!$A:$A,DADOS_GRAF!O19,'SPR - QTD'!$H:$H) -> 0 | R19: =SUMIF('SCI - QTD'!$A:$A,DADOS_GRAF!O19,'SCI - QTD'!$H:$H) -> 3.7 | S19: =SUM(Q19:R19) -> 3.7 | U19: 4600 | V19: =(S19/T19)*10^6 -> #DIV/0! | W19: =SUMIF('SPR - QTD'!$A:$A,DADOS_GRAF!O19,'SPR - QTD'!$M:$M) -> 0 | X19: =SUMIF('SCI - QTD'!$A:$A,DADOS_GRAF!O19,'SCI - QTD'!$L:$L) -> 0 | AJ19: WD | AK19: Ref | AL19: Fat | AM19: SPR | AN19: SCI | AO19: Total | AP19: % | AQ19: Produzido | AR19: Ref. | AS19: PPM | AV19: SPR | AW19: SCI | AX19: Total | BA19: 2021 | BB19: 2022 | BC19: 2023
B20: =TEXT(WEEKDAY(C20),"ddd") -> dom | C20: =O20 -> 46040 | D20: =IFERROR(SUMIF(O:O,C20,W:W),#N/A) -> 130.80264 | E20: =IFERROR(SUMIF(O:O,C20,Y:Y),#N/A) -> 0 | F20: =IFERROR(D20/E20,#N/A) -> #N/A | G20: 0.0035 | H20: =IF(E20=0,#N/A,IFERROR(SUMIF(O:O,C20,W:W),#N/A)/E20) -> #N/A | I20: =IF(E20=0,#N/A,IFERROR(SUMIF(O:O,C20,X:X),#N/A)/E20) -> #N/A | J20: =SUM(H20:I20) -> #N/A | L20: =MONTH(O20) -> 1 | M20: =YEAR(O20) -> 2026 | N20: =WEEKNUM(O20) -> 4 | O20: 46040 | P20: =TEXT(WEEKDAY(O20),"ddd") -> dom | Q20: =SUMIF('SPR - QTD'!$A:$A,DADOS_GRAF!O20,'SPR - QTD'!$H:$H) -> 4 | R20: =SUMIF('SCI - QTD'!$A:$A,DADOS_GRAF!O20,'SCI - QTD'!$H:$H) -> 0 | S20: =SUM(Q20:R20) -> 4 | U20: 4600 | V20: =(S20/T20)*10^6 -> #DIV/0! | W20: =SUMIF('SPR - QTD'!$A:$A,DADOS_GRAF!O20,'SPR - QTD'!$M:$M) -> 130.80264 | X20: =SUMIF('SCI - QTD'!$A:$A,DADOS_GRAF!O20,'SCI - QTD'!$L:$L) -> 0 | AH20: 1 | AI20: Jan | AJ20: 22 | AM20: =SUMIF(L:L,$AS4,W:W)/$AV4 -> #N/A | AN20: =SUMIF(L:L,$AS4,X:X)/$AV4 -> #DIV/0! | AO20: 0.0084 | AP20: =AO20 -> 0.0084 | AQ20: 1510581 | AR20: =16508+520 -> 17028 | AS20: =AR20/(AQ20+AR20)*10^6 -> 11146.831 | AT20: 1 | AU20: Jan | AV20: 0.0082 | AW20: 0.0002 | AX20: =SUM(AV20:AW20) -> 0.0084
B21: =TEXT(WEEKDAY(C21),"ddd") -> seg | C21: =O21 -> 46041 | D21: =IFERROR(SUMIF(O:O,C21,W:W),#N/A) -> 2203.0616 | E21: =IFERROR(SUMIF(O:O,C21,Y:Y),#N/A) -> 1242418 | F21: =IFERROR(D21/E21,#N/A) -> 0.0017732048 | G21: 0.0035 | H21: =IF(E21=0,#N/A,IFERROR(SUMIF(O:O,C21,W:W),#N/A)/E21) -> 0.0017732048 | I21: =IF(E21=0,#N/A,IFERROR(SUMIF(O:O,C21,X:X),#N/A)/E21) -> 0 | J21: =SUM(H21:I21) -> 0.0017732048 | L21: =MONTH(O21) -> 1 | M21: =YEAR(O21) -> 2026 | N21: =WEEKNUM(O21) -> 4 | O21: 46041 | P21: =TEXT(WEEKDAY(O21),"ddd") -> seg | Q21: =SUMIF('SPR - QTD'!$A:$A,DADOS_GRAF!O21,'SPR - QTD'!$H:$H) -> 251 | R21: =SUMIF('SCI - QTD'!$A:$A,DADOS_GRAF!O21,'SCI - QTD'!$H:$H) -> 274 | S21: =SUM(Q21:R21) -> 525 | U21: 4600 | V21: =(S21/T21)*10^6 -> #DIV/0! | W21: =SUMIF('SPR - QTD'!$A:$A,DADOS_GRAF!O21,'SPR - QTD'!$M:$M) -> 2203.0616 | X21: =SUMIF('SCI - QTD'!$A:$A,DADOS_GRAF!O21,'SCI - QTD'!$L:$L) -> 0 | Y21: =AE21-AE18 -> 1242418 | Z21: =IFERROR((W21+X21)/Y21,#N/A) -> 0.0017732048 | AA21: =IF(Y21="",#N/A,W21/Y21) -> 0.0017732048 | AB21: =IF(Y21="",#N/A,X21/Y21) -> 0 | AC21: X | AE21: =AE18+$AG$30 -> 9473137.8 | AI21: Fev | AJ21: 20 | AM21: =SUMIF(L:L,$AS5,W:W)/$AV5 -> #DIV/0! | AN21: =SUMIF(L:L,$AS5,X:X)/$AV5 -> #DIV/0! | AO21: 0.0093 | AP21: =AO21 -> 0.0093 | AQ21: 1627116 | AR21: =17433+655 -> 18088 | AS21: =AR21/(AQ21+AR21)*10^6 -> 10994.381 | AT21: =AT20+1 -> 2 | AU21: Fev | AV21: 0.0085 | AW21: 0.0008 | AX21: =SUM(AV21:AW21) -> 0.0093 | AZ21: Ref | BC21: =AK4 -> 0
B22: =TEXT(WEEKDAY(C22),"ddd") -> ter | C22: =O22 -> 46042 | D22: =IFERROR(SUMIF(O:O,C22,W:W),#N/A) -> 3561.8532 | E22: =IFERROR(SUMIF(O:O,C22,Y:Y),#N/A) -> 1242418 | F22: =IFERROR(D22/E22,#N/A) -> 0.0028668717 | G22: 0.0035 | H22: =IF(E22=0,#N/A,IFERROR(SUMIF(O:O,C22,W:W),#N/A)/E22) -> 0.0028668717 | I22: =IF(E22=0,#N/A,IFERROR(SUMIF(O:O,C22,X:X),#N/A)/E22) -> 0 | J22: =SUM(H22:I22) -> 0.0028668717 | L22: =MONTH(O22) -> 1 | M22: =YEAR(O22) -> 2026 | N22: =WEEKNUM(O22) -> 4 | O22: 46042 | P22: =TEXT(WEEKDAY(O22),"ddd") -> ter | Q22: =SUMIF('SPR - QTD'!$A:$A,DADOS_GRAF!O22,'SPR - QTD'!$H:$H) -> 390 | R22: =SUMIF('SCI - QTD'!$A:$A,DADOS_GRAF!O22,'SCI - QTD'!$H:$H) -> 386.5 | S22: =SUM(Q22:R22) -> 776.5 | U22: 4600 | V22: =(S22/T22)*10^6 -> #DIV/0! | W22: =SUMIF('SPR - QTD'!$A:$A,DADOS_GRAF!O22,'SPR - QTD'!$M:$M) -> 3561.8532 | X22: =SUMIF('SCI - QTD'!$A:$A,DADOS_GRAF!O22,'SCI - QTD'!$L:$L) -> 0 | Y22: =AE22-AE21 -> 1242418 | Z22: =IFERROR((W22+X22)/Y22,#N/A) -> 0.0028668717 | AA22: =IF(Y22="",#N/A,W22/Y22) -> 0.0028668717 | AB22: =IF(Y22="",#N/A,X22/Y22) -> 0 | AC22: X | AE22: =AE21+$AG$30 -> 10715556 | AH22: =AH21+1 -> 1 | AI22: Mar | AJ22: 23 | AM22: =SUMIF(L:L,$AS6,W:W)/$AV6 -> #DIV/0! | AN22: =SUMIF(L:L,$AS6,X:X)/$AV6 -> #DIV/0! | AO22: 0.0074 | AP22: =AO22 -> 0.0074 | AQ22: 2347220 | AR22: =19528+3708 -> 23236 | AS22: =AR22/(AQ22+AR22)*10^6 -> 9802.3334 | AT22: =AT21+1 -> 3 | AU22: Mar | AV22: 0.0069 | AW22: 0.0005 | AX22: =SUM(AV22:AW22) -> 0.0074 | AZ22: Prod | BC22: =12775539+AK4 -> 12775539
B23: =TEXT(WEEKDAY(C23),"ddd") -> qua | C23: =O23 -> 46043 | D23: =IFERROR(SUMIF(O:O,C23,W:W),#N/A) -> #N/A | E23: =IFERROR(SUMIF(O:O,C23,Y:Y),#N/A) -> 1242418 | F23: =IFERROR(D23/E23,#N/A) -> #N/A | G23: 0.0035 | H23: =IF(E23=0,#N/A,IFERROR(SUMIF(O:O,C23,W:W),#N/A)/E23) -> #N/A | I23: =IF(E23=0,#N/A,IFERROR(SUMIF(O:O,C23,X:X),#N/A)/E23) -> 0 | J23: =SUM(H23:I23) -> #N/A | L23: =MONTH(O23) -> 1 | M23: =YEAR(O23) -> 2026 | N23: =WEEKNUM(O23) -> 4 | O23: 46043 | P23: =TEXT(WEEKDAY(O23),"ddd") -> qua | Q23: =SUMIF('SPR - QTD'!$A:$A,DADOS_GRAF!O23,'SPR - QTD'!$H:$H) -> 311 | R23: =SUMIF('SCI - QTD'!$A:$A,DADOS_GRAF!O23,'SCI - QTD'!$H:$H) -> 415 | S23: =SUM(Q23:R23) -> 726 | U23: 4600 | V23: =(S23/T23)*10^6 -> #DIV/0! | W23: =SUMIF('SPR - QTD'!$A:$A,DADOS_GRAF!O23,'SPR - QTD'!$M:$M) -> #N/A | X23: =SUMIF('SCI - QTD'!$A:$A,DADOS_GRAF!O23,'SCI - QTD'!$L:$L) -> 0 | Y23: =AE23-AE22 -> 1242418 | Z23: =IFERROR((W23+X23)/Y23,#N/A) -> #N/A | AA23: =IF(Y23="",#N/A,W23/Y23) -> #N/A | AB23: =IF(Y23="",#N/A,X23/Y23) -> 0 | AC23: X | AE23: =AE22+$AG$30 -> 11957974 | AH23: =AH22+1 -> 2 | AI23: Abr | AJ23: 18 | AK23: =(AU7/COUNTIFS(AC:AC,"x",L:L,AS7)*AJ23) -> #DIV/0! | AL23: 20107770 | AM23: =SUMIF(L:L,$AS7,W:W)/$AL23 -> 0 | AN23: =SUMIF(L:L,$AS7,X:X)/$AL23 -> 0 | AO23: =AN23+AM23 -> 0 | AP23: =AO23 -> 0 | AQ23: 1787658 | AR23: =SUMIF(#REF!,DADOS_GRAF!AH23,#REF!)+SUMIF('SPR - QTD'!#REF!,DADOS_GRAF!AH23,'SPR - QTD'!#REF!) -> #REF! | AS23: =AR23/(AQ23+AR23)*10^6 -> #REF! | AT23: =AT22+1 -> 4 | AU23: Abr | AV23: 0.0037442268 | AW23: 0.00023653866 | AX23: =SUM(AV23:AW23) -> 0.0039807654
B24: =TEXT(WEEKDAY(C24),"ddd") -> qui | C24: =O24 -> 46044 | D24: =IFERROR(SUMIF(O:O,C24,W:W),#N/A) -> 2695.5664 | E24: =IFERROR(SUMIF(O:O,C24,Y:Y),#N/A) -> 1242418 | F24: =IFERROR(D24/E24,#N/A) -> 0.0021696131 | G24: 0.0035 | H24: =IF(E24=0,#N/A,IFERROR(SUMIF(O:O,C24,W:W),#N/A)/E24) -> 0.0021696131 | I24: =IF(E24=0,#N/A,IFERROR(SUMIF(O:O,C24,X:X),#N/A)/E24) -> 0 | J24: =SUM(H24:I24) -> 0.0021696131 | L24: =MONTH(O24) -> 1 | M24: =YEAR(O24) -> 2026 | N24: =WEEKNUM(O24) -> 4 | O24: 46044 | P24: =TEXT(WEEKDAY(O24),"ddd") -> qui | Q24: =SUMIF('SPR - QTD'!$A:$A,DADOS_GRAF!O24,'SPR - QTD'!$H:$H) -> 754 | R24: =SUMIF('SCI - QTD'!$A:$A,DADOS_GRAF!O24,'SCI - QTD'!$H:$H) -> 253 | S24: =SUM(Q24:R24) -> 1007 | U24: 4600 | V24: =(S24/T24)*10^6 -> #DIV/0! | W24: =SUMIF('SPR - QTD'!$A:$A,DADOS_GRAF!O24,'SPR - QTD'!$M:$M) -> 2695.5664 | X24: =SUMIF('SCI - QTD'!$A:$A,DADOS_GRAF!O24,'SCI - QTD'!$L:$L) -> 0 | Y24: =AE24-AE23 -> 1242418 | Z24: =IFERROR((W24+X24)/Y24,#N/A) -> 0.0021696131 | AA24: =IF(Y24="",#N/A,W24/Y24) -> 0.0021696131 | AB24: =IF(Y24="",#N/A,X24/Y24) -> 0 | AC24: X | AE24: =AE23+$AG$30 -> 13200392 | AH24: =AH23+1 -> 3 | AI24: Mai | AJ24: 22 | AK24: =(AU8/COUNTIFS(AC:AC,"x",L:L,AS8)*AJ24) -> #DIV/0! | AL24: 25364437 | AM24: =SUMIF(L:L,$AS8,W:W)/$AL24 -> 0 | AN24: =SUMIF(L:L,$AS8,X:X)/$AL24 -> 0 | AO24: =AN24+AM24 -> 0 | AP24: =AO24 -> 0 | AQ24: 2054062 | AR24: =SUMIF(#REF!,DADOS_GRAF!AH24,#REF!)+SUMIF('SPR - QTD'!#REF!,DADOS_GRAF!AH24,'SPR - QTD'!#REF!) -> #REF! | AS24: =AR24/(AQ24+AR24)*10^6 -> #REF! | AT24: =AT23+1 -> 5 | AU24: Mai | AV24: 0.0029463182 | AW24: 0.00024788385 | AX24: =SUM(AV24:AW24) -> 0.0031942021
B25: =TEXT(WEEKDAY(C25),"ddd") -> sex | C25: =O25 -> 46045 | D25: =IFERROR(SUMIF(O:O,C25,W:W),#N/A) -> 1827.8823 | E25: =IFERROR(SUMIF(O:O,C25,Y:Y),#N/A) -> 0 | F25: =IFERROR(D25/E25,#N/A) -> #N/A | G25: 0.0035 | H25: =IF(E25=0,#N/A,IFERROR(SUMIF(O:O,C25,W:W),#N/A)/E25) -> #N/A | I25: =IF(E25=0,#N/A,IFERROR(SUMIF(O:O,C25,X:X),#N/A)/E25) -> #N/A | J25: =SUM(H25:I25) -> #N/A | L25: =MONTH(O25) -> 1 | M25: =YEAR(O25) -> 2026 | N25: =WEEKNUM(O25) -> 4 | O25: 46045 | P25: =TEXT(WEEKDAY(O25),"ddd") -> sex | Q25: =SUMIF('SPR - QTD'!$A:$A,DADOS_GRAF!O25,'SPR - QTD'!$H:$H) -> 456 | R25: =SUMIF('SCI - QTD'!$A:$A,DADOS_GRAF!O25,'SCI - QTD'!$H:$H) -> 406.5 | S25: =SUM(Q25:R25) -> 862.5 | U25: 4600 | V25: =(S25/T25)*10^6 -> #DIV/0! | W25: =SUMIF('SPR - QTD'!$A:$A,DADOS_GRAF!O25,'SPR - QTD'!$M:$M) -> 1827.8823 | X25: =SUMIF('SCI - QTD'!$A:$A,DADOS_GRAF!O25,'SCI - QTD'!$L:$L) -> 0 | Z25: =IFERROR((W25+X25)/Y25,#N/A) -> #N/A | AA25: =IF(Y25="",#N/A,W25/Y25) -> #N/A | AB25: =IF(Y25="",#N/A,X25/Y25) -> #N/A | AC25: X | AE25: =AE24+$AG$30 -> 14442810 | AH25: =AH24+1 -> 4 | AI25: Jun | AJ25: 21 | AK25: =(AU9/COUNTIFS(AC:AC,"x",L:L,AS9)*AJ25) -> #DIV/0! | AL25: 18187627 | AM25: =SUMIF(L:L,$AS9,W:W)/$AL25 -> 0 | AN25: =SUMIF(L:L,$AS9,X:X)/$AL25 -> 0 | AO25: =AN25+AM25 -> 0 | AP25: 0.0034 | AQ25: 1668290 | AR25: =SUMIF(#REF!,DADOS_GRAF!AH25,#REF!)+SUMIF('SPR - QTD'!#REF!,DADOS_GRAF!AH25,'SPR - QTD'!#REF!) -> #REF! | AS25: =AR25/(AQ25+AR25)*10^6 -> #REF! | AT25: =AT24+1 -> 6 | AU25: Jun | BA25: 0.005 | BB25: 0.0049 | BC25: =BC21/BC22*10^6 -> 0
B26: =TEXT(WEEKDAY(C26),"ddd") -> sáb | C26: =O26 -> 46046 | D26: =IFERROR(SUMIF(O:O,C26,W:W),#N/A) -> 324.85395 | E26: =IFERROR(SUMIF(O:O,C26,Y:Y),#N/A) -> 0 | F26: =IFERROR(D26/E26,#N/A) -> #N/A | G26: 0.0035 | H26: =IF(E26=0,#N/A,IFERROR(SUMIF(O:O,C26,W:W),#N/A)/E26) -> #N/A | I26: =IF(E26=0,#N/A,IFERROR(SUMIF(O:O,C26,X:X),#N/A)/E26) -> #N/A | J26: =SUM(H26:I26) -> #N/A | L26: =MONTH(O26) -> 1 | M26: =YEAR(O26) -> 2026 | N26: =WEEKNUM(O26) -> 4 | O26: 46046 | P26: =TEXT(WEEKDAY(O26),"ddd") -> sáb | Q26: =SUMIF('SPR - QTD'!$A:$A,DADOS_GRAF!O26,'SPR - QTD'!$H:$H) -> 35 | R26: =SUMIF('SCI - QTD'!$A:$A,DADOS_GRAF!O26,'SCI - QTD'!$H:$H) -> 177 | S26: =SUM(Q26:R26) -> 212 | U26: 4600 | V26: =(S26/T26)*10^6 -> #DIV/0! | W26: =SUMIF('SPR - QTD'!$A:$A,DADOS_GRAF!O26,'SPR - QTD'!$M:$M) -> 324.85395 | X26: =SUMIF('SCI - QTD'!$A:$A,DADOS_GRAF!O26,'SCI - QTD'!$L:$L) -> 0 | AH26: =AH25+1 -> 5 | AI26: Jul | AJ26: 21 | AT26: =AT25+1 -> 7 | AU26: Jul
B27: =TEXT(WEEKDAY(C27),"ddd") -> dom | C27: =O27 -> 46047 | D27: =IFERROR(SUMIF(O:O,C27,W:W),#N/A) -> 275.58747 | E27: =IFERROR(SUMIF(O:O,C27,Y:Y),#N/A) -> 0 | F27: =IFERROR(D27/E27,#N/A) -> #N/A | G27: 0.0035 | H27: =IF(E27=0,#N/A,IFERROR(SUMIF(O:O,C27,W:W),#N/A)/E27) -> #N/A | I27: =IF(E27=0,#N/A,IFERROR(SUMIF(O:O,C27,X:X),#N/A)/E27) -> #N/A | J27: =SUM(H27:I27) -> #N/A | L27: =MONTH(O27) -> 1 | M27: =YEAR(O27) -> 2026 | N27: =WEEKNUM(O27) -> 5 | O27: 46047 | P27: =TEXT(WEEKDAY(O27),"ddd") -> dom | Q27: =SUMIF('SPR - QTD'!$A:$A,DADOS_GRAF!O27,'SPR - QTD'!$H:$H) -> 45 | R27: =SUMIF('SCI - QTD'!$A:$A,DADOS_GRAF!O27,'SCI - QTD'!$H:$H) -> 0 | S27: =SUM(Q27:R27) -> 45 | U27: 4600 | V27: =(S27/T27)*10^6 -> #DIV/0! | W27: =SUMIF('SPR - QTD'!$A:$A,DADOS_GRAF!O27,'SPR - QTD'!$M:$M) -> 275.58747 | X27: =SUMIF('SCI - QTD'!$A:$A,DADOS_GRAF!O27,'SCI - QTD'!$L:$L) -> 0 | AH27: =AH26+1 -> 6 | AI27: Ago | AJ27: 23 | AT27: =AT26+1 -> 8 | AU27: Ago
B28: =TEXT(WEEKDAY(C28),"ddd") -> seg | C28: =O28 -> 46048 | D28: =IFERROR(SUMIF(O:O,C28,W:W),#N/A) -> 1647.1582 | E28: =IFERROR(SUMIF(O:O,C28,Y:Y),#N/A) -> 1242418 | F28: =IFERROR(D28/E28,#N/A) -> 0.0013257681 | G28: 0.0035 | H28: =IF(E28=0,#N/A,IFERROR(SUMIF(O:O,C28,W:W),#N/A)/E28) -> 0.0013257681 | I28: =IF(E28=0,#N/A,IFERROR(SUMIF(O:O,C28,X:X),#N/A)/E28) -> 0 | J28: =SUM(H28:I28) -> 0.0013257681 | L28: =MONTH(O28) -> 1 | M28: =YEAR(O28) -> 2026 | N28: =WEEKNUM(O28) -> 5 | O28: 46048 | P28: =TEXT(WEEKDAY(O28),"ddd") -> seg | Q28: =SUMIF('SPR - QTD'!$A:$A,DADOS_GRAF!O28,'SPR - QTD'!$H:$H) -> 329 | R28: =SUMIF('SCI - QTD'!$A:$A,DADOS_GRAF!O28,'SCI - QTD'!$H:$H) -> 312 | S28: =SUM(Q28:R28) -> 641 | U28: 4600 | V28: =(S28/T28)*10^6 -> #DIV/0! | W28: =SUMIF('SPR - QTD'!$A:$A,DADOS_GRAF!O28,'SPR - QTD'!$M:$M) -> 1647.1582 | X28: =SUMIF('SCI - QTD'!$A:$A,DADOS_GRAF!O28,'SCI - QTD'!$L:$L) -> 0 | Y28: =AE28-AE25 -> 1242418 | Z28: =IFERROR((W28+X28)/Y28,#N/A) -> 0.0013257681 | AA28: =IF(Y28="",#N/A,W28/Y28) -> 0.0013257681 | AB28: =IF(Y28="",#N/A,X28/Y28) -> 0 | AC28: X | AE28: =AE25+$AG$30 -> 15685228 | AH28: =AH27+1 -> 7 | AI28: Set | AJ28: 20 | AT28: =AT27+1 -> 9 | AU28: Set
B29: =TEXT(WEEKDAY(C29),"ddd") -> ter | C29: =O29 -> 46049 | D29: =IFERROR(SUMIF(O:O,C29,W:W),#N/A) -> 0 | E29: =IFERROR(SUMIF(O:O,C29,Y:Y),#N/A) -> 1242418 | F29: =IFERROR(D29/E29,#N/A) -> 0 | G29: 0.0035 | H29: =IF(E29=0,#N/A,IFERROR(SUMIF(O:O,C29,W:W),#N/A)/E29) -> 0 | I29: =IF(E29=0,#N/A,IFERROR(SUMIF(O:O,C29,X:X),#N/A)/E29) -> 0 | J29: =SUM(H29:I29) -> 0 | L29: =MONTH(O29) -> 1 | M29: =YEAR(O29) -> 2026 | N29: =WEEKNUM(O29) -> 5 | O29: 46049 | P29: =TEXT(WEEKDAY(O29),"ddd") -> ter | Q29: =SUMIF('SPR - QTD'!$A:$A,DADOS_GRAF!O29,'SPR - QTD'!$H:$H) -> 606 | R29: =SUMIF('SCI - QTD'!$A:$A,DADOS_GRAF!O29,'SCI - QTD'!$H:$H) -> 429.5 | S29: =SUM(Q29:R29) -> 1035.5 | U29: 4600 | V29: =(S29/T29)*10^6 -> #DIV/0! | W29: =SUMIF('SPR - QTD'!$A:$A,DADOS_GRAF!O29,'SPR - QTD'!$M:$M) -> 0 | X29: =SUMIF('SCI - QTD'!$A:$A,DADOS_GRAF!O29,'SCI - QTD'!$L:$L) -> 0 | Y29: =AE29-AE28 -> 1242418 | Z29: =IFERROR((W29+X29)/Y29,#N/A) -> 0 | AA29: =IF(Y29="",#N/A,W29/Y29) -> 0 | AB29: =IF(Y29="",#N/A,X29/Y29) -> 0 | AC29: X | AE29: =AE28+$AG$30 -> 16927646 | AH29: =AH28+1 -> 8 | AI29: Out | AJ29: 21 | AT29: =AT28+1 -> 10 | AU29: Out
B30: =TEXT(WEEKDAY(C30),"ddd") -> qua | C30: =O30 -> 46050 | D30: =IFERROR(SUMIF(O:O,C30,W:W),#N/A) -> 0 | E30: =IFERROR(SUMIF(O:O,C30,Y:Y),#N/A) -> 0 | F30: =IFERROR(D30/E30,#N/A) -> #N/A | G30: 0.0035 | H30: =IF(E30=0,#N/A,IFERROR(SUMIF(O:O,C30,W:W),#N/A)/E30) -> #N/A | I30: =IF(E30=0,#N/A,IFERROR(SUMIF(O:O,C30,X:X),#N/A)/E30) -> #N/A | J30: =SUM(H30:I30) -> #N/A | L30: =MONTH(O30) -> 1 | M30: =YEAR(O30) -> 2026 | N30: =WEEKNUM(O30) -> 5 | O30: 46050 | P30: =TEXT(WEEKDAY(O30),"ddd") -> qua | Q30: =SUMIF('SPR - QTD'!$A:$A,DADOS_GRAF!O30,'SPR - QTD'!$H:$H) -> 527 | R30: =SUMIF('SCI - QTD'!$A:$A,DADOS_GRAF!O30,'SCI - QTD'!$H:$H) -> 835.1 | S30: =SUM(Q30:R30) -> 1362.1 | U30: 4600 | V30: =(S30/T30)*10^6 -> #DIV/0! | W30: =SUMIF('SPR - QTD'!$A:$A,DADOS_GRAF!O30,'SPR - QTD'!$M:$M) -> 0 | X30: =SUMIF('SCI - QTD'!$A:$A,DADOS_GRAF!O30,'SCI - QTD'!$L:$L) -> 0 | Z30: =IFERROR((W30+X30)/Y30,#N/A) -> #N/A | AA30: =IF(Y30="",#N/A,W30/Y30) -> #N/A | AB30: =IF(Y30="",#N/A,X30/Y30) -> #N/A | AC30: X | AG30: =(AG31-AE16)/9 -> 1242418 | AH30: =AH29+1 -> 9 | AI30: Nov | AJ30: 20 | AT30: =AT29+1 -> 11 | AU30: Nov
B31: =TEXT(WEEKDAY(C31),"ddd") -> qui | C31: =O31 -> 46051 | D31: =IFERROR(SUMIF(O:O,C31,W:W),#N/A) -> 0 | E31: =IFERROR(SUMIF(O:O,C31,Y:Y),#N/A) -> 0 | F31: =IFERROR(D31/E31,#N/A) -> #N/A | G31: 0.0035 | H31: =IF(E31=0,#N/A,IFERROR(SUMIF(O:O,C31,W:W),#N/A)/E31) -> #N/A | I31: =IF(E31=0,#N/A,IFERROR(SUMIF(O:O,C31,X:X),#N/A)/E31) -> #N/A | J31: =SUM(H31:I31) -> #N/A | L31: =MONTH(O31) -> 1 | M31: =YEAR(O31) -> 2026 | N31: =WEEKNUM(O31) -> 5 | O31: 46051 | P31: =TEXT(WEEKDAY(O31),"ddd") -> qui | Q31: =SUMIF('SPR - QTD'!$A:$A,DADOS_GRAF!O31,'SPR - QTD'!$H:$H) -> 400 | R31: =SUMIF('SCI - QTD'!$A:$A,DADOS_GRAF!O31,'SCI - QTD'!$H:$H) -> 470.5 | S31: =SUM(Q31:R31) -> 870.5 | U31: 4600 | V31: =(S31/T31)*10^6 -> #DIV/0! | W31: =SUMIF('SPR - QTD'!$A:$A,DADOS_GRAF!O31,'SPR - QTD'!$M:$M) -> 0 | X31: =SUMIF('SCI - QTD'!$A:$A,DADOS_GRAF!O31,'SCI - QTD'!$L:$L) -> 0 | Y31: =AE31-AE30 -> 0 | Z31: =IFERROR((W31+X31)/Y31,#N/A) -> #N/A | AA31: =IF(Y31="",#N/A,W31/Y31) -> #DIV/0! | AB31: =IF(Y31="",#N/A,X31/Y31) -> #DIV/0! | AC31: X | AG31: 16927646 | AH31: =AH30+1 -> 10 | AI31: Dez | AJ31: 20 | AT31: =AT30+1 -> 12 | AU31: Dez
B32: =TEXT(WEEKDAY(C32),"ddd") -> sex | C32: =O32 -> 46052 | D32: =IFERROR(SUMIF(O:O,C32,W:W),#N/A) -> 0 | E32: =IFERROR(SUMIF(O:O,C32,Y:Y),#N/A) -> 18904592 | F32: =IFERROR(D32/E32,#N/A) -> 0 | G32: 0.0035 | H32: =IF(E32=0,#N/A,IFERROR(SUMIF(O:O,C32,W:W),#N/A)/E32) -> 0 | I32: =IF(E32=0,#N/A,IFERROR(SUMIF(O:O,C32,X:X),#N/A)/E32) -> 0 | J32: =SUM(H32:I32) -> 0 | L32: =MONTH(O32) -> 1 | M32: =YEAR(O32) -> 2026 | N32: =WEEKNUM(O32) -> 5 | O32: 46052 | P32: =TEXT(WEEKDAY(O32),"ddd") -> sex | Q32: =SUMIF('SPR - QTD'!$A:$A,DADOS_GRAF!O32,'SPR - QTD'!$H:$H) -> 293 | R32: =SUMIF('SCI - QTD'!$A:$A,DADOS_GRAF!O32,'SCI - QTD'!$H:$H) -> 754 | S32: =SUM(Q32:R32) -> 1047 | U32: 4600 | V32: =(S32/T32)*10^6 -> #DIV/0! | W32: =SUMIF('SPR - QTD'!$A:$A,DADOS_GRAF!O32,'SPR - QTD'!$M:$M) -> 0 | X32: =SUMIF('SCI - QTD'!$A:$A,DADOS_GRAF!O32,'SCI - QTD'!$L:$L) -> 0 | Y32: =AE32-AE31 -> 18904592 | Z32: =IFERROR((W32+X32)/Y32,#N/A) -> 0 | AA32: =IF(Y32="",#N/A,W32/Y32) -> 0 | AB32: =IF(Y32="",#N/A,X32/Y32) -> 0 | AC32: X | AE32: 18904592 | AG32: 18803636 | AJ32: =SUM(AJ20:AJ31) -> 251
B33: =TEXT(WEEKDAY(C33),"ddd") -> sáb | C33: =O33 -> 46053 | D33: =IFERROR(SUMIF(O:O,C33,W:W),#N/A) -> 0 | E33: =IFERROR(SUMIF(O:O,C33,Y:Y),#N/A) -> 0 | F33: =IFERROR(D33/E33,#N/A) -> #N/A | G33: 0.0035 | H33: =IF(E33=0,#N/A,IFERROR(SUMIF(O:O,C33,W:W),#N/A)/E33) -> #N/A | I33: =IF(E33=0,#N/A,IFERROR(SUMIF(O:O,C33,X:X),#N/A)/E33) -> #N/A | J33: =SUM(H33:I33) -> #N/A | L33: =MONTH(O33) -> 1 | M33: =YEAR(O33) -> 2026 | N33: =WEEKNUM(O33) -> 5 | O33: 46053 | P33: =TEXT(WEEKDAY(O33),"ddd") -> sáb | Q33: =SUMIF('SPR - QTD'!$A:$A,DADOS_GRAF!O33,'SPR - QTD'!$H:$H) -> 46 | R33: =SUMIF('SCI - QTD'!$A:$A,DADOS_GRAF!O33,'SCI - QTD'!$H:$H) -> 49 | S33: =SUM(Q33:R33) -> 95 | U33: 4600 | V33: =(S33/T33)*10^6 -> #DIV/0! | W33: =SUMIF('SPR - QTD'!$A:$A,DADOS_GRAF!O33,'SPR - QTD'!$M:$M) -> 0 | X33: =SUMIF('SCI - QTD'!$A:$A,DADOS_GRAF!O33,'SCI - QTD'!$L:$L) -> 0
B34: =TEXT(WEEKDAY(C34),"ddd") -> dom | C34: =O34 -> 46054 | D34: =IFERROR(SUMIF(O:O,C34,W:W),#N/A) -> 0 | E34: =IFERROR(SUMIF(O:O,C34,Y:Y),#N/A) -> 0 | F34: =IFERROR(D34/E34,#N/A) -> #N/A | G34: 0.0035 | H34: =IF(E34=0,#N/A,IFERROR(SUMIF(O:O,C34,W:W),#N/A)/E34) -> #N/A | I34: =IF(E34=0,#N/A,IFERROR(SUMIF(O:O,C34,X:X),#N/A)/E34) -> #N/A | J34: =SUM(H34:I34) -> #N/A | L34: =MONTH(O34) -> 2 | M34: =YEAR(O34) -> 2026 | N34: =WEEKNUM(O34) -> 6 | O34: 46054 | P34: =TEXT(WEEKDAY(O34),"ddd") -> dom | Q34: =SUMIF('SPR - QTD'!$A:$A,DADOS_GRAF!O34,'SPR - QTD'!$H:$H) -> 57 | R34: =SUMIF('SCI - QTD'!$A:$A,DADOS_GRAF!O34,'SCI - QTD'!$H:$H) -> 20 | S34: =SUM(Q34:R34) -> 77 | U34: 4600 | V34: =(S34/T34)*10^6 -> #DIV/0! | W34: =SUMIF('SPR - QTD'!$A:$A,DADOS_GRAF!O34,'SPR - QTD'!$M:$M) -> 0 | X34: =SUMIF('SCI - QTD'!$A:$A,DADOS_GRAF!O34,'SCI - QTD'!$L:$L) -> 0
B35: =TEXT(WEEKDAY(C35),"ddd") -> seg | C35: =O35 -> 46055 | D35: =IFERROR(SUMIF(O:O,C35,W:W),#N/A) -> 0 | E35: =IFERROR(SUMIF(O:O,C35,Y:Y),#N/A) -> 0 | F35: =IFERROR(D35/E35,#N/A) -> #N/A | G35: 0.0035 | H35: =IF(E35=0,#N/A,IFERROR(SUMIF(O:O,C35,W:W),#N/A)/E35) -> #N/A | I35: =IF(E35=0,#N/A,IFERROR(SUMIF(O:O,C35,X:X),#N/A)/E35) -> #N/A | J35: =SUM(H35:I35) -> #N/A | L35: =MONTH(O35) -> 2 | M35: =YEAR(O35) -> 2026 | N35: =WEEKNUM(O35) -> 6 | O35: 46055 | P35: =TEXT(WEEKDAY(O35),"ddd") -> seg | Q35: =SUMIF('SPR - QTD'!$A:$A,DADOS_GRAF!O35,'SPR - QTD'!$H:$H) -> 479 | R35: =SUMIF('SCI - QTD'!$A:$A,DADOS_GRAF!O35,'SCI - QTD'!$H:$H) -> 583 | S35: =SUM(Q35:R35) -> 1062 | U35: 4600 | V35: =(S35/T35)*10^6 -> #DIV/0! | W35: =SUMIF('SPR - QTD'!$A:$A,DADOS_GRAF!O35,'SPR - QTD'!$M:$M) -> 0 | X35: =SUMIF('SCI - QTD'!$A:$A,DADOS_GRAF!O35,'SCI - QTD'!$L:$L) -> 0
B36: =TEXT(WEEKDAY(C36),"ddd") -> ter | C36: =O36 -> 46056 | D36: =IFERROR(SUMIF(O:O,C36,W:W),#N/A) -> 0 | E36: =IFERROR(SUMIF(O:O,C36,Y:Y),#N/A) -> 0 | F36: =IFERROR(D36/E36,#N/A) -> #N/A | G36: 0.0035 | H36: =IF(E36=0,#N/A,IFERROR(SUMIF(O:O,C36,W:W),#N/A)/E36) -> #N/A | I36: =IF(E36=0,#N/A,IFERROR(SUMIF(O:O,C36,X:X),#N/A)/E36) -> #N/A | J36: =SUM(H36:I36) -> #N/A | L36: =MONTH(O36) -> 2 | M36: =YEAR(O36) -> 2026 | N36: =WEEKNUM(O36) -> 6 | O36: 46056 | P36: =TEXT(WEEKDAY(O36),"ddd") -> ter | Q36: =SUMIF('SPR - QTD'!$A:$A,DADOS_GRAF!O36,'SPR - QTD'!$H:$H) -> 300 | R36: =SUMIF('SCI - QTD'!$A:$A,DADOS_GRAF!O36,'SCI - QTD'!$H:$H) -> 598 | S36: =SUM(Q36:R36) -> 898 | U36: 4600 | V36: =(S36/T36)*10^6 -> #DIV/0! | W36: =SUMIF('SPR - QTD'!$A:$A,DADOS_GRAF!O36,'SPR - QTD'!$M:$M) -> 0 | X36: =SUMIF('SCI - QTD'!$A:$A,DADOS_GRAF!O36,'SCI - QTD'!$L:$L) -> 0
B37: =TEXT(WEEKDAY(C37),"ddd") -> qua | C37: =O37 -> 46057 | D37: =IFERROR(SUMIF(O:O,C37,W:W),#N/A) -> 0 | E37: =IFERROR(SUMIF(O:O,C37,Y:Y),#N/A) -> 0 | F37: =IFERROR(D37/E37,#N/A) -> #N/A | G37: 0.0035 | H37: =IF(E37=0,#N/A,IFERROR(SUMIF(O:O,C37,W:W),#N/A)/E37) -> #N/A | I37: =IF(E37=0,#N/A,IFERROR(SUMIF(O:O,C37,X:X),#N/A)/E37) -> #N/A | J37: =SUM(H37:I37) -> #N/A | L37: =MONTH(O37) -> 2 | M37: =YEAR(O37) -> 2026 | N37: =WEEKNUM(O37) -> 6 | O37: 46057 | P37: =TEXT(WEEKDAY(O37),"ddd") -> qua | Q37: =SUMIF('SPR - QTD'!$A:$A,DADOS_GRAF!O37,'SPR - QTD'!$H:$H) -> 370 | R37: =SUMIF('SCI - QTD'!$A:$A,DADOS_GRAF!O37,'SCI - QTD'!$H:$H) -> 452.5 | S37: =SUM(Q37:R37) -> 822.5 | U37: 4600 | V37: =(S37/T37)*10^6 -> #DIV/0! | W37: =SUMIF('SPR - QTD'!$A:$A,DADOS_GRAF!O37,'SPR - QTD'!$M:$M) -> 0 | X37: =SUMIF('SCI - QTD'!$A:$A,DADOS_GRAF!O37,'SCI - QTD'!$L:$L) -> 0
B38: =TEXT(WEEKDAY(C38),"ddd") -> qui | C38: =O38 -> 46058 | D38: =IFERROR(SUMIF(O:O,C38,W:W),#N/A) -> 0 | E38: =IFERROR(SUMIF(O:O,C38,Y:Y),#N/A) -> 0 | F38: =IFERROR(D38/E38,#N/A) -> #N/A | G38: 0.0035 | H38: =IF(E38=0,#N/A,IFERROR(SUMIF(O:O,C38,W:W),#N/A)/E38) -> #N/A | I38: =IF(E38=0,#N/A,IFERROR(SUMIF(O:O,C38,X:X),#N/A)/E38) -> #N/A | J38: =SUM(H38:I38) -> #N/A | L38: =MONTH(O38) -> 2 | M38: =YEAR(O38) -> 2026 | N38: =WEEKNUM(O38) -> 6 | O38: 46058 | P38: =TEXT(WEEKDAY(O38),"ddd") -> qui | Q38: =SUMIF('SPR - QTD'!$A:$A,DADOS_GRAF!O38,'SPR - QTD'!$H:$H) -> 522 | R38: =SUMIF('SCI - QTD'!$A:$A,DADOS_GRAF!O38,'SCI - QTD'!$H:$H) -> 269.5 | S38: =SUM(Q38:R38) -> 791.5 | U38: 4600 | V38: =(S38/T38)*10^6 -> #DIV/0! | W38: =SUMIF('SPR - QTD'!$A:$A,DADOS_GRAF!O38,'SPR - QTD'!$M:$M) -> 0 | X38: =SUMIF('SCI - QTD'!$A:$A,DADOS_GRAF!O38,'SCI - QTD'!$L:$L) -> 0
B39: =TEXT(WEEKDAY(C39),"ddd") -> sex | C39: =O39 -> 46059 | D39: =IFERROR(SUMIF(O:O,C39,W:W),#N/A) -> 0 | E39: =IFERROR(SUMIF(O:O,C39,Y:Y),#N/A) -> 0 | F39: =IFERROR(D39/E39,#N/A) -> #N/A | G39: 0.0035 | H39: =IF(E39=0,#N/A,IFERROR(SUMIF(O:O,C39,W:W),#N/A)/E39) -> #N/A | I39: =IF(E39=0,#N/A,IFERROR(SUMIF(O:O,C39,X:X),#N/A)/E39) -> #N/A | J39: =SUM(H39:I39) -> #N/A | L39: =MONTH(O39) -> 2 | M39: =YEAR(O39) -> 2026 | N39: =WEEKNUM(O39) -> 6 | O39: 46059 | P39: =TEXT(WEEKDAY(O39),"ddd") -> sex | Q39: =SUMIF('SPR - QTD'!$A:$A,DADOS_GRAF!O39,'SPR - QTD'!$H:$H) -> 376 | R39: =SUMIF('SCI - QTD'!$A:$A,DADOS_GRAF!O39,'SCI - QTD'!$H:$H) -> 315.5 | S39: =SUM(Q39:R39) -> 691.5 | U39: 4600 | V39: =(S39/T39)*10^6 -> #DIV/0! | W39: =SUMIF('SPR - QTD'!$A:$A,DADOS_GRAF!O39,'SPR - QTD'!$M:$M) -> 0 | X39: =SUMIF('SCI - QTD'!$A:$A,DADOS_GRAF!O39,'SCI - QTD'!$L:$L) -> 0
B40: =TEXT(WEEKDAY(C40),"ddd") -> sáb | C40: =O40 -> 46060 | D40: =IFERROR(SUMIF(O:O,C40,W:W),#N/A) -> 0 | E40: =IFERROR(SUMIF(O:O,C40,Y:Y),#N/A) -> 0 | F40: =IFERROR(D40/E40,#N/A) -> #N/A | G40: 0.0035 | H40: =IF(E40=0,#N/A,IFERROR(SUMIF(O:O,C40,W:W),#N/A)/E40) -> #N/A | I40: =IF(E40=0,#N/A,IFERROR(SUMIF(O:O,C40,X:X),#N/A)/E40) -> #N/A | J40: =SUM(H40:I40) -> #N/A | L40: =MONTH(O40) -> 2 | M40: =YEAR(O40) -> 2026 | N40: =WEEKNUM(O40) -> 6 | O40: 46060 | P40: =TEXT(WEEKDAY(O40),"ddd") -> sáb | Q40: =SUMIF('SPR - QTD'!$A:$A,DADOS_GRAF!O40,'SPR - QTD'!$H:$H) -> 67 | R40: =SUMIF('SCI - QTD'!$A:$A,DADOS_GRAF!O40,'SCI - QTD'!$H:$H) -> 35 | S40: =SUM(Q40:R40) -> 102 | U40: 4600 | V40: =(S40/T40)*10^6 -> #DIV/0! | W40: =SUMIF('SPR - QTD'!$A:$A,DADOS_GRAF!O40,'SPR - QTD'!$M:$M) -> 0 | X40: =SUMIF('SCI - QTD'!$A:$A,DADOS_GRAF!O40,'SCI - QTD'!$L:$L) -> 0
B41: =TEXT(WEEKDAY(C41),"ddd") -> dom | C41: =O41 -> 46061 | D41: =IFERROR(SUMIF(O:O,C41,W:W),#N/A) -> 0 | E41: =IFERROR(SUMIF(O:O,C41,Y:Y),#N/A) -> 0 | F41: =IFERROR(D41/E41,#N/A) -> #N/A | G41: 0.0035 | H41: =IF(E41=0,#N/A,IFERROR(SUMIF(O:O,C41,W:W),#N/A)/E41) -> #N/A | I41: =IF(E41=0,#N/A,IFERROR(SUMIF(O:O,C41,X:X),#N/A)/E41) -> #N/A | J41: =SUM(H41:I41) -> #N/A | L41: =MONTH(O41) -> 2 | M41: =YEAR(O41) -> 2026 | N41: =WEEKNUM(O41) -> 7 | O41: 46061 | P41: =TEXT(WEEKDAY(O41),"ddd") -> dom | Q41: =SUMIF('SPR - QTD'!$A:$A,DADOS_GRAF!O41,'SPR - QTD'!$H:$H) -> 42 | R41: =SUMIF('SCI - QTD'!$A:$A,DADOS_GRAF!O41,'SCI - QTD'!$H:$H) -> 50.5 | S41: =SUM(Q41:R41) -> 92.5 | U41: 4600 | V41: =(S41/T41)*10^6 -> #DIV/0! | W41: =SUMIF('SPR - QTD'!$A:$A,DADOS_GRAF!O41,'SPR - QTD'!$M:$M) -> 0 | X41: =SUMIF('SCI - QTD'!$A:$A,DADOS_GRAF!O41,'SCI - QTD'!$L:$L) -> 0
B42: =TEXT(WEEKDAY(C42),"ddd") -> seg | C42: =O42 -> 46062 | D42: =IFERROR(SUMIF(O:O,C42,W:W),#N/A) -> 0 | E42: =IFERROR(SUMIF(O:O,C42,Y:Y),#N/A) -> 0 | F42: =IFERROR(D42/E42,#N/A) -> #N/A | G42: 0.0035 | H42: =IF(E42=0,#N/A,IFERROR(SUMIF(O:O,C42,W:W),#N/A)/E42) -> #N/A | I42: =IF(E42=0,#N/A,IFERROR(SUMIF(O:O,C42,X:X),#N/A)/E42) -> #N/A | J42: =SUM(H42:I42) -> #N/A | L42: =MONTH(O42) -> 2 | M42: =YEAR(O42) -> 2026 | N42: =WEEKNUM(O42) -> 7 | O42: 46062 | P42: =TEXT(WEEKDAY(O42),"ddd") -> seg | Q42: =SUMIF('SPR - QTD'!$A:$A,DADOS_GRAF!O42,'SPR - QTD'!$H:$H) -> 295 | R42: =SUMIF('SCI - QTD'!$A:$A,DADOS_GRAF!O42,'SCI - QTD'!$H:$H) -> 267.5 | S42: =SUM(Q42:R42) -> 562.5 | U42: 4600 | V42: =(S42/T42)*10^6 -> #DIV/0! | W42: =SUMIF('SPR - QTD'!$A:$A,DADOS_GRAF!O42,'SPR - QTD'!$M:$M) -> 0 | X42: =SUMIF('SCI - QTD'!$A:$A,DADOS_GRAF!O42,'SCI - QTD'!$L:$L) -> 0
B43: =TEXT(WEEKDAY(C43),"ddd") -> ter | C43: =O43 -> 46063 | D43: =IFERROR(SUMIF(O:O,C43,W:W),#N/A) -> 0 | E43: =IFERROR(SUMIF(O:O,C43,Y:Y),#N/A) -> 0 | F43: =IFERROR(D43/E43,#N/A) -> #N/A | G43: 0.0035 | H43: =IF(E43=0,#N/A,IFERROR(SUMIF(O:O,C43,W:W),#N/A)/E43) -> #N/A | I43: =IF(E43=0,#N/A,IFERROR(SUMIF(O:O,C43,X:X),#N/A)/E43) -> #N/A | J43: =SUM(H43:I43) -> #N/A | L43: =MONTH(O43) -> 2 | M43: =YEAR(O43) -> 2026 | N43: =WEEKNUM(O43) -> 7 | O43: 46063 | P43: =TEXT(WEEKDAY(O43),"ddd") -> ter | Q43: =SUMIF('SPR - QTD'!$A:$A,DADOS_GRAF!O43,'SPR - QTD'!$H:$H) -> 425 | R43: =SUMIF('SCI - QTD'!$A:$A,DADOS_GRAF!O43,'SCI - QTD'!$H:$H) -> 175.5 | S43: =SUM(Q43:R43) -> 600.5 | U43: 4600 | V43: =(S43/T43)*10^6 -> #DIV/0! | W43: =SUMIF('SPR - QTD'!$A:$A,DADOS_GRAF!O43,'SPR - QTD'!$M:$M) -> 0 | X43: =SUMIF('SCI - QTD'!$A:$A,DADOS_GRAF!O43,'SCI - QTD'!$L:$L) -> 0
B44: =TEXT(WEEKDAY(C44),"ddd") -> qua | C44: =O44 -> 46064 | D44: =IFERROR(SUMIF(O:O,C44,W:W),#N/A) -> 0 | E44: =IFERROR(SUMIF(O:O,C44,Y:Y),#N/A) -> 0 | F44: =IFERROR(D44/E44,#N/A) -> #N/A | G44: 0.0035 | H44: =IF(E44=0,#N/A,IFERROR(SUMIF(O:O,C44,W:W),#N/A)/E44) -> #N/A | I44: =IF(E44=0,#N/A,IFERROR(SUMIF(O:O,C44,X:X),#N/A)/E44) -> #N/A | J44: =SUM(H44:I44) -> #N/A | L44: =MONTH(O44) -> 2 | M44: =YEAR(O44) -> 2026 | N44: =WEEKNUM(O44) -> 7 | O44: 46064 | P44: =TEXT(WEEKDAY(O44),"ddd") -> qua | Q44: =SUMIF('SPR - QTD'!$A:$A,DADOS_GRAF!O44,'SPR - QTD'!$H:$H) -> 595 | R44: =SUMIF('SCI - QTD'!$A:$A,DADOS_GRAF!O44,'SCI - QTD'!$H:$H) -> 449.5 | S44: =SUM(Q44:R44) -> 1044.5 | U44: 4600 | V44: =(S44/T44)*10^6 -> #DIV/0! | W44: =SUMIF('SPR - QTD'!$A:$A,DADOS_GRAF!O44,'SPR - QTD'!$M:$M) -> 0 | X44: =SUMIF('SCI - QTD'!$A:$A,DADOS_GRAF!O44,'SCI - QTD'!$L:$L) -> 0
... B132: =TEXT(WEEKDAY(C132),"ddd") -> dom | C132: =O132 -> 46152 | D132: =IFERROR(SUMIF(O:O,C132,W:W),#N/A) -> 0 | E132: =IFERROR(SUMIF(O:O,C132,Y:Y),#N/A) -> 0 | F132: =IFERROR(D132/E132,#N/A) -> #N/A | G132: 0.0032 | H132: =IF(E132=0,#N/A,IFERROR(SUMIF(O:O,C132,W:W),#N/A)/E132) -> #N/A | I132: =IF(E132=0,#N/A,IFERROR(SUMIF(O:O,C132,X:X),#N/A)/E132) -> #N/A | J132: =SUM(H132:I132) -> #N/A | L132: =MONTH(O132) -> 5 | M132: =YEAR(O132) -> 2026 | N132: =WEEKNUM(O132) -> 20 | O132: 46152 | P132: =TEXT(WEEKDAY(O132),"ddd") -> dom | Q132: =SUMIF('SPR - QTD'!$A:$A,DADOS_GRAF!O132,'SPR - QTD'!$H:$H) -> 0 | R132: =SUMIF('SCI - QTD'!$A:$A,DADOS_GRAF!O132,'SCI - QTD'!$H:$H) -> 0 | S132: =SUM(Q132:R132) -> 0 | U132: 4600 | V132: =(S132/T132)*10^6 -> #DIV/0! | W132: =SUMIF('SPR - QTD'!$A:$A,DADOS_GRAF!O132,'SPR - QTD'!$M:$M) -> 0 | X132: =SUMIF('SCI - QTD'!$A:$A,DADOS_GRAF!O132,'SCI - QTD'!$L:$L) -> 0
B133: =TEXT(WEEKDAY(C133),"ddd") -> seg | C133: =O133 -> 46153 | D133: =IFERROR(SUMIF(O:O,C133,W:W),#N/A) -> 0 | E133: =IFERROR(SUMIF(O:O,C133,Y:Y),#N/A) -> 0 | F133: =IFERROR(D133/E133,#N/A) -> #N/A | G133: 0.0032 | H133: =IF(E133=0,#N/A,IFERROR(SUMIF(O:O,C133,W:W),#N/A)/E133) -> #N/A | I133: =IF(E133=0,#N/A,IFERROR(SUMIF(O:O,C133,X:X),#N/A)/E133) -> #N/A | J133: =SUM(H133:I133) -> #N/A | L133: =MONTH(O133) -> 5 | M133: =YEAR(O133) -> 2026 | N133: =WEEKNUM(O133) -> 20 | O133: 46153 | P133: =TEXT(WEEKDAY(O133),"ddd") -> seg | Q133: =SUMIF('SPR - QTD'!$A:$A,DADOS_GRAF!O133,'SPR - QTD'!$H:$H) -> 0 | R133: =SUMIF('SCI - QTD'!$A:$A,DADOS_GRAF!O133,'SCI - QTD'!$H:$H) -> 0 | S133: =SUM(Q133:R133) -> 0 | U133: 4600 | V133: =(S133/T134)*10^6 -> #DIV/0! | W133: =SUMIF('SPR - QTD'!$A:$A,DADOS_GRAF!O133,'SPR - QTD'!$M:$M) -> 0 | X133: =SUMIF('SCI - QTD'!$A:$A,DADOS_GRAF!O133,'SCI - QTD'!$L:$L) -> 0
B134: =TEXT(WEEKDAY(C134),"ddd") -> ter | C134: =O134 -> 46154 | D134: =IFERROR(SUMIF(O:O,C134,W:W),#N/A) -> 0 | E134: =IFERROR(SUMIF(O:O,C134,Y:Y),#N/A) -> 0 | F134: =IFERROR(D134/E134,#N/A) -> #N/A | G134: 0.0032 | H134: =IF(E134=0,#N/A,IFERROR(SUMIF(O:O,C134,W:W),#N/A)/E134) -> #N/A | I134: =IF(E134=0,#N/A,IFERROR(SUMIF(O:O,C134,X:X),#N/A)/E134) -> #N/A | J134: =SUM(H134:I134) -> #N/A | L134: =MONTH(O134) -> 5 | M134: =YEAR(O134) -> 2026 | N134: =WEEKNUM(O134) -> 20 | O134: 46154 | P134: =TEXT(WEEKDAY(O134),"ddd") -> ter | Q134: =SUMIF('SPR - QTD'!$A:$A,DADOS_GRAF!O134,'SPR - QTD'!$H:$H) -> 0 | R134: =SUMIF('SCI - QTD'!$A:$A,DADOS_GRAF!O134,'SCI - QTD'!$H:$H) -> 0 | S134: =SUM(Q134:R134) -> 0 | U134: 4600 | V134: =(S134/T134)*10^6 -> #DIV/0! | W134: =SUMIF('SPR - QTD'!$A:$A,DADOS_GRAF!O134,'SPR - QTD'!$M:$M) -> 0 | X134: =SUMIF('SCI - QTD'!$A:$A,DADOS_GRAF!O134,'SCI - QTD'!$L:$L) -> 0
B135: =TEXT(WEEKDAY(C135),"ddd") -> qua | C135: =O135 -> 46155 | D135: =IFERROR(SUMIF(O:O,C135,W:W),#N/A) -> 0 | E135: =IFERROR(SUMIF(O:O,C135,Y:Y),#N/A) -> 0 | F135: =IFERROR(D135/E135,#N/A) -> #N/A | G135: 0.0032 | H135: =IF(E135=0,#N/A,IFERROR(SUMIF(O:O,C135,W:W),#N/A)/E135) -> #N/A | I135: =IF(E135=0,#N/A,IFERROR(SUMIF(O:O,C135,X:X),#N/A)/E135) -> #N/A | J135: =SUM(H135:I135) -> #N/A | L135: =MONTH(O135) -> 5 | M135: =YEAR(O135) -> 2026 | N135: =WEEKNUM(O135) -> 20 | O135: 46155 | P135: =TEXT(WEEKDAY(O135),"ddd") -> qua | Q135: =SUMIF('SPR - QTD'!$A:$A,DADOS_GRAF!O135,'SPR - QTD'!$H:$H) -> 0 | R135: =SUMIF('SCI - QTD'!$A:$A,DADOS_GRAF!O135,'SCI - QTD'!$H:$H) -> 0 | S135: =SUM(Q135:R135) -> 0 | U135: 4600 | V135: =(S135/T135)*10^6 -> #DIV/0! | W135: =SUMIF('SPR - QTD'!$A:$A,DADOS_GRAF!O135,'SPR - QTD'!$M:$M) -> 0 | X135: =SUMIF('SCI - QTD'!$A:$A,DADOS_GRAF!O135,'SCI - QTD'!$L:$L) -> 0
B136: =TEXT(WEEKDAY(C136),"ddd") -> qui | C136: =O136 -> 46156 | D136: =IFERROR(SUMIF(O:O,C136,W:W),#N/A) -> 0 | E136: =IFERROR(SUMIF(O:O,C136,Y:Y),#N/A) -> 0 | F136: =IFERROR(D136/E136,#N/A) -> #N/A | G136: 0.0032 | H136: =IF(E136=0,#N/A,IFERROR(SUMIF(O:O,C136,W:W),#N/A)/E136) -> #N/A | I136: =IF(E136=0,#N/A,IFERROR(SUMIF(O:O,C136,X:X),#N/A)/E136) -> #N/A | J136: =SUM(H136:I136) -> #N/A | L136: =MONTH(O136) -> 5 | M136: =YEAR(O136) -> 2026 | N136: =WEEKNUM(O136) -> 20 | O136: 46156 | P136: =TEXT(WEEKDAY(O136),"ddd") -> qui | Q136: =SUMIF('SPR - QTD'!$A:$A,DADOS_GRAF!O136,'SPR - QTD'!$H:$H) -> 0 | R136: =SUMIF('SCI - QTD'!$A:$A,DADOS_GRAF!O136,'SCI - QTD'!$H:$H) -> 0 | S136: =SUM(Q136:R136) -> 0 | U136: 4600 | V136: =(S136/T136)*10^6 -> #DIV/0! | W136: =SUMIF('SPR - QTD'!$A:$A,DADOS_GRAF!O136,'SPR - QTD'!$M:$M) -> 0 | X136: =SUMIF('SCI - QTD'!$A:$A,DADOS_GRAF!O136,'SCI - QTD'!$L:$L) -> 0
B137: =TEXT(WEEKDAY(C137),"ddd") -> sex | C137: =O137 -> 46157 | D137: =IFERROR(SUMIF(O:O,C137,W:W),#N/A) -> 0 | E137: =IFERROR(SUMIF(O:O,C137,Y:Y),#N/A) -> 0 | F137: =IFERROR(D137/E137,#N/A) -> #N/A | G137: 0.0032 | H137: =IF(E137=0,#N/A,IFERROR(SUMIF(O:O,C137,W:W),#N/A)/E137) -> #N/A | I137: =IF(E137=0,#N/A,IFERROR(SUMIF(O:O,C137,X:X),#N/A)/E137) -> #N/A | J137: =SUM(H137:I137) -> #N/A | L137: =MONTH(O137) -> 5 | M137: =YEAR(O137) -> 2026 | N137: =WEEKNUM(O137) -> 20 | O137: 46157 | P137: =TEXT(WEEKDAY(O137),"ddd") -> sex | Q137: =SUMIF('SPR - QTD'!$A:$A,DADOS_GRAF!O137,'SPR - QTD'!$H:$H) -> 0 | R137: =SUMIF('SCI - QTD'!$A:$A,DADOS_GRAF!O137,'SCI - QTD'!$H:$H) -> 0 | S137: =SUM(Q137:R137) -> 0 | U137: 4600 | V137: =(S137/T137)*10^6 -> #DIV/0! | W137: =SUMIF('SPR - QTD'!$A:$A,DADOS_GRAF!O137,'SPR - QTD'!$M:$M) -> 0 | X137: =SUMIF('SCI - QTD'!$A:$A,DADOS_GRAF!O137,'SCI - QTD'!$L:$L) -> 0
B138: =TEXT(WEEKDAY(C138),"ddd") -> sáb | C138: =O138 -> 46158 | D138: =IFERROR(SUMIF(O:O,C138,W:W),#N/A) -> 0 | E138: =IFERROR(SUMIF(O:O,C138,Y:Y),#N/A) -> 0 | F138: =IFERROR(D138/E138,#N/A) -> #N/A | G138: 0.0032 | H138: =IF(E138=0,#N/A,IFERROR(SUMIF(O:O,C138,W:W),#N/A)/E138) -> #N/A | I138: =IF(E138=0,#N/A,IFERROR(SUMIF(O:O,C138,X:X),#N/A)/E138) -> #N/A | J138: =SUM(H138:I138) -> #N/A | L138: =MONTH(O138) -> 5 | M138: =YEAR(O138) -> 2026 | N138: =WEEKNUM(O138) -> 20 | O138: 46158 | P138: =TEXT(WEEKDAY(O138),"ddd") -> sáb | Q138: =SUMIF('SPR - QTD'!$A:$A,DADOS_GRAF!O138,'SPR - QTD'!$H:$H) -> 0 | R138: =SUMIF('SCI - QTD'!$A:$A,DADOS_GRAF!O138,'SCI - QTD'!$H:$H) -> 0 | S138: =SUM(Q138:R138) -> 0 | U138: 4600 | V138: =(S138/T138)*10^6 -> #DIV/0! | W138: =SUMIF('SPR - QTD'!$A:$A,DADOS_GRAF!O138,'SPR - QTD'!$M:$M) -> 0 | X138: =SUMIF('SCI - QTD'!$A:$A,DADOS_GRAF!O138,'SCI - QTD'!$L:$L) -> 0
B139: =TEXT(WEEKDAY(C139),"ddd") -> dom | C139: =O139 -> 46159 | D139: =IFERROR(SUMIF(O:O,C139,W:W),#N/A) -> 0 | E139: =IFERROR(SUMIF(O:O,C139,Y:Y),#N/A) -> 0 | F139: =IFERROR(D139/E139,#N/A) -> #N/A | G139: 0.0032 | H139: =IF(E139=0,#N/A,IFERROR(SUMIF(O:O,C139,W:W),#N/A)/E139) -> #N/A | I139: =IF(E139=0,#N/A,IFERROR(SUMIF(O:O,C139,X:X),#N/A)/E139) -> #N/A | J139: =SUM(H139:I139) -> #N/A | L139: =MONTH(O139) -> 5 | M139: =YEAR(O139) -> 2026 | N139: =WEEKNUM(O139) -> 21 | O139: 46159 | P139: =TEXT(WEEKDAY(O139),"ddd") -> dom | Q139: =SUMIF('SPR - QTD'!$A:$A,DADOS_GRAF!O139,'SPR - QTD'!$H:$H) -> 0 | R139: =SUMIF('SCI - QTD'!$A:$A,DADOS_GRAF!O139,'SCI - QTD'!$H:$H) -> 0 | S139: =SUM(Q139:R139) -> 0 | U139: 4600 | V139: =(S139/T139)*10^6 -> #DIV/0! | W139: =SUMIF('SPR - QTD'!$A:$A,DADOS_GRAF!O139,'SPR - QTD'!$M:$M) -> 0 | X139: =SUMIF('SCI - QTD'!$A:$A,DADOS_GRAF!O139,'SCI - QTD'!$L:$L) -> 0
B140: =TEXT(WEEKDAY(C140),"ddd") -> seg | C140: =O140 -> 46160 | D140: =IFERROR(SUMIF(O:O,C140,W:W),#N/A) -> 0 | E140: =IFERROR(SUMIF(O:O,C140,Y:Y),#N/A) -> 0 | F140: =IFERROR(D140/E140,#N/A) -> #N/A | G140: 0.0032 | H140: =IF(E140=0,#N/A,IFERROR(SUMIF(O:O,C140,W:W),#N/A)/E140) -> #N/A | I140: =IF(E140=0,#N/A,IFERROR(SUMIF(O:O,C140,X:X),#N/A)/E140) -> #N/A | J140: =SUM(H140:I140) -> #N/A | L140: =MONTH(O140) -> 5 | M140: =YEAR(O140) -> 2026 | N140: =WEEKNUM(O140) -> 21 | O140: 46160 | P140: =TEXT(WEEKDAY(O140),"ddd") -> seg | Q140: =SUMIF('SPR - QTD'!$A:$A,DADOS_GRAF!O140,'SPR - QTD'!$H:$H) -> 0 | R140: =SUMIF('SCI - QTD'!$A:$A,DADOS_GRAF!O140,'SCI - QTD'!$H:$H) -> 0 | S140: =SUM(Q140:R140) -> 0 | U140: 4600 | V140: =(S140/T140)*10^6 -> #DIV/0! | W140: =SUMIF('SPR - QTD'!$A:$A,DADOS_GRAF!O140,'SPR - QTD'!$M:$M) -> 0 | X140: =SUMIF('SCI - QTD'!$A:$A,DADOS_GRAF!O140,'SCI - QTD'!$L:$L) -> 0
B141: =TEXT(WEEKDAY(C141),"ddd") -> ter | C141: =O141 -> 46161 | D141: =IFERROR(SUMIF(O:O,C141,W:W),#N/A) -> 0 | E141: =IFERROR(SUMIF(O:O,C141,Y:Y),#N/A) -> 0 | F141: =IFERROR(D141/E141,#N/A) -> #N/A | G141: 0.0032 | H141: =IF(E141=0,#N/A,IFERROR(SUMIF(O:O,C141,W:W),#N/A)/E141) -> #N/A | I141: =IF(E141=0,#N/A,IFERROR(SUMIF(O:O,C141,X:X),#N/A)/E141) -> #N/A | J141: =SUM(H141:I141) -> #N/A | L141: =MONTH(O141) -> 5 | M141: =YEAR(O141) -> 2026 | N141: =WEEKNUM(O141) -> 21 | O141: 46161 | P141: =TEXT(WEEKDAY(O141),"ddd") -> ter | Q141: =SUMIF('SPR - QTD'!$A:$A,DADOS_GRAF!O141,'SPR - QTD'!$H:$H) -> 0 | R141: =SUMIF('SCI - QTD'!$A:$A,DADOS_GRAF!O141,'SCI - QTD'!$H:$H) -> 0 | S141: =SUM(Q141:R141) -> 0 | U141: 4600 | V141: =(S141/T141)*10^6 -> #DIV/0! | W141: =SUMIF('SPR - QTD'!$A:$A,DADOS_GRAF!O141,'SPR - QTD'!$M:$M) -> 0 | X141: =SUMIF('SCI - QTD'!$A:$A,DADOS_GRAF!O141,'SCI - QTD'!$L:$L) -> 0
B142: =TEXT(WEEKDAY(C142),"ddd") -> qua | C142: =O142 -> 46162 | D142: =IFERROR(SUMIF(O:O,C142,W:W),#N/A) -> 0 | E142: =IFERROR(SUMIF(O:O,C142,Y:Y),#N/A) -> 0 | F142: =IFERROR(D142/E142,#N/A) -> #N/A | G142: 0.0032 | H142: =IF(E142=0,#N/A,IFERROR(SUMIF(O:O,C142,W:W),#N/A)/E142) -> #N/A | I142: =IF(E142=0,#N/A,IFERROR(SUMIF(O:O,C142,X:X),#N/A)/E142) -> #N/A | J142: =SUM(H142:I142) -> #N/A | L142: =MONTH(O142) -> 5 | M142: =YEAR(O142) -> 2026 | N142: =WEEKNUM(O142) -> 21 | O142: 46162 | P142: =TEXT(WEEKDAY(O142),"ddd") -> qua | Q142: =SUMIF('SPR - QTD'!$A:$A,DADOS_GRAF!O142,'SPR - QTD'!$H:$H) -> 0 | R142: =SUMIF('SCI - QTD'!$A:$A,DADOS_GRAF!O142,'SCI - QTD'!$H:$H) -> 0 | S142: =SUM(Q142:R142) -> 0 | U142: 4600 | V142: =(S142/T142)*10^6 -> #DIV/0! | W142: =SUMIF('SPR - QTD'!$A:$A,DADOS_GRAF!O142,'SPR - QTD'!$M:$M) -> 0 | X142: =SUMIF('SCI - QTD'!$A:$A,DADOS_GRAF!O142,'SCI - QTD'!$L:$L) -> 0
B143: =TEXT(WEEKDAY(C143),"ddd") -> qui | C143: =O143 -> 46163 | D143: =IFERROR(SUMIF(O:O,C143,W:W),#N/A) -> 0 | E143: =IFERROR(SUMIF(O:O,C143,Y:Y),#N/A) -> 0 | F143: =IFERROR(D143/E143,#N/A) -> #N/A | G143: 0.0032 | H143: =IF(E143=0,#N/A,IFERROR(SUMIF(O:O,C143,W:W),#N/A)/E143) -> #N/A | I143: =IF(E143=0,#N/A,IFERROR(SUMIF(O:O,C143,X:X),#N/A)/E143) -> #N/A | J143: =SUM(H143:I143) -> #N/A | L143: =MONTH(O143) -> 5 | M143: =YEAR(O143) -> 2026 | N143: =WEEKNUM(O143) -> 21 | O143: 46163 | P143: =TEXT(WEEKDAY(O143),"ddd") -> qui | Q143: =SUMIF('SPR - QTD'!$A:$A,DADOS_GRAF!O143,'SPR - QTD'!$H:$H) -> 0 | R143: =SUMIF('SCI - QTD'!$A:$A,DADOS_GRAF!O143,'SCI - QTD'!$H:$H) -> 0 | S143: =SUM(Q143:R143) -> 0 | U143: 4600 | V143: =(S143/T143)*10^6 -> #DIV/0! | W143: =SUMIF('SPR - QTD'!$A:$A,DADOS_GRAF!O143,'SPR - QTD'!$M:$M) -> 0 | X143: =SUMIF('SCI - QTD'!$A:$A,DADOS_GRAF!O143,'SCI - QTD'!$L:$L) -> 0
B144: =TEXT(WEEKDAY(C144),"ddd") -> sex | C144: =O144 -> 46164 | D144: =IFERROR(SUMIF(O:O,C144,W:W),#N/A) -> 0 | E144: =IFERROR(SUMIF(O:O,C144,Y:Y),#N/A) -> 0 | F144: =IFERROR(D144/E144,#N/A) -> #N/A | G144: 0.0032 | H144: =IF(E144=0,#N/A,IFERROR(SUMIF(O:O,C144,W:W),#N/A)/E144) -> #N/A | I144: =IF(E144=0,#N/A,IFERROR(SUMIF(O:O,C144,X:X),#N/A)/E144) -> #N/A | J144: =SUM(H144:I144) -> #N/A | L144: =MONTH(O144) -> 5 | M144: =YEAR(O144) -> 2026 | N144: =WEEKNUM(O144) -> 21 | O144: 46164 | P144: =TEXT(WEEKDAY(O144),"ddd") -> sex | Q144: =SUMIF('SPR - QTD'!$A:$A,DADOS_GRAF!O144,'SPR - QTD'!$H:$H) -> 0 | R144: =SUMIF('SCI - QTD'!$A:$A,DADOS_GRAF!O144,'SCI - QTD'!$H:$H) -> 0 | S144: =SUM(Q144:R144) -> 0 | U144: 4600 | V144: =(S144/T144)*10^6 -> #DIV/0! | W144: =SUMIF('SPR - QTD'!$A:$A,DADOS_GRAF!O144,'SPR - QTD'!$M:$M) -> 0 | X144: =SUMIF('SCI - QTD'!$A:$A,DADOS_GRAF!O144,'SCI - QTD'!$L:$L) -> 0
B145: =TEXT(WEEKDAY(C145),"ddd") -> sáb | C145: =O145 -> 46165 | D145: =IFERROR(SUMIF(O:O,C145,W:W),#N/A) -> 0 | E145: =IFERROR(SUMIF(O:O,C145,Y:Y),#N/A) -> 0 | F145: =IFERROR(D145/E145,#N/A) -> #N/A | G145: 0.0032 | H145: =IF(E145=0,#N/A,IFERROR(SUMIF(O:O,C145,W:W),#N/A)/E145) -> #N/A | I145: =IF(E145=0,#N/A,IFERROR(SUMIF(O:O,C145,X:X),#N/A)/E145) -> #N/A | J145: =SUM(H145:I145) -> #N/A | L145: =MONTH(O145) -> 5 | M145: =YEAR(O145) -> 2026 | N145: =WEEKNUM(O145) -> 21 | O145: 46165 | P145: =TEXT(WEEKDAY(O145),"ddd") -> sáb | Q145: =SUMIF('SPR - QTD'!$A:$A,DADOS_GRAF!O145,'SPR - QTD'!$H:$H) -> 0 | R145: =SUMIF('SCI - QTD'!$A:$A,DADOS_GRAF!O145,'SCI - QTD'!$H:$H) -> 0 | S145: =SUM(Q145:R145) -> 0 | U145: 4600 | V145: =(S145/T145)*10^6 -> #DIV/0! | W145: =SUMIF('SPR - QTD'!$A:$A,DADOS_GRAF!O145,'SPR - QTD'!$M:$M) -> 0 | X145: =SUMIF('SCI - QTD'!$A:$A,DADOS_GRAF!O145,'SCI - QTD'!$L:$L) -> 0
... B367: =TEXT(WEEKDAY(C367),"ddd") -> qui | C367: =O367 -> 46387 | D367: =IFERROR(SUMIF(O:O,C367,W:W),#N/A) -> 0 | E367: =IFERROR(SUMIF(O:O,C367,Y:Y),#N/A) -> 0 | F367: =IFERROR(D367/E367,#N/A) -> #N/A | G367: 212.0032 | H367: =IF(E367=0,#N/A,IFERROR(SUMIF(O:O,C367,W:W),#N/A)/E367) -> #N/A | I367: =IF(E367=0,#N/A,IFERROR(SUMIF(O:O,C367,X:X),#N/A)/E367) -> #N/A | J367: =SUM(H367:I367) -> #N/A | L367: =MONTH(O367) -> 12 | M367: =YEAR(O367) -> 2026 | N367: =WEEKNUM(O367) -> 53 | O367: 46387 | P367: =TEXT(WEEKDAY(O367),"ddd") -> qui | Q367: =SUMIF('SPR - QTD'!$A:$A,DADOS_GRAF!O367,'SPR - QTD'!$H:$H) -> 0 | R367: =SUMIF('SCI - QTD'!$A:$A,DADOS_GRAF!O367,'SCI - QTD'!$H:$H) -> 0 | S367: =SUM(Q367:R367) -> 0 | U367: 4812 | V367: =(S367/T367)*10^6 -> #DIV/0! | W367: =SUMIF('SPR - QTD'!$A:$A,DADOS_GRAF!O367,'SPR - QTD'!$M:$M) -> 0 | X367: =SUMIF('SCI - QTD'!$A:$A,DADOS_GRAF!O367,'SCI - QTD'!$L:$L) -> 0

Sheet SCI - QTD
A1: Data | B1: Turno | C1: PN Novo | D1: Produto | E1: Código NC | F1: Setor | G1: Máquina | H1: Qtde | I1: Responsavel | J1: Médio | K1: R$/Kg | L1: Vlr Total | M1: Qtde Suc | N1: Mês | O1: QTD
A2: 46027 | B2: 1 | C2: MDAI001325 | D2: MDAI001325 | E2: 31 | F2: 320 | G2: GUI02 | H2: 25 | I2: JOABES | J2: 0 | K2: =VLOOKUP(C2,'CUSTO CONTABIL Dez.24 A Dez.25'!$B:$J,9,0) -> 16.272928 | L2: =IF(LEFT(C2,4)="mdac",0,IF(LEFT(C2,4)="mdai",0,IF(J2=0,ABS(K2*H2),ABS(J2)))) -> 0 | M2: =IF(L2=0,0,H2) -> 0 | N2: =MONTH(A2) -> 1 | O2: =ABS(IF(H2=0,0)) -> 0
A3: 46027 | B3: 2 | C3: MDAI001325 | D3: MDAI001325 | E3: 31 | F3: 320 | G3: GUI02 | H3: 20 | I3: LESIDO | J3: 0 | K3: =VLOOKUP(C3,'CUSTO CONTABIL Dez.24 A Dez.25'!$B:$J,9,0) -> 16.272928 | L3: =IF(LEFT(C3,4)="mdac",0,IF(LEFT(C3,4)="mdai",0,IF(J3=0,ABS(K3*H3),ABS(J3)))) -> 0 | M3: =IF(L3=0,0,H3) -> 0 | N3: =MONTH(A3) -> 1 | O3: =ABS(IF(H3=0,0)) -> 0
A4: 46027 | B4: 1 | C4: MDAC001169 | D4: MDAC001169 | E4: 31 | F4: 320 | G4: PRN55 | H4: 80 | I4: FABIO | J4: 0 | K4: =VLOOKUP(C4,'CUSTO CONTABIL Dez.24 A Dez.25'!$B:$J,9,0) -> 7.0201442 | L4: =IF(LEFT(C4,4)="mdac",0,IF(LEFT(C4,4)="mdai",0,IF(J4=0,ABS(K4*H4),ABS(J4)))) -> 0 | M4: =IF(L4=0,0,H4) -> 0 | N4: =MONTH(A4) -> 1 | O4: =ABS(IF(H4=0,0)) -> 0
A5: 46027 | B5: 1 | C5: MDAI001369 | D5: MDAI001369 | E5: 31 | F5: 320 | G5: PRN40 | H5: 10 | I5: LUCAS/PAULO | J5: 0 | K5: =VLOOKUP(C5,'CUSTO CONTABIL Dez.24 A Dez.25'!$B:$J,9,0) -> 29.51846 | L5: =IF(LEFT(C5,4)="mdac",0,IF(LEFT(C5,4)="mdai",0,IF(J5=0,ABS(K5*H5),ABS(J5)))) -> 0 | M5: =IF(L5=0,0,H5) -> 0 | N5: =MONTH(A5) -> 1 | O5: =ABS(IF(H5=0,0)) -> 0
A6: 46027 | B6: 1 | C6: MDAI000978 | D6: MDAC000978 | E6: 31 | F6: 320 | G6: PRN51 | H6: 20 | I6: EDUARDO / DOUGLAS | J6: 0 | K6: =VLOOKUP(C6,'CUSTO CONTABIL Dez.24 A Dez.25'!$B:$J,9,0) -> 16.269568 | L6: =IF(LEFT(C6,4)="mdac",0,IF(LEFT(C6,4)="mdai",0,IF(J6=0,ABS(K6*H6),ABS(J6)))) -> 0 | M6: =IF(L6=0,0,H6) -> 0 | N6: =MONTH(A6) -> 1 | O6: =ABS(IF(H6=0,0)) -> 0
A7: 46027 | B7: 2 | C7: MDAC001181 | D7: MDAC001181 | E7: 31 | F7: 314 | G7: PRN14 | H7: 3 | I7: VINICIUS | J7: 0 | K7: =VLOOKUP(C7,'CUSTO CONTABIL Dez.24 A Dez.25'!$B:$J,9,0) -> 7.2897674 | L7: =IF(LEFT(C7,4)="mdac",0,IF(LEFT(C7,4)="mdai",0,IF(J7=0,ABS(K7*H7),ABS(J7)))) -> 0 | M7: =IF(L7=0,0,H7) -> 0 | N7: =MONTH(A7) -> 1 | O7: =ABS(IF(H7=0,0)) -> 0
A8: 46027 | B8: 2 | C8: MDAI001370 | D8: MDAI001370 | E8: 31 | F8: 320 | G8: PRN40 | H8: 10 | I8: VINICIUS | J8: 0 | K8: =VLOOKUP(C8,'CUSTO CONTABIL Dez.24 A Dez.25'!$B:$J,9,0) -> 29.863125 | L8: =IF(LEFT(C8,4)="mdac",0,IF(LEFT(C8,4)="mdai",0,IF(J8=0,ABS(K8*H8),ABS(J8)))) -> 0 | M8: =IF(L8=0,0,H8) -> 0 | N8: =MONTH(A8) -> 1 | O8: =ABS(IF(H8=0,0)) -> 0
A9: 46027 | B9: 2 | C9: MDAI001371 | D9: MDAI001371 | E9: 31 | F9: 320 | G9: PRN50 | H9: 11.5 | I9: LEONARDO | J9: 0 | K9: =VLOOKUP(C9,'CUSTO CONTABIL Dez.24 A Dez.25'!$B:$J,9,0) -> 29.81609 | L9: =IF(LEFT(C9,4)="mdac",0,IF(LEFT(C9,4)="mdai",0,IF(J9=0,ABS(K9*H9),ABS(J9)))) -> 0 | M9: =IF(L9=0,0,H9) -> 0 | N9: =MONTH(A9) -> 1 | O9: =ABS(IF(H9=0,0)) -> 0
A10: 46027 | B10: 2 | C10: MDAC001169 | D10: MDAC001169 | E10: 31 | F10: 320 | G10: PRN55 | H10: 60 | I10: EDUARDO | J10: 0 | K10: =VLOOKUP(C10,'CUSTO CONTABIL Dez.24 A Dez.25'!$B:$J,9,0) -> 7.0201442 | L10: =IF(LEFT(C10,4)="mdac",0,IF(LEFT(C10,4)="mdai",0,IF(J10=0,ABS(K10*H10),ABS(J10)))) -> 0 | M10: =IF(L10=0,0,H10) -> 0 | N10: =MONTH(A10) -> 1 | O10: =ABS(IF(H10=0,0)) -> 0
A11: 46027 | B11: 3 | C11: =D11 -> MDAC000925 | D11: MDAC000925 | E11: 31 | F11: 314 | G11: PRN18 | H11: 9 | I11: GUILHERME | K11: =VLOOKUP(C11,'CUSTO CONTABIL Dez.24 A Dez.25'!$B:$J,9,0) -> 8.7954707 | L11: =IF(LEFT(C11,4)="mdac",0,IF(LEFT(C11,4)="mdai",0,IF(J11=0,ABS(K11*H11),ABS(J11)))) -> 0 | M11: =IF(L11=0,0,H11) -> 0 | N11: =MONTH(A11) -> 1 | O11: =ABS(IF(H11=0,0)) -> 0
A12: 46028 | B12: 1 | C12: MDAC001130 | D12: MDAC001130 | E12: 31 | F12: 314 | G12: PRN35 | H12: 94 | I12: LUCIANO | J12: 0 | K12: =VLOOKUP(C12,'CUSTO CONTABIL Dez.24 A Dez.25'!$B:$J,9,0) -> 6.0714698 | L12: =IF(LEFT(C12,4)="mdac",0,IF(LEFT(C12,4)="mdai",0,IF(J12=0,ABS(K12*H12),ABS(J12)))) -> 0 | M12: =IF(L12=0,0,H12) -> 0 | N12: =MONTH(A12) -> 1 | O12: =ABS(IF(H12=0,0)) -> 0
A13: 46028 | B13: 1 | C13: MDAC001169 | D13: MDAC001169 | E13: 31 | F13: 320 | G13: PRN28 | H13: 27 | I13: KEYLA | J13: 0 | K13: =VLOOKUP(C13,'CUSTO CONTABIL Dez.24 A Dez.25'!$B:$J,9,0) -> 7.0201442 | L13: =IF(LEFT(C13,4)="mdac",0,IF(LEFT(C13,4)="mdai",0,IF(J13=0,ABS(K13*H13),ABS(J13)))) -> 0 | M13: =IF(L13=0,0,H13) -> 0 | N13: =MONTH(A13) -> 1 | O13: =ABS(IF(H13=0,0)) -> 0
A14: 46028 | B14: 1 | C14: MDAI001160 | D14: MDAI001160 | E14: 31 | F14: 320 | G14: PRN51 | H14: 15 | I14: EDUARDO | J14: 0 | K14: =VLOOKUP(C14,'CUSTO CONTABIL Dez.24 A Dez.25'!$B:$J,9,0) -> 15.295833 | L14: =IF(LEFT(C14,4)="mdac",0,IF(LEFT(C14,4)="mdai",0,IF(J14=0,ABS(K14*H14),ABS(J14)))) -> 0 | M14: =IF(L14=0,0,H14) -> 0 | N14: =MONTH(A14) -> 1 | O14: =ABS(IF(H14=0,0)) -> 0
A15: 46028 | B15: 2 | C15: MDAI001325 | D15: MDAI001325 | E15: 31 | F15: 320 | G15: PRN50 | H15: 16.5 | I15: LEONARDO | J15: 0 | K15: =VLOOKUP(C15,'CUSTO CONTABIL Dez.24 A Dez.25'!$B:$J,9,0) -> 16.272928 | L15: =IF(LEFT(C15,4)="mdac",0,IF(LEFT(C15,4)="mdai",0,IF(J15=0,ABS(K15*H15),ABS(J15)))) -> 0 | M15: =IF(L15=0,0,H15) -> 0 | N15: =MONTH(A15) -> 1 | O15: =ABS(IF(H15=0,0)) -> 0
A16: 46028 | B16: 2 | C16: MDAC001130 | D16: MDAC001130 | E16: 31 | F16: 314 | G16: PRN35 | H16: 19 | I16: ALEXANDRE | J16: 0 | K16: =VLOOKUP(C16,'CUSTO CONTABIL Dez.24 A Dez.25'!$B:$J,9,0) -> 6.0714698 | L16: =IF(LEFT(C16,4)="mdac",0,IF(LEFT(C16,4)="mdai",0,IF(J16=0,ABS(K16*H16),ABS(J16)))) -> 0 | M16: =IF(L16=0,0,H16) -> 0 | N16: =MONTH(A16) -> 1 | O16: =ABS(IF(H16=0,0)) -> 0
A17: 46028 | B17: 2 | C17: MDAC001169 | D17: MDAC001169 | E17: 31 | F17: 320 | G17: PRN55 | H17: 62 | I17: EDUARDO | J17: 0 | K17: =VLOOKUP(C17,'CUSTO CONTABIL Dez.24 A Dez.25'!$B:$J,9,0) -> 7.0201442 | L17: =IF(LEFT(C17,4)="mdac",0,IF(LEFT(C17,4)="mdai",0,IF(J17=0,ABS(K17*H17),ABS(J17)))) -> 0 | M17: =IF(L17=0,0,H17) -> 0 | N17: =MONTH(A17) -> 1 | O17: =ABS(IF(H17=0,0)) -> 0
A18: 46028 | B18: 2 | C18: MDAI001316 | D18: MDAI001316 | E18: 31 | F18: 320 | G18: GUI02 | H18: 9.5 | I18: LESIDO | J18: 0 | K18: =VLOOKUP(C18,'CUSTO CONTABIL Dez.24 A Dez.25'!$B:$J,9,0) -> 16.28455 | L18: =IF(LEFT(C18,4)="mdac",0,IF(LEFT(C18,4)="mdai",0,IF(J18=0,ABS(K18*H18),ABS(J18)))) -> 0 | M18: =IF(L18=0,0,H18) -> 0 | N18: =MONTH(A18) -> 1 | O18: =ABS(IF(H18=0,0)) -> 0
A19: 46029 | B19: 1 | C19: MDAC000736 | D19: MDAC000736 | E19: 31 | F19: 320 | G19: PRN51 | H19: 23 | I19: EDUARDO | J19: 0 | K19: =VLOOKUP(C19,'CUSTO CONTABIL Dez.24 A Dez.25'!$B:$J,9,0) -> 6.8412214 | L19: =IF(LEFT(C19,4)="mdac",0,IF(LEFT(C19,4)="mdai",0,IF(J19=0,ABS(K19*H19),ABS(J19)))) -> 0 | M19: =IF(L19=0,0,H19) -> 0 | N19: =MONTH(A19) -> 1 | O19: =ABS(IF(H19=0,0)) -> 0
A20: 46029 | B20: 1 | C20: MDAC001169 | D20: MDAC001169 | E20: 31 | F20: 320 | G20: PRN55 | H20: 23 | I20: KEYLA | J20: 0 | K20: =VLOOKUP(C20,'CUSTO CONTABIL Dez.24 A Dez.25'!$B:$J,9,0) -> 7.0201442 | L20: =IF(LEFT(C20,4)="mdac",0,IF(LEFT(C20,4)="mdai",0,IF(J20=0,ABS(K20*H20),ABS(J20)))) -> 0 | M20: =IF(L20=0,0,H20) -> 0 | N20: =MONTH(A20) -> 1 | O20: =ABS(IF(H20=0,0)) -> 0
A21: 46029 | B21: 2 | C21: MDAC001180 | D21: MDAC001180 | E21: 31 | F21: 314 | G21: PRN14 | H21: 4 | I21: VINICIUS | J21: 0 | K21: =VLOOKUP(C21,'CUSTO CONTABIL Dez.24 A Dez.25'!$B:$J,9,0) -> 7.9075201 | L21: =IF(LEFT(C21,4)="mdac",0,IF(LEFT(C21,4)="mdai",0,IF(J21=0,ABS(K21*H21),ABS(J21)))) -> 0 | M21: =IF(L21=0,0,H21) -> 0 | N21: =MONTH(A21) -> 1 | O21: =ABS(IF(H21=0,0)) -> 0
A22: 46029 | B22: 2 | C22: MDAI001377 | D22: MDAC001377 | E22: 31 | F22: 320 | G22: PRN40 | H22: 20 | I22: ROGERIO | J22: 0 | K22: =VLOOKUP(C22,'CUSTO CONTABIL Dez.24 A Dez.25'!$B:$J,9,0) -> 24.595665 | L22: =IF(LEFT(C22,4)="mdac",0,IF(LEFT(C22,4)="mdai",0,IF(J22=0,ABS(K22*H22),ABS(J22)))) -> 0 | M22: =IF(L22=0,0,H22) -> 0 | N22: =MONTH(A22) -> 1 | O22: =ABS(IF(H22=0,0)) -> 0
A23: 46029 | B23: 2 | C23: MDAC000736 | D23: MDAI000736 | E23: 31 | F23: 320 | G23: PRN51 | H23: 25 | I23: GABRIEL | J23: 0 | K23: =VLOOKUP(C23,'CUSTO CONTABIL Dez.24 A Dez.25'!$B:$J,9,0) -> 6.8412214 | L23: =IF(LEFT(C23,4)="mdac",0,IF(LEFT(C23,4)="mdai",0,IF(J23=0,ABS(K23*H23),ABS(J23)))) -> 0 | M23: =IF(L23=0,0,H23) -> 0 | N23: =MONTH(A23) -> 1 | O23: =ABS(IF(H23=0,0)) -> 0
... A38: 46034 | B38: 1 | C38: MDAC001169 | D38: MDAC001169 | E38: 31 | F38: 320 | G38: PRN55 | H38: 18 | I38: KEYLA | J38: 0 | K38: =VLOOKUP(C38,'CUSTO CONTABIL Dez.24 A Dez.25'!$B:$J,9,0) -> 7.0201442 | L38: =IF(LEFT(C38,4)="mdac",0,IF(LEFT(C38,4)="mdai",0,IF(J38=0,ABS(K38*H38),ABS(J38)))) -> 0 | M38: =IF(L38=0,0,H38) -> 0 | N38: =MONTH(A38) -> 1 | O38: =ABS(IF(H38=0,0)) -> 0
A39: 46034 | B39: 1 | C39: =D39 -> MDAC001171 | D39: MDAC001171 | E39: 31 | F39: 320 | G39: PRN54 | H39: 75 | I39: RAFAEL
A40: 46035 | B40: 1 | C40: MDAC001169 | D40: MDAC001169 | E40: 31 | F40: 320 | G40: PRN55 | H40: 18 | I40: KEYLA | J40: 0 | K40: =VLOOKUP(C40,'CUSTO CONTABIL Dez.24 A Dez.25'!$B:$J,9,0) -> 7.0201442 | L40: =IF(LEFT(C40,4)="mdac",0,IF(LEFT(C40,4)="mdai",0,IF(J40=0,ABS(K40*H40),ABS(J40)))) -> 0 | M40: =IF(L40=0,0,H40) -> 0 | N40: =MONTH(A40) -> 1 | O40: =ABS(IF(H40=0,0)) -> 0
A41: 46035 | B41: 2 | C41: MDAC001233 | D41: MDAC001233 | E41: 31 | F41: 314 | G41: PRN35 | H41: 76 | I41: ALEXANDRE | J41: 0 | K41: =VLOOKUP(C41,'CUSTO CONTABIL Dez.24 A Dez.25'!$B:$J,9,0) -> 6.4359066 | L41: =IF(LEFT(C41,4)="mdac",0,IF(LEFT(C41,4)="mdai",0,IF(J41=0,ABS(K41*H41),ABS(J41)))) -> 0 | M41: =IF(L41=0,0,H41) -> 0 | N41: =MONTH(A41) -> 1 | O41: =ABS(IF(H41=0,0)) -> 0
A42: 46035 | B42: 2 | C42: MDAI001396 | D42: MDAI001396 | E42: 31 | F42: 320 | G42: PRN51 | H42: 25 | I42: GABRIEL | J42: 0 | K42: =VLOOKUP(C42,'CUSTO CONTABIL Dez.24 A Dez.25'!$B:$J,9,0) -> 22.59135 | L42: =IF(LEFT(C42,4)="mdac",0,IF(LEFT(C42,4)="mdai",0,IF(J42=0,ABS(K42*H42),ABS(J42)))) -> 0 | M42: =IF(L42=0,0,H42) -> 0 | N42: =MONTH(A42) -> 1 | O42: =ABS(IF(H42=0,0)) -> 0
A43: 46035 | B43: 2 | C43: MDAC001322 | D43: MDAI001322 | E43: 31 | F43: 320 | G43: GUI02 | H43: 22.5 | I43: LESIDO | J43: 0 | K43: =VLOOKUP(C43,'CUSTO CONTABIL Dez.24 A Dez.25'!$B:$J,9,0) -> 6.3520138 | L43: =IF(LEFT(C43,4)="mdac",0,IF(LEFT(C43,4)="mdai",0,IF(J43=0,ABS(K43*H43),ABS(J43)))) -> 0 | M43: =IF(L43=0,0,H43) -> 0 | N43: =MONTH(A43) -> 1 | O43: =ABS(IF(H43=0,0)) -> 0
A44: 46035 | B44: 2 | C44: MDAC000736 | D44: MDAI000736 | E44: 31 | F44: 314 | G44: PRN17 | H44: 5 | I44: PATRICK | J44: 0 | K44: =VLOOKUP(C44,'CUSTO CONTABIL Dez.24 A Dez.25'!$B:$J,9,0) -> 6.8412214 | L44: =IF(LEFT(C44,4)="mdac",0,IF(LEFT(C44,4)="mdai",0,IF(J44=0,ABS(K44*H44),ABS(J44)))) -> 0 | M44: =IF(L44=0,0,H44) -> 0 | N44: =MONTH(A44) -> 1 | O44: =ABS(IF(H44=0,0)) -> 0
A45: 46035 | B45: 2 | C45: MDAC001314 | D45: MDAI001314 | E45: 31 | F45: 314 | G45: PRN17 | H45: 42.5 | I45: PATRICK | J45: 0 | K45: =VLOOKUP(C45,'CUSTO CONTABIL Dez.24 A Dez.25'!$B:$J,9,0) -> 7.1067062 | L45: =IF(LEFT(C45,4)="mdac",0,IF(LEFT(C45,4)="mdai",0,IF(J45=0,ABS(K45*H45),ABS(J45)))) -> 0 | M45: =IF(L45=0,0,H45) -> 0 | N45: =MONTH(A45) -> 1 | O45: =ABS(IF(H45=0,0)) -> 0
A46: 46035 | B46: 2 | C46: MDAI000978 | D46: MDAI000978 | E46: 31 | F46: 320 | G46: PRN50 | H46: 25 | I46: LEONARDO | J46: 0 | K46: =VLOOKUP(C46,'CUSTO CONTABIL Dez.24 A Dez.25'!$B:$J,9,0) -> 16.269568 | L46: =IF(LEFT(C46,4)="mdac",0,IF(LEFT(C46,4)="mdai",0,IF(J46=0,ABS(K46*H46),ABS(J46)))) -> 0 | M46: =IF(L46=0,0,H46) -> 0 | N46: =MONTH(A46) -> 1 | O46: =ABS(IF(H46=0,0)) -> 0
A47: 46035 | B47: 2 | C47: MDAC001169 | D47: MDAC001169 | E47: 31 | F47: 320 | G47: PRN50 | H47: 60 | I47: EDUARDO | J47: 0 | K47: =VLOOKUP(C47,'CUSTO CONTABIL Dez.24 A Dez.25'!$B:$J,9,0) -> 7.0201442 | L47: =IF(LEFT(C47,4)="mdac",0,IF(LEFT(C47,4)="mdai",0,IF(J47=0,ABS(K47*H47),ABS(J47)))) -> 0 | M47: =IF(L47=0,0,H47) -> 0 | N47: =MONTH(A47) -> 1 | O47: =ABS(IF(H47=0,0)) -> 0
A48: 46035 | B48: 3 | C48: MDAI001373 | D48: MDAI001373 | E48: 31 | F48: 320 | G48: PRN51 | H48: 25 | I48: EMERSON | J48: 0 | K48: =VLOOKUP(C48,'CUSTO CONTABIL Dez.24 A Dez.25'!$B:$J,9,0) -> 17.24803 | L48: =IF(LEFT(C48,4)="mdac",0,IF(LEFT(C48,4)="mdai",0,IF(J48=0,ABS(K48*H48),ABS(J48)))) -> 0 | M48: =IF(L48=0,0,H48) -> 0 | N48: =MONTH(A48) -> 1 | O48: =ABS(IF(H48=0,0)) -> 0
A49: 46035 | B49: 3 | C49: MDAC001233 | D49: MDAC001233 | E49: 31 | F49: 314 | G49: PRN35 | H49: 33.3 | I49: ADEMIR | J49: 0 | K49: =VLOOKUP(C49,'CUSTO CONTABIL Dez.24 A Dez.25'!$B:$J,9,0) -> 6.4359066 | L49: =IF(LEFT(C49,4)="mdac",0,IF(LEFT(C49,4)="mdai",0,IF(J49=0,ABS(K49*H49),ABS(J49)))) -> 0 | M49: =IF(L49=0,0,H49) -> 0 | N49: =MONTH(A49) -> 1 | O49: =ABS(IF(H49=0,0)) -> 0
A50: 46035 | B50: 1 | C50: MDAC001233 | D50: MDAC001233 | E50: 31 | F50: 314 | G50: PRN35 | H50: 20 | I50: LUCIANO | J50: 0 | K50: =VLOOKUP(C50,'CUSTO CONTABIL Dez.24 A Dez.25'!$B:$J,9,0) -> 6.4359066 | L50: =IF(LEFT(C50,4)="mdac",0,IF(LEFT(C50,4)="mdai",0,IF(J50=0,ABS(K50*H50),ABS(J50)))) -> 0 | M50: =IF(L50=0,0,H50) -> 0 | N50: =MONTH(A50) -> 1 | O50: =ABS(IF(H50=0,0)) -> 0
A51: 46035 | B51: 1 | C51: MDAC001233 | D51: MDAC001233 | E51: 31 | F51: 314 | G51: PRN35 | H51: 10 | I51: LUCIANO | J51: 0 | K51: =VLOOKUP(C51,'CUSTO CONTABIL Dez.24 A Dez.25'!$B:$J,9,0) -> 6.4359066 | L51: =IF(LEFT(C51,4)="mdac",0,IF(LEFT(C51,4)="mdai",0,IF(J51=0,ABS(K51*H51),ABS(J51)))) -> 0 | M51: =IF(L51=0,0,H51) -> 0 | N51: =MONTH(A51) -> 1 | O51: =ABS(IF(H51=0,0)) -> 0
... A54: 46035 | B54: 1 | C54: MDAC001233 | D54: MDAC001233 | E54: 31 | F54: 314 | G54: PRN35 | H54: 10 | I54: LUCIANO | J54: 0 | K54: =VLOOKUP(C54,'CUSTO CONTABIL Dez.24 A Dez.25'!$B:$J,9,0) -> 6.4359066 | L54: =IF(LEFT(C54,4)="mdac",0,IF(LEFT(C54,4)="mdai",0,IF(J54=0,ABS(K54*H54),ABS(J54)))) -> 0 | M54: =IF(L54=0,0,H54) -> 0 | N54: =MONTH(A54) -> 1 | O54: =ABS(IF(H54=0,0)) -> 0
A55: 46036 | B55: 1 | C55: MDAC001117 | D55: MDAC001117 | E55: 31 | F55: 320 | G55: PRN40 | H55: 12 | I55: RICARDO | J55: 0 | K55: =VLOOKUP(C55,'CUSTO CONTABIL Dez.24 A Dez.25'!B:J,9,0) -> 7.7064936 | L55: =IF(LEFT(C55,4)="mdac",0,IF(LEFT(C55,4)="mdai",0,IF(J55=0,ABS(K55*H55),ABS(J55)))) -> 0 | M55: =IF(L55=0,0,H55) -> 0 | N55: =MONTH(A55) -> 1 | O55: =ABS(IF(H55=0,0)) -> 0
A56: 46036 | B56: 1 | C56: MDAC001233 | D56: MDAC001233 | E56: 31 | F56: 314 | G56: PRN35 | H56: 116 | I56: LUCIANO | J56: 0 | K56: =VLOOKUP(C56,'CUSTO CONTABIL Dez.24 A Dez.25'!$B:$J,9,0) -> 6.4359066 | L56: =IF(LEFT(C56,4)="mdac",0,IF(LEFT(C56,4)="mdai",0,IF(J56=0,ABS(K56*H56),ABS(J56)))) -> 0 | M56: =IF(L56=0,0,H56) -> 0 | N56: =MONTH(A56) -> 1 | O56: =ABS(IF(H56=0,0)) -> 0
A57: 46036 | B57: 1 | C57: MDAC001117 | D57: MDAC001117 | E57: 31 | F57: 320 | G57: PRN40 | H57: 30 | I57: KEYLA | J57: 0 | K57: =VLOOKUP(C57,'CUSTO CONTABIL Dez.24 A Dez.25'!$B:$J,9,0) -> 7.7064936 | L57: =IF(LEFT(C57,4)="mdac",0,IF(LEFT(C57,4)="mdai",0,IF(J57=0,ABS(K57*H57),ABS(J57)))) -> 0 | M57: =IF(L57=0,0,H57) -> 0 | N57: =MONTH(A57) -> 1 | O57: =ABS(IF(H57=0,0)) -> 0
A58: 46036 | B58: 1 | C58: MDAI001373 | D58: MDAC001373 | E58: 31 | F58: 320 | G58: PRN51 | H58: 25 | I58: EDUARDO | J58: 0 | K58: =VLOOKUP(C58,'CUSTO CONTABIL Dez.24 A Dez.25'!$B:$J,9,0) -> 17.24803 | L58: =IF(LEFT(C58,4)="mdac",0,IF(LEFT(C58,4)="mdai",0,IF(J58=0,ABS(K58*H58),ABS(J58)))) -> 0 | M58: =IF(L58=0,0,H58) -> 0 | N58: =MONTH(A58) -> 1 | O58: =ABS(IF(H58=0,0)) -> 0
A59: 46036 | B59: 1 | C59: MDAI001004 | D59: MDAI001004 | E59: 31 | F59: 314 | G59: PRN14 | H59: 4 | I59: VINICIUS | J59: 0 | K59: =VLOOKUP(C59,'CUSTO CONTABIL Dez.24 A Dez.25'!$B:$J,9,0) -> 12.242651 | L59: =IF(LEFT(C59,4)="mdac",0,IF(LEFT(C59,4)="mdai",0,IF(J59=0,ABS(K59*H59),ABS(J59)))) -> 0 | M59: =IF(L59=0,0,H59) -> 0 | N59: =MONTH(A59) -> 1 | O59: =ABS(IF(H59=0,0)) -> 0
A60: 46036 | B60: 2 | C60: MDAI001217 | D60: MDAI001217 | E60: 31 | F60: 314 | G60: PRN17 | H60: 68 | I60: JOSENILDO | J60: 0 | K60: =VLOOKUP(C60,'CUSTO CONTABIL Dez.24 A Dez.25'!$B:$J,9,0) -> 14.92409 | L60: =IF(LEFT(C60,4)="mdac",0,IF(LEFT(C60,4)="mdai",0,IF(J60=0,ABS(K60*H60),ABS(J60)))) -> 0 | M60: =IF(L60=0,0,H60) -> 0 | N60: =MONTH(A60) -> 1 | O60: =ABS(IF(H60=0,0)) -> 0
A61: 46036 | B61: 2 | C61: MDAC001117 | D61: MDAC001117 | E61: 31 | F61: 320 | G61: PRN40 | H61: 18 | I61: ROGERIO | J61: 0 | K61: =VLOOKUP(C61,'CUSTO CONTABIL Dez.24 A Dez.25'!$B:$J,9,0) -> 7.7064936 | L61: =IF(LEFT(C61,4)="mdac",0,IF(LEFT(C61,4)="mdai",0,IF(J61=0,ABS(K61*H61),ABS(J61)))) -> 0 | M61: =IF(L61=0,0,H61) -> 0 | N61: =MONTH(A61) -> 1 | O61: =ABS(IF(H61=0,0)) -> 0
A62: 46036 | B62: 2 | C62: MDAI001421 | D62: MDAI001421 | E62: 37 | F62: 320 | G62: GUI02 | H62: 10.5 | I62: LESIDO | J62: 0 | K62: 0 | L62: =IF(LEFT(C62,4)="mdac",0,IF(LEFT(C62,4)="mdai",0,IF(J62=0,ABS(K62*H62),ABS(J62)))) -> 0 | M62: =IF(L62=0,0,H62) -> 0 | N62: =MONTH(A62) -> 1 | O62: =ABS(IF(H62=0,0)) -> 0
A63: 46036 | B63: 1 | C63: =D63 -> MDAI000978 | D63: MDAI000978 | E63: 31 | F63: 320 | G63: PRN50 | H63: 15 | I63: ALEX | J63: 0 | K63: =VLOOKUP(C63,'CUSTO CONTABIL Dez.24 A Dez.25'!$B:$J,9,0) -> 16.269568 | L63: =IF(LEFT(C63,4)="mdac",0,IF(LEFT(C63,4)="mdai",0,IF(J63=0,ABS(K63*H63),ABS(J63)))) -> 0 | M63: =IF(L63=0,0,H63) -> 0 | N63: =MONTH(A63) -> 1 | O63: =ABS(IF(H63=0,0)) -> 0
A64: 46036 | B64: 1 | C64: =D64 -> MDAI001327 | D64: MDAI001327 | E64: 31 | F64: 320 | G64: GUI02 | H64: 20 | I64: JOABES | J64: 0 | K64: =VLOOKUP(C64,'CUSTO CONTABIL Dez.24 A Dez.25'!$B:$J,9,0) -> 15.763266 | L64: =IF(LEFT(C64,4)="mdac",0,IF(LEFT(C64,4)="mdai",0,IF(J64=0,ABS(K64*H64),ABS(J64)))) -> 0 | M64: =IF(L64=0,0,H64) -> 0 | N64: =MONTH(A64) -> 1 | O64: =ABS(IF(H64=0,0)) -> 0
A65: 46037 | B65: 2 | C65: =D65 -> MDAI001164 | D65: MDAI001164 | E65: 31 | F65: 320 | G65: GUI02 | H65: 74.5 | I65: ABNER | J65: 0 | K65: =VLOOKUP(C65,'CUSTO CONTABIL Dez.24 A Dez.25'!$B:$J,9,0) -> 20.933489 | L65: =IF(LEFT(C65,4)="mdac",0,IF(LEFT(C65,4)="mdai",0,IF(J65=0,ABS(K65*H65),ABS(J65)))) -> 0 | M65: =IF(L65=0,0,H65) -> 0 | N65: =MONTH(A65) -> 1 | O65: =ABS(IF(H65=0,0)) -> 0
A66: 46037 | B66: 2 | C66: =D66 -> MDAC000737 | D66: MDAC000737 | E66: 31 | F66: 314 | G66: PRN14 | H66: 6 | I66: JOSENILDO | J66: 0 | K66: =VLOOKUP(C66,'CUSTO CONTABIL Dez.24 A Dez.25'!$B:$J,9,0) -> 5.56785 | L66: =IF(LEFT(C66,4)="mdac",0,IF(LEFT(C66,4)="mdai",0,IF(J66=0,ABS(K66*H66),ABS(J66)))) -> 0 | M66: =IF(L66=0,0,H66) -> 0 | N66: =MONTH(A66) -> 1 | O66: =ABS(IF(H66=0,0)) -> 0
A67: 46037 | B67: 2 | C67: =D67 -> MDAC001174 | D67: MDAC001174 | E67: 31 | F67: 313 | G67: PRN36 | H67: 1.5 | I67: AMANDA | J67: 0 | K67: =VLOOKUP(C67,'CUSTO CONTABIL Dez.24 A Dez.25'!$B:$J,9,0) -> 5.8571135 | L67: =IF(LEFT(C67,4)="mdac",0,IF(LEFT(C67,4)="mdai",0,IF(J67=0,ABS(K67*H67),ABS(J67)))) -> 0 | M67: =IF(L67=0,0,H67) -> 0 | N67: =MONTH(A67) -> 1 | O67: =ABS(IF(H67=0,0)) -> 0
A68: 46037 | B68: 2 | C68: =D68 -> MDAI001379 | D68: MDAI001379 | E68: 31 | F68: 320 | G68: PRN55 | H68: 35 | I68: EDUARDO | J68: 0 | K68: =VLOOKUP(C68,'CUSTO CONTABIL Dez.24 A Dez.25'!$B:$J,9,0) -> 15.578662 | L68: =IF(LEFT(C68,4)="mdac",0,IF(LEFT(C68,4)="mdai",0,IF(J68=0,ABS(K68*H68),ABS(J68)))) -> 0 | M68: =IF(L68=0,0,H68) -> 0 | N68: =MONTH(A68) -> 1 | O68: =ABS(IF(H68=0,0)) -> 0
A69: 46037 | B69: 2 | C69: =D69 -> MDAC001117 | D69: MDAC001117 | E69: 31 | F69: 320 | G69: PRN40 | H69: 17 | I69: ROGÉRIO | J69: 0 | K69: =VLOOKUP(C69,'CUSTO CONTABIL Dez.24 A Dez.25'!$B:$J,9,0) -> 7.7064936 | L69: =IF(LEFT(C69,4)="mdac",0,IF(LEFT(C69,4)="mdai",0,IF(J69=0,ABS(K69*H69),ABS(J69)))) -> 0 | M69: =IF(L69=0,0,H69) -> 0 | N69: =MONTH(A69) -> 1 | O69: =ABS(IF(H69=0,0)) -> 0
A70: 46037 | B70: 1 | C70: =D70 -> MDAC001117 | D70: MDAC001117 | E70: 31 | F70: 320 | G70: PRN40 | H70: 50 | I70: KEYLA | J70: 0 | K70: =VLOOKUP(C70,'CUSTO CONTABIL Dez.24 A Dez.25'!$B:$J,9,0) -> 7.7064936 | L70: =IF(LEFT(C70,4)="mdac",0,IF(LEFT(C70,4)="mdai",0,IF(J70=0,ABS(K70*H70),ABS(J70)))) -> 0 | M70: =IF(L70=0,0,H70) -> 0 | N70: =MONTH(A70) -> 1 | O70: =ABS(IF(H70=0,0)) -> 0
A71: 46037 | B71: 1 | C71: =D71 -> MDAC001169 | D71: MDAC001169 | E71: 31 | F71: 320 | G71: PRN55 | H71: 9 | I71: KEYLA | J71: 0 | K71: =VLOOKUP(C71,'CUSTO CONTABIL Dez.24 A Dez.25'!$B:$J,9,0) -> 7.0201442 | L71: =IF(LEFT(C71,4)="mdac",0,IF(LEFT(C71,4)="mdai",0,IF(J71=0,ABS(K71*H71),ABS(J71)))) -> 0 | M71: =IF(L71=0,0,H71) -> 0 | N71: =MONTH(A71) -> 1 | O71: =ABS(IF(H71=0,0)) -> 0
A72: 46037 | B72: 1 | C72: =D72 -> MDAC000896 | D72: MDAC000896 | E72: 31 | F72: 314 | G72: PRN35 | H72: 6 | I72: LUCIANO | J72: 0 | K72: 0 | L72: =IF(LEFT(C72,4)="mdac",0,IF(LEFT(C72,4)="mdai",0,IF(J72=0,ABS(K72*H72),ABS(J72)))) -> 0 | M72: =IF(L72=0,0,H72) -> 0 | N72: =MONTH(A72) -> 1 | O72: =ABS(IF(H72=0,0)) -> 0
A73: 46037 | B73: 3 | C73: =D73 -> MDAC001155 | D73: MDAC001155 | E73: 31 | F73: 314 | G73: PRN29 | H73: 2.5 | I73: VINICIUS | J73: 0 | K73: =VLOOKUP(C73,'CUSTO CONTABIL Dez.24 A Dez.25'!$B:$J,9,0) -> 7.7871038 | L73: =IF(LEFT(C73,4)="mdac",0,IF(LEFT(C73,4)="mdai",0,IF(J73=0,ABS(K73*H73),ABS(J73)))) -> 0 | M73: =IF(L73=0,0,H73) -> 0 | N73: =MONTH(A73) -> 1 | O73: =ABS(IF(H73=0,0)) -> 0
A74: 46037 | B74: 3 | C74: =D74 -> MDAC001072 | D74: MDAC001072 | E74: 31 | F74: 314 | G74: PRN14 | H74: 8 | I74: GENILSON | J74: 0 | K74: 0 | L74: =IF(LEFT(C74,4)="mdac",0,IF(LEFT(C74,4)="mdai",0,IF(J74=0,ABS(K74*H74),ABS(J74)))) -> 0 | M74: =IF(L74=0,0,H74) -> 0 | N74: =MONTH(A74) -> 1 | O74: =ABS(IF(H74=0,0)) -> 0
A75: 46038 | B75: 3 | C75: =D75 -> MDAC000923 | D75: MDAC000923 | E75: 31 | F75: 314 | G75: PRN14 | H75: 6 | I75: GUILHU | J75: 0 | K75: =VLOOKUP(C75,'CUSTO CONTABIL Dez.24 A Dez.25'!$B:$J,9,0) -> 8.0620621 | L75: =IF(LEFT(C75,4)="mdac",0,IF(LEFT(C75,4)="mdai",0,IF(J75=0,ABS(K75*H75),ABS(J75)))) -> 0 | M75: =IF(L75=0,0,H75) -> 0 | N75: =MONTH(A75) -> 1 | O75: =ABS(IF(H75=0,0)) -> 0
A76: 46038 | B76: 2 | C76: =D76 -> MDAC001314 | D76: MDAC001314 | E76: 31 | F76: 314 | G76: PRN35 | H76: 77 | I76: ALEXANDRE | J76: 0 | K76: =VLOOKUP(C76,'CUSTO CONTABIL Dez.24 A Dez.25'!$B:$J,9,0) -> 7.1067062 | L76: =IF(LEFT(C76,4)="mdac",0,IF(LEFT(C76,4)="mdai",0,IF(J76=0,ABS(K76*H76),ABS(J76)))) -> 0 | M76: =IF(L76=0,0,H76) -> 0 | N76: =MONTH(A76) -> 1 | O76: =ABS(IF(H76=0,0)) -> 0
A77: 46038 | B77: 2 | C77: =D77 -> MDAI000976 | D77: MDAI000976 | E77: 31 | F77: 320 | G77: PRN51 | H77: 25 | I77: KAUÃ | J77: 0 | K77: =VLOOKUP(C77,'CUSTO CONTABIL Dez.24 A Dez.25'!$B:$J,9,0) -> 28.249897 | L77: =IF(LEFT(C77,4)="mdac",0,IF(LEFT(C77,4)="mdai",0,IF(J77=0,ABS(K77*H77),ABS(J77)))) -> 0 | M77: =IF(L77=0,0,H77) -> 0 | N77: =MONTH(A77) -> 1 | O77: =ABS(IF(H77=0,0)) -> 0
A78: 46038 | B78: 2 | C78: =D78 -> MDAC001166 | D78: MDAC001166 | E78: 31 | F78: 313 | G78: PRN36 | H78: 2.7 | I78: JOÃO | J78: 0 | K78: =VLOOKUP(C78,'CUSTO CONTABIL Dez.24 A Dez.25'!$B:$J,9,0) -> 6.0239974 | L78: =IF(LEFT(C78,4)="mdac",0,IF(LEFT(C78,4)="mdai",0,IF(J78=0,ABS(K78*H78),ABS(J78)))) -> 0 | M78: =IF(L78=0,0,H78) -> 0 | N78: =MONTH(A78) -> 1 | O78: =ABS(IF(H78=0,0)) -> 0
A79: 46038 | B79: 2 | C79: =D79 -> MDAC001207 | D79: MDAC001207 | E79: 31 | F79: 320 | G79: GUI02 | H79: 15.5 | I79: LESIDO | J79: 0 | K79: =VLOOKUP(C79,'CUSTO CONTABIL Dez.24 A Dez.25'!$B:$J,9,0) -> 7.798642 | L79: =IF(LEFT(C79,4)="mdac",0,IF(LEFT(C79,4)="mdai",0,IF(J79=0,ABS(K79*H79),ABS(J79)))) -> 0 | M79: =IF(L79=0,0,H79) -> 0 | N79: =MONTH(A79) -> 1 | O79: =ABS(IF(H79=0,0)) -> 0
A80: 46038 | B80: 1 | C80: =D80 -> MDAC001158 | D80: MDAC001158 | E80: 31 | F80: 320 | G80: GUI02 | H80: 4 | I80: JOABES | J80: 0 | K80: 0 | L80: =IF(LEFT(C80,4)="mdac",0,IF(LEFT(C80,4)="mdai",0,IF(J80=0,ABS(K80*H80),ABS(J80)))) -> 0 | M80: =IF(L80=0,0,H80) -> 0 | N80: =MONTH(A80) -> 1 | O80: =ABS(IF(H80=0,0)) -> 0
A81: 46038 | B81: 3 | C81: =D81 -> MDAC001314 | D81: MDAC001314 | E81: 31 | F81: 314 | G81: PRN35 | H81: 134 | I81: ADEMIR | J81: 0 | K81: =VLOOKUP(C81,'CUSTO CONTABIL Dez.24 A Dez.25'!$B:$J,9,0) -> 7.1067062 | L81: =IF(LEFT(C81,4)="mdac",0,IF(LEFT(C81,4)="mdai",0,IF(J81=0,ABS(K81*H81),ABS(J81)))) -> 0 | M81: =IF(L81=0,0,H81) -> 0 | N81: =MONTH(A81) -> 1 | O81: =ABS(IF(H81=0,0)) -> 0
A82: 46039 | B82: 1 | C82: =D82 -> MDAC001208 | D82: MDAC001208 | E82: 31 | F82: 320 | G82: GUI02 | H82: 3.7 | I82: FEL | J82: 0 | K82: =VLOOKUP(C82,'CUSTO CONTABIL Dez.24 A Dez.25'!$B:$J,9,0) -> 8.2893849 | L82: =IF(LEFT(C82,4)="mdac",0,IF(LEFT(C82,4)="mdai",0,IF(J82=0,ABS(K82*H82),ABS(J82)))) -> 0 | M82: =IF(L82=0,0,H82) -> 0 | N82: =MONTH(A82) -> 1 | O82: =ABS(IF(H82=0,0)) -> 0
A83: 46041 | B83: 1 | C83: =D83 -> MDAC001075 | D83: MDAC001075 | E83: 31 | F83: 320 | G83: GUI02 | H83: 67 | I83: JOABES | J83: 0 | K83: =VLOOKUP(C83,'CUSTO CONTABIL Dez.24 A Dez.25'!$B:$J,9,0) -> 7.786003 | L83: =IF(LEFT(C83,4)="mdac",0,IF(LEFT(C83,4)="mdai",0,IF(J83=0,ABS(K83*H83),ABS(J83)))) -> 0 | M83: =IF(L83=0,0,H83) -> 0 | N83: =MONTH(A83) -> 1 | O83: =ABS(IF(H83=0,0)) -> 0
A84: 46041 | B84: 1 | C84: =D84 -> MDAC001314 | D84: MDAC001314 | E84: 31 | F84: 314 | G84: PRN35 | H84: 100 | I84: LUCIANO | J84: 0 | K84: =VLOOKUP(C84,'CUSTO CONTABIL Dez.24 A Dez.25'!$B:$J,9,0) -> 7.1067062 | L84: =IF(LEFT(C84,4)="mdac",0,IF(LEFT(C84,4)="mdai",0,IF(J84=0,ABS(K84*H84),ABS(J84)))) -> 0 | M84: =IF(L84=0,0,H84) -> 0 | N84: =MONTH(A84) -> 1 | O84: =ABS(IF(H84=0,0)) -> 0
A85: 46041 | B85: 1 | C85: =D85 -> MDAC000798 | D85: MDAC000798 | E85: 31 | F85: 320 | G85: PRN35 | H85: 20 | I85: ADEMIR | J85: 0 | K85: 0 | L85: =IF(LEFT(C85,4)="mdac",0,IF(LEFT(C85,4)="mdai",0,IF(J85=0,ABS(K85*H85),ABS(J85)))) -> 0 | M85: =IF(L85=0,0,H85) -> 0 | N85: =MONTH(A85) -> 1 | O85: =ABS(IF(H85=0,0)) -> 0
A86: 46041 | B86: 2 | C86: =D86 -> MDAC001069 | D86: MDAC001069 | E86: 31 | F86: 320 | G86: GUI02 | H86: 6.5 | I86: LESIDO | J86: 0 | K86: =VLOOKUP(C86,'CUSTO CONTABIL Dez.24 A Dez.25'!$B:$J,9,0) -> 6.5280026 | L86: =IF(LEFT(C86,4)="mdac",0,IF(LEFT(C86,4)="mdai",0,IF(J86=0,ABS(K86*H86),ABS(J86)))) -> 0 | M86: =IF(L86=0,0,H86) -> 0 | N86: =MONTH(A86) -> 1 | O86: =ABS(IF(H86=0,0)) -> 0
A87: 46041 | B87: 2 | C87: =D87 -> MDAC000879 | D87: MDAC000879 | E87: 31 | F87: 320 | G87: PRN50 | H87: 23 | I87: LEONARDO | J87: 0 | K87: =VLOOKUP(C87,'CUSTO CONTABIL Dez.24 A Dez.25'!$B:$J,9,0) -> 6.886877 | L87: =IF(LEFT(C87,4)="mdac",0,IF(LEFT(C87,4)="mdai",0,IF(J87=0,ABS(K87*H87),ABS(J87)))) -> 0 | M87: =IF(L87=0,0,H87) -> 0 | N87: =MONTH(A87) -> 1 | O87: =ABS(IF(H87=0,0)) -> 0
A88: 46041 | B88: 2 | C88: =D88 -> MDAC001205 | D88: MDAC001205 | E88: 31 | F88: 320 | G88: GUI02 | H88: 3.5 | I88: LESIDO | J88: 0 | K88: =VLOOKUP(C88,'CUSTO CONTABIL Dez.24 A Dez.25'!$B:$J,9,0) -> 7.7533128 | L88: =IF(LEFT(C88,4)="mdac",0,IF(LEFT(C88,4)="mdai",0,IF(J88=0,ABS(K88*H88),ABS(J88)))) -> 0 | M88: =IF(L88=0,0,H88) -> 0 | N88: =MONTH(A88) -> 1 | O88: =ABS(IF(H88=0,0)) -> 0
A89: 46041 | B89: 2 | C89: =D89 -> MDAI001396 | D89: MDAI001396 | E89: 31 | F89: 320 | G89: PRN51 | H89: 20 | I89: KAUÃ | J89: 0 | K89: =VLOOKUP(C89,'CUSTO CONTABIL Dez.24 A Dez.25'!$B:$J,9,0) -> 22.59135 | L89: =IF(LEFT(C89,4)="mdac",0,IF(LEFT(C89,4)="mdai",0,IF(J89=0,ABS(K89*H89),ABS(J89)))) -> 0 | M89: =IF(L89=0,0,H89) -> 0 | N89: =MONTH(A89) -> 1 | O89: =ABS(IF(H89=0,0)) -> 0
A90: 46041 | B90: 2 | C90: =D90 -> MDAC000923 | D90: MDAC000923 | E90: 31 | F90: 314 | G90: PRN14 | H90: 3 | I90: VINICIUS | J90: 0 | K90: =VLOOKUP(C90,'CUSTO CONTABIL Dez.24 A Dez.25'!$B:$J,9,0) -> 8.0620621 | L90: =IF(LEFT(C90,4)="mdac",0,IF(LEFT(C90,4)="mdai",0,IF(J90=0,ABS(K90*H90),ABS(J90)))) -> 0 | M90: =IF(L90=0,0,H90) -> 0 | N90: =MONTH(A90) -> 1 | O90: =ABS(IF(H90=0,0)) -> 0
A91: 46041 | B91: 2 | C91: =D91 -> MDAI001396 | D91: MDAI001396 | E91: 31 | F91: 320 | G91: PRN51 | H91: 20 | I91: KAUÃ | J91: 0 | K91: =VLOOKUP(C91,'CUSTO CONTABIL Dez.24 A Dez.25'!$B:$J,9,0) -> 22.59135 | L91: =IF(LEFT(C91,4)="mdac",0,IF(LEFT(C91,4)="mdai",0,IF(J91=0,ABS(K91*H91),ABS(J91)))) -> 0 | M91: =IF(L91=0,0,H91) -> 0 | N91: =MONTH(A91) -> 1 | O91: =ABS(IF(H91=0,0)) -> 0
A92: 46041 | B92: 2 | C92: =D92 -> MDAC001195 | D92: MDAC001195 | E92: 31 | F92: 320 | G92: GUI02 | H92: 11 | I92: LESIDO | J92: 0 | K92: =VLOOKUP(C92,'CUSTO CONTABIL Dez.24 A Dez.25'!$B:$J,9,0) -> 7.4797062 | L92: =IF(LEFT(C92,4)="mdac",0,IF(LEFT(C92,4)="mdai",0,IF(J92=0,ABS(K92*H92),ABS(J92)))) -> 0 | M92: =IF(L92=0,0,H92) -> 0 | N92: =MONTH(A92) -> 1 | O92: =ABS(IF(H92=0,0)) -> 0
A93: 46042 | B93: 2 | C93: =D93 -> MDAC001297 | D93: MDAC001297 | E93: 31 | F93: 314 | G93: PRN35 | H93: 47 | I93: ALEXANDRE | J93: 0 | K93: =VLOOKUP(C93,'CUSTO CONTABIL Dez.24 A Dez.25'!$B:$J,9,0) -> 7.1039299 | L93: =IF(LEFT(C93,4)="mdac",0,IF(LEFT(C93,4)="mdai",0,IF(J93=0,ABS(K93*H93),ABS(J93)))) -> 0 | M93: =IF(L93=0,0,H93) -> 0 | N93: =MONTH(A93) -> 1 | O93: =ABS(IF(H93=0,0)) -> 0
A94: 46042 | B94: 2 | C94: =D94 -> MDAC001154 | D94: MDAC001154 | E94: 31 | F94: 314 | G94: PRN14 | H94: 3.5 | I94: VINICIUS | J94: 0 | K94: =VLOOKUP(C94,'CUSTO CONTABIL Dez.24 A Dez.25'!$B:$J,9,0) -> 8.7932875 | L94: =IF(LEFT(C94,4)="mdac",0,IF(LEFT(C94,4)="mdai",0,IF(J94=0,ABS(K94*H94),ABS(J94)))) -> 0 | M94: =IF(L94=0,0,H94) -> 0 | N94: =MONTH(A94) -> 1 | O94: =ABS(IF(H94=0,0)) -> 0
A95: 46042 | B95: 2 | C95: =D95 -> MDAC000598 | D95: MDAC000598 | E95: 31 | F95: 320 | G95: GUI03 | H95: 35 | I95: LESIDO | J95: 0 | K95: =VLOOKUP(C95,'CUSTO CONTABIL Dez.24 A Dez.25'!$B:$J,9,0) -> 7.7361641 | L95: =IF(LEFT(C95,4)="mdac",0,IF(LEFT(C95,4)="mdai",0,IF(J95=0,ABS(K95*H95),ABS(J95)))) -> 0 | M95: =IF(L95=0,0,H95) -> 0 | N95: =MONTH(A95) -> 1 | O95: =ABS(IF(H95=0,0)) -> 0
A96: 46042 | B96: 1 | C96: =D96 -> MDAI001396 | D96: MDAI001396 | E96: 31 | F96: 320 | G96: PRN51 | H96: 20 | I96: MAICON | J96: 0 | K96: =VLOOKUP(C96,'CUSTO CONTABIL Dez.24 A Dez.25'!$B:$J,9,0) -> 22.59135 | L96: =IF(LEFT(C96,4)="mdac",0,IF(LEFT(C96,4)="mdai",0,IF(J96=0,ABS(K96*H96),ABS(J96)))) -> 0 | M96: =IF(L96=0,0,H96) -> 0 | N96: =MONTH(A96) -> 1 | O96: =ABS(IF(H96=0,0)) -> 0
A97: 46042 | B97: 3 | C97: =D97 -> MDAI000935 | D97: MDAI000935 | E97: 31 | F97: 314 | G97: PRN18 | H97: 6.5 | I97: GUILHERME | J97: 0 | K97: =VLOOKUP(C97,'CUSTO CONTABIL Dez.24 A Dez.25'!$B:$J,9,0) -> 11.412386 | L97: =IF(LEFT(C97,4)="mdac",0,IF(LEFT(C97,4)="mdai",0,IF(J97=0,ABS(K97*H97),ABS(J97)))) -> 0 | M97: =IF(L97=0,0,H97) -> 0 | N97: =MONTH(A97) -> 1 | O97: =ABS(IF(H97=0,0)) -> 0
A98: 46042 | B98: 1 | C98: =D98 -> MDAC000793 | D98: MDAC000793 | E98: 31 | F98: 314 | G98: PRN35 | H98: 60 | I98: LUCIANO | J98: 0 | K98: 0 | L98: =IF(LEFT(C98,4)="mdac",0,IF(LEFT(C98,4)="mdai",0,IF(J98=0,ABS(K98*H98),ABS(J98)))) -> 0 | M98: =IF(L98=0,0,H98) -> 0 | N98: =MONTH(A98) -> 1 | O98: =ABS(IF(H98=0,0)) -> 0
A99: 46042 | B99: 3 | C99: =D99 -> MDAC001313 | D99: MDAC001313 | E99: 31 | F99: 320 | G99: PRN35 | H99: 90 | I99: ADEMIR | J99: 0 | K99: =VLOOKUP(C99,'CUSTO CONTABIL Dez.24 A Dez.25'!$B:$J,9,0) -> 7.0930409 | L99: =IF(LEFT(C99,4)="mdac",0,IF(LEFT(C99,4)="mdai",0,IF(J99=0,ABS(K99*H99),ABS(J99)))) -> 0 | M99: =IF(L99=0,0,H99) -> 0 | N99: =MONTH(A99) -> 1 | O99: =ABS(IF(H99=0,0)) -> 0
A100: 46042 | B100: 1 | C100: =D100 -> MDAI001325 | D100: MDAI001325 | E100: 31 | F100: 320 | G100: GUI02 | H100: 17 | I100: JOABES | J100: 0 | K100: =VLOOKUP(C100,'CUSTO CONTABIL Dez.24 A Dez.25'!$B:$J,9,0) -> 16.272928 | L100: =IF(LEFT(C100,4)="mdac",0,IF(LEFT(C100,4)="mdai",0,IF(J100=0,ABS(K100*H100),ABS(J100)))) -> 0 | M100: =IF(L100=0,0,H100) -> 0 | N100: =MONTH(A100) -> 1 | O100: =ABS(IF(H100=0,0)) -> 0
A101: 46042 | B101: 2 | C101: =D101 -> MDAI000935 | D101: MDAI000935 | E101: 31 | F101: 314 | G101: PRN18 | H101: 15 | I101: GILMO | J101: 0 | K101: =VLOOKUP(C101,'CUSTO CONTABIL Dez.24 A Dez.25'!$B:$J,9,0) -> 11.412386 | L101: =IF(LEFT(C101,4)="mdac",0,IF(LEFT(C101,4)="mdai",0,IF(J101=0,ABS(K101*H101),ABS(J101)))) -> 0 | M101: =IF(L101=0,0,H101) -> 0 | N101: =MONTH(A101) -> 1 | O101: =ABS(IF(H101=0,0)) -> 0
A102: 46042 | B102: 2 | C102: =D102 -> MDAI001316 | D102: MDAI001316 | E102: 31 | F102: 320 | G102: GUI02 | H102: 11 | I102: ABNER | J102: 0 | K102: =VLOOKUP(C102,'CUSTO CONTABIL Dez.24 A Dez.25'!$B:$J,9,0) -> 16.28455 | L102: =IF(LEFT(C102,4)="mdac",0,IF(LEFT(C102,4)="mdai",0,IF(J102=0,ABS(K102*H102),ABS(J102)))) -> 0 | M102: =IF(L102=0,0,H102) -> 0 | N102: =MONTH(A102) -> 1 | O102: =ABS(IF(H102=0,0)) -> 0
A103: 46042 | B103: 2 | C103: =D103 -> MDAI001379 | D103: MDAI001379 | E103: 31 | F103: 320 | G103: PRN55 | H103: 10 | I103: EDUARDO | J103: 0 | K103: =VLOOKUP(C103,'CUSTO CONTABIL Dez.24 A Dez.25'!$B:$J,9,0) -> 15.578662 | L103: =IF(LEFT(C103,4)="mdac",0,IF(LEFT(C103,4)="mdai",0,IF(J103=0,ABS(K103*H103),ABS(J103)))) -> 0 | M103: =IF(L103=0,0,H103) -> 0 | N103: =MONTH(A103) -> 1 | O103: =ABS(IF(H103=0,0)) -> 0
A104: 46042 | B104: 2 | C104: =D104 -> MDAC000879 | D104: MDAC000879 | E104: 31 | F104: 320 | G104: PRN50 | H104: 66 | I104: LEONARDO | J104: 0 | K104: =VLOOKUP(C104,'CUSTO CONTABIL Dez.24 A Dez.25'!$B:$J,9,0) -> 6.886877 | L104: =IF(LEFT(C104,4)="mdac",0,IF(LEFT(C104,4)="mdai",0,IF(J104=0,ABS(K104*H104),ABS(J104)))) -> 0 | M104: =IF(L104=0,0,H104) -> 0 | N104: =MONTH(A104) -> 1 | O104: =ABS(IF(H104=0,0)) -> 0
A105: 46042 | B105: 3 | C105: =D105 -> MDAI000935 | D105: MDAI000935 | E105: 31 | F105: 314 | G105: PRN18 | H105: 5.5 | I105: GUILHERME | J105: 0 | K105: =VLOOKUP(C105,'CUSTO CONTABIL Dez.24 A Dez.25'!$B:$J,9,0) -> 11.412386 | L105: =IF(LEFT(C105,4)="mdac",0,IF(LEFT(C105,4)="mdai",0,IF(J105=0,ABS(K105*H105),ABS(J105)))) -> 0 | M105: =IF(L105=0,0,H105) -> 0 | N105: =MONTH(A105) -> 1 | O105: =ABS(IF(H105=0,0)) -> 0
A106: 46043 | B106: 2 | C106: =D106 -> MDAC001050 | D106: MDAC001050 | E106: 31 | F106: 314 | G106: PRN14 | H106: 6 | I106: VINICIUS | J106: 0 | K106: =VLOOKUP(C106,'CUSTO CONTABIL Dez.24 A Dez.25'!$B:$J,9,0) -> 7.8194234 | L106: =IF(LEFT(C106,4)="mdac",0,IF(LEFT(C106,4)="mdai",0,IF(J106=0,ABS(K106*H106),ABS(J106)))) -> 0 | M106: =IF(L106=0,0,H106) -> 0 | N106: =MONTH(A106) -> 1 | O106: =ABS(IF(H106=0,0)) -> 0
A107: 46043 | B107: 2 | C107: =D107 -> MDAC000598 | D107: MDAC000598 | E107: 31 | F107: 320 | G107: GUI03 | H107: 95.5 | I107: LESIDO | J107: 0 | K107: =VLOOKUP(C107,'CUSTO CONTABIL Dez.24 A Dez.25'!$B:$J,9,0) -> 7.7361641 | L107: =IF(LEFT(C107,4)="mdac",0,IF(LEFT(C107,4)="mdai",0,IF(J107=0,ABS(K107*H107),ABS(J107)))) -> 0 | M107: =IF(L107=0,0,H107) -> 0 | N107: =MONTH(A107) -> 1 | O107: =ABS(IF(H107=0,0)) -> 0
A108: 46043 | B108: 2 | C108: =D108 -> MDAI001369 | D108: MDAI001369 | E108: 31 | F108: 320 | G108: PRN40 | H108: 20 | I108: ROGÉRIO | J108: 0 | K108: =VLOOKUP(C108,'CUSTO CONTABIL Dez.24 A Dez.25'!$B:$J,9,0) -> 29.51846 | L108: =IF(LEFT(C108,4)="mdac",0,IF(LEFT(C108,4)="mdai",0,IF(J108=0,ABS(K108*H108),ABS(J108)))) -> 0 | M108: =IF(L108=0,0,H108) -> 0 | N108: =MONTH(A108) -> 1 | O108: =ABS(IF(H108=0,0)) -> 0
A109: 46043 | B109: 2 | C109: =D109 -> MDAC000879 | D109: MDAC000879 | E109: 37 | F109: 320 | G109: PRN50 | H109: 51 | I109: LEONARDO | J109: 0 | K109: =VLOOKUP(C109,'CUSTO CONTABIL Dez.24 A Dez.25'!$B:$J,9,0) -> 6.886877 | L109: =IF(LEFT(C109,4)="mdac",0,IF(LEFT(C109,4)="mdai",0,IF(J109=0,ABS(K109*H109),ABS(J109)))) -> 0 | M109: =IF(L109=0,0,H109) -> 0 | N109: =MONTH(A109) -> 1 | O109: =ABS(IF(H109=0,0)) -> 0
A110: 46043 | B110: 2 | C110: =D110 -> MDAI001342 | D110: MDAI001342 | E110: 31 | F110: 320 | G110: PRN55 | H110: 25 | I110: EDUARDO | J110: 0 | K110: =VLOOKUP(C110,'CUSTO CONTABIL Dez.24 A Dez.25'!$B:$J,9,0) -> 15.56413 | L110: =IF(LEFT(C110,4)="mdac",0,IF(LEFT(C110,4)="mdai",0,IF(J110=0,ABS(K110*H110),ABS(J110)))) -> 0 | M110: =IF(L110=0,0,H110) -> 0 | N110: =MONTH(A110) -> 1 | O110: =ABS(IF(H110=0,0)) -> 0
... A114: 46043 | B114: 1 | C114: =D114 -> MDAC000879 | D114: MDAC000879 | E114: 31 | F114: 320 | G114: PRN50 | H114: 10 | I114: ALEX | J114: 0 | K114: =VLOOKUP(C114,'CUSTO CONTABIL Dez.24 A Dez.25'!$B:$J,9,0) -> 6.886877 | L114: =IF(LEFT(C114,4)="mdac",0,IF(LEFT(C114,4)="mdai",0,IF(J114=0,ABS(K114*H114),ABS(J114)))) -> 0 | M114: =IF(L114=0,0,H114) -> 0 | N114: =MONTH(A114) -> 1 | O114: =ABS(IF(H114=0,0)) -> 0
A115: 46043 | B115: 1 | C115: =D115 -> MDAC001342 | D115: MDAC001342 | E115: 31 | F115: 320 | G115: PRN55 | H115: 12 | I115: KEYLA | J115: 0 | K115: 0 | L115: =IF(LEFT(C115,4)="mdac",0,IF(LEFT(C115,4)="mdai",0,IF(J115=0,ABS(K115*H115),ABS(J115)))) -> 0 | M115: =IF(L115=0,0,H115) -> 0 | N115: =MONTH(A115) -> 1 | O115: =ABS(IF(H115=0,0)) -> 0
A116: 46043 | B116: 2 | C116: =D116 -> MDAC000935 | D116: MDAC000935 | E116: 31 | F116: 314 | G116: PRN18 | H116: 13 | I116: GILMA | J116: 0 | K116: 0 | L116: =IF(LEFT(C116,4)="mdac",0,IF(LEFT(C116,4)="mdai",0,IF(J116=0,ABS(K116*H116),ABS(J116)))) -> 0 | M116: =IF(L116=0,0,H116) -> 0 | N116: =MONTH(A116) -> 1 | O116: =ABS(IF(H116=0,0)) -> 0
A117: 46043 | B117: 1 | C117: =D117 -> MDAC001298 | D117: MDAC001298 | E117: 31 | F117: 314 | G117: PRN35 | H117: 100 | I117: LUCIANO | J117: 0 | K117: =VLOOKUP(C117,'CUSTO CONTABIL Dez.24 A Dez.25'!$B:$J,9,0) -> 7.0900721 | L117: =IF(LEFT(C117,4)="mdac",0,IF(LEFT(C117,4)="mdai",0,IF(J117=0,ABS(K117*H117),ABS(J117)))) -> 0 | M117: =IF(L117=0,0,H117) -> 0 | N117: =MONTH(A117) -> 1 | O117: =ABS(IF(H117=0,0)) -> 0
A118: 46044 | B118: 3 | C118: =D118 -> MDAI001369 | D118: MDAI001369 | E118: 31 | F118: 320 | G118: PRN40 | H118: 20 | I118: RICARDO | J118: 0 | K118: =VLOOKUP(C118,'CUSTO CONTABIL Dez.24 A Dez.25'!$B:$J,9,0) -> 29.51846 | L118: =IF(LEFT(C118,4)="mdac",0,IF(LEFT(C118,4)="mdai",0,IF(J118=0,ABS(K118*H118),ABS(J118)))) -> 0 | M118: =IF(L118=0,0,H118) -> 0 | N118: =MONTH(A118) -> 1 | O118: =ABS(IF(H118=0,0)) -> 0
A119: 46044 | B119: 3 | C119: =D119 -> MDAI001369 | D119: MDAI001369 | E119: 31 | F119: 320 | G119: PRN40 | H119: 21 | I119: RICARDO | J119: 0 | K119: =VLOOKUP(C119,'CUSTO CONTABIL Dez.24 A Dez.25'!$B:$J,9,0) -> 29.51846 | L119: =IF(LEFT(C119,4)="mdac",0,IF(LEFT(C119,4)="mdai",0,IF(J119=0,ABS(K119*H119),ABS(J119)))) -> 0 | M119: =IF(L119=0,0,H119) -> 0 | N119: =MONTH(A119) -> 1 | O119: =ABS(IF(H119=0,0)) -> 0
...

Sheet SPR - QTD
A1: Data | B1: Turno | C1: PN Novo | D1: Produto | E1: Código NC | F1: Setor | G1: Máquina | H1: Qtde | I1: Responsavel | J1: Médio | K1: Média Total | L1: R$/pç | M1: Vlr Total | N1: Mês | O1: QTD
A2: 46025 | B2: 1 | C2: FV10203B | D2: FV10203B | E2: 8 | F2: 322 | G2: LXD001 | H2: 30 | I2: ROMILDO | J2: 0 | K2: 0 | L2: =VLOOKUP(C2,'Custo dos Produtos'!$D:$Q,14,0) -> 36.631275 | M2: =IF(J2=0,ABS(L2*H2),ABS(K2)) -> 1098.9383 | N2: =MONTH(A2) -> 1 | O2: =ABS(IF(M2=0,0,H2)) -> 30 | Q2: =VLOOKUP(C2,Planilha1!$C:$L,10,0) -> #N/A
A3: 46025 | B3: 1 | C3: FQ10179A | D3: FQ10179A | E3: 9 | F3: 320 | G3: PRN55 | H3: 5 | I3: DOUGLAS | J3: 0 | K3: 0 | L3: =VLOOKUP(C3,'Custo dos Produtos'!$D:$Q,14,0) -> 10.47868 | M3: =IF(J3=0,ABS(L3*H3),ABS(K3)) -> 52.3934 | N3: =MONTH(A3) -> 1 | O3: =ABS(IF(M3=0,0,H3)) -> 5 | Q3: =VLOOKUP(C3,Planilha1!$C:$L,10,0) -> 10.686741
A4: 46025 | B4: 1 | C4: FV10136C | D4: FV10136C | E4: 34 | F4: 320 | G4: PRN51 | H4: 29 | I4: ACACIO | J4: 0 | K4: 0 | L4: =VLOOKUP(C4,'Custo dos Produtos'!$D:$Q,14,0) -> 8.166144 | M4: =IF(J4=0,ABS(L4*H4),ABS(K4)) -> 236.81818 | N4: =MONTH(A4) -> 1 | O4: =ABS(IF(M4=0,0,H4)) -> 29 | Q4: =VLOOKUP(C4,Planilha1!$C:$L,10,0) -> 7.7345065
A5: 46027 | B5: 3 | C5: FV10136B | D5: FV10136B | E5: 9 | F5: 320 | G5: PRN40 | H5: 16 | I5: RICARDO | J5: 0 | K5: 0 | L5: =VLOOKUP(C5,'Custo dos Produtos'!$D:$Q,14,0) -> 5.2053074 | M5: =IF(J5=0,ABS(L5*H5),ABS(K5)) -> 83.284919 | N5: =MONTH(A5) -> 1 | O5: =ABS(IF(M5=0,0,H5)) -> 16 | Q5: =VLOOKUP(C5,Planilha1!$C:$L,10,0) -> 4.8911962
A6: 46027 | B6: 2 | C6: FQ10176A | D6: FQ10176A | E6: 31 | F6: 320 | G6: PRN55 | H6: 10 | I6: EDUARDO | J6: 0 | K6: 0 | L6: =VLOOKUP(C6,'Custo dos Produtos'!$D:$Q,14,0) -> 14.576795 | M6: =IF(J6=0,ABS(L6*H6),ABS(K6)) -> 145.76795 | N6: =MONTH(A6) -> 1 | O6: =ABS(IF(M6=0,0,H6)) -> 10 | Q6: =VLOOKUP(C6,Planilha1!$C:$L,10,0) -> 14.802467
A7: 46027 | B7: 2 | C7: FQ10176A | D7: FQ10176A | E7: 20 | F7: 320 | G7: PRN55 | H7: 5 | I7: EDUARDO | J7: 0 | K7: 0 | L7: =VLOOKUP(C7,'Custo dos Produtos'!$D:$Q,14,0) -> 14.576795 | M7: =IF(J7=0,ABS(L7*H7),ABS(K7)) -> 72.883974 | N7: =MONTH(A7) -> 1 | O7: =ABS(IF(M7=0,0,H7)) -> 5 | Q7: =VLOOKUP(C7,Planilha1!$C:$L,10,0) -> 14.802467
A8: 46027 | B8: 2 | C8: HW10151A | D8: HW10151A | E8: 9 | F8: 314 | G8: PRN53 | H8: 2 | I8: DANILO | J8: 0 | K8: 0 | L8: =VLOOKUP(C8,'Custo dos Produtos'!$D:$Q,14,0) -> 8.4691176 | M8: =IF(J8=0,ABS(L8*H8),ABS(K8)) -> 16.938235 | N8: =MONTH(A8) -> 1 | O8: =ABS(IF(M8=0,0,H8)) -> 2 | Q8: =VLOOKUP(C8,Planilha1!$C:$L,10,0) -> 9.4513251
A9: 46027 | B9: 2 | C9: HW10151A | D9: HW10151A | E9: 8 | F9: 314 | G9: PRN53 | H9: 1 | I9: DANILO | J9: 0 | K9: 0 | L9: =VLOOKUP(C9,'Custo dos Produtos'!$D:$Q,14,0) -> 8.4691176 | M9: =IF(J9=0,ABS(L9*H9),ABS(K9)) -> 8.4691176 | N9: =MONTH(A9) -> 1 | O9: =ABS(IF(M9=0,0,H9)) -> 1 | Q9: =VLOOKUP(C9,Planilha1!$C:$L,10,0) -> 9.4513251
A10: 46027 | B10: 2 | C10: HW10151A | D10: HW10151A | E10: 20 | F10: 314 | G10: PRN53 | H10: 1 | I10: DANILO | J10: 0 | K10: 0 | L10: =VLOOKUP(C10,'Custo dos Produtos'!$D:$Q,14,0) -> 8.4691176 | M10: =IF(J10=0,ABS(L10*H10),ABS(K10)) -> 8.4691176 | N10: =MONTH(A10) -> 1 | O10: =ABS(IF(M10=0,0,H10)) -> 1 | Q10: =VLOOKUP(C10,Planilha1!$C:$L,10,0) -> 9.4513251
A11: 46027 | B11: 2 | C11: HW10120A | D11: HW10120A | E11: 27 | F11: 207 | G11: CONTENÇÃO | H11: 6 | I11: JOYCE | J11: 0 | K11: 0 | L11: =VLOOKUP(C11,'Custo dos Produtos'!$D:$Q,14,0) -> 3.0383692 | M11: =IF(J11=0,ABS(L11*H11),ABS(K11)) -> 18.230215 | N11: =MONTH(A11) -> 1 | O11: =ABS(IF(M11=0,0,H11)) -> 6 | Q11: =VLOOKUP(C11,Planilha1!$C:$L,10,0) -> 2.8483244
A12: 46027 | B12: 2 | C12: HW10056A | D12: HW10056A | E12: 11 | F12: 314 | G12: PRN57 | H12: 1 | I12: DANILO | J12: 0 | K12: 0 | L12: =VLOOKUP(C12,'Custo dos Produtos'!$D:$Q,14,0) -> 4.4056159 | M12: =IF(J12=0,ABS(L12*H12),ABS(K12)) -> 4.4056159 | N12: =MONTH(A12) -> 1 | O12: =ABS(IF(M12=0,0,H12)) -> 1 | Q12: =VLOOKUP(C12,Planilha1!$C:$L,10,0) -> 5.1634603
A13: 46027 | B13: 2 | C13: HW10132A | D13: HW10132A | E13: 33 | F13: 314 | G13: PRN52 | H13: 1 | I13: SILVANEX | J13: 0 | K13: 0 | L13: =VLOOKUP(C13,'Custo dos Produtos'!$D:$Q,14,0) -> 7.8916714 | M13: =IF(J13=0,ABS(L13*H13),ABS(K13)) -> 7.8916714 | N13: =MONTH(A13) -> 1 | O13: =ABS(IF(M13=0,0,H13)) -> 1 | Q13: =VLOOKUP(C13,Planilha1!$C:$L,10,0) -> 8.5143739
... A260: 46031 | B260: 1 | C260: BS10073A | D260: BS10073A | E260: 2 | F260: 320 | G260: PRN40 | H260: 5 | I260: PAULO | J260: 0 | K260: 0 | L260: =VLOOKUP(C260,'Custo dos Produtos'!$D:$Q,14,0) -> 4.7478778 | M260: =IF(J260=0,ABS(L260*H260),ABS(K260)) -> 23.739389 | N260: =MONTH(A260) -> 1 | O260: =ABS(IF(M260=0,0,H260)) -> 5 | Q260: =VLOOKUP(C260,Planilha1!$C:$L,10,0) -> 5.1492668
A261: 46031 | B261: 1 | C261: CT10034A | D261: CT10034A | E261: 7 | F261: 207 | G261: CONTENÇÃO | H261: 2 | I261: JACIRA | J261: 0 | K261: 0 | L261: =VLOOKUP(C261,'Custo dos Produtos'!$D:$Q,14,0) -> 4.1205389 | M261: =IF(J261=0,ABS(L261*H261),ABS(K261)) -> 8.2410778 | N261: =MONTH(A261) -> 1 | O261: =ABS(IF(M261=0,0,H261)) -> 2
A262: 46031 | B262: 1 | C262: FV10133B | D262: FV10133B1 | E262: 2 | F262: 321 | G262: LAV05 | H262: 1 | I262: ADEILDO | J262: 0 | K262: 0 | L262: =VLOOKUP(C262,'Custo dos Produtos'!$D:$Q,14,0) -> 12.45558 | M262: =IF(J262=0,ABS(L262*H262),ABS(K262)) -> 12.45558 | N262: =MONTH(A262) -> 1 | O262: =ABS(IF(M262=0,0,H262)) -> 1
A263: 46031 | B263: 1 | C263: HW10143A | D263: HW10143A | E263: 11 | F263: 314 | G263: PRN58 | H263: 1 | I263: VIKTOR | J263: 0 | K263: 0 | L263: =VLOOKUP(C263,'Custo dos Produtos'!$D:$Q,14,0) -> 19.479727 | M263: =IF(J263=0,ABS(L263*H263),ABS(K263)) -> 19.479727 | N263: =MONTH(A263) -> 1 | O263: =ABS(IF(M263=0,0,H263)) -> 1
A264: 46031 | B264: 1 | C264: HW10143A | D264: HW10143A | E264: 8 | F264: 314 | G264: PRN58 | H264: 5 | I264: VIKTOR | J264: 0 | K264: 0 | L264: =VLOOKUP(C264,'Custo dos Produtos'!$D:$Q,14,0) -> 19.479727 | M264: =IF(J264=0,ABS(L264*H264),ABS(K264)) -> 97.398636 | N264: =MONTH(A264) -> 1 | O264: =ABS(IF(M264=0,0,H264)) -> 5
A265: 46031 | B265: 1 | C265: CT10018B | D265: CT10018B | E265: 19 | F265: 320 | G265: PRN51 | H265: 8 | I265: EDUARDO | J265: 0 | K265: 0 | L265: =VLOOKUP(C265,'Custo dos Produtos'!$D:$Q,14,0) -> 8.81 | M265: =IF(J265=0,ABS(L265*H265),ABS(K265)) -> 70.48 | N265: =MONTH(A265) -> 1 | O265: =ABS(IF(M265=0,0,H265)) -> 8
A266: 46031 | B266: 1 | C266: CT10018B | D266: CT10018B | E266: 31 | F266: 320 | G266: PRN51 | H266: 3 | I266: EDUARDO | J266: 0 | K266: 0 | L266: =VLOOKUP(C266,'Custo dos Produtos'!$D:$Q,14,0) -> 8.81 | M266: =IF(J266=0,ABS(L266*H266),ABS(K266)) -> 26.43 | N266: =MONTH(A266) -> 1 | O266: =ABS(IF(M266=0,0,H266)) -> 3
A267: 46031 | B267: 1 | C267: CT10018B | D267: CT10018B | E267: 9 | F267: 320 | G267: PRN51 | H267: 8 | I267: EDUARDO | J267: 0 | K267: 0 | L267: =VLOOKUP(C267,'Custo dos Produtos'!$D:$Q,14,0) -> 8.81 | M267: =IF(J267=0,ABS(L267*H267),ABS(K267)) -> 70.48 | N267: =MONTH(A267) -> 1 | O267: =ABS(IF(M267=0,0,H267)) -> 8
A268: 46031 | B268: 1 | C268: HW10061A | D268: HW10061A | E268: 20 | F268: 315 | G268: PON11 | H268: 118 | I268: HENRIQUE | J268: 0 | K268: 0 | L268: =VLOOKUP(C268,'Custo dos Produtos'!$D:$Q,14,0) -> 2.1285172 | M268: =IF(J268=0,ABS(L268*H268),ABS(K268)) -> 251.16503 | N268: =MONTH(A268) -> 1 | O268: =ABS(IF(M268=0,0,H268)) -> 118
A269: 46031 | B269: 1 | C269: HW10088A | D269: HW10088A | E269: 33 | F269: 314 | G269: PRN52 | H269: 3 | I269: JHONY | J269: 0 | K269: 0 | L269: =VLOOKUP(C269,'Custo dos Produtos'!$D:$Q,14,0) -> 17.029657 | M269: =IF(J269=0,ABS(L269*H269),ABS(K269)) -> 51.08897 | N269: =MONTH(A269) -> 1 | O269: =ABS(IF(M269=0,0,H269)) -> 3
A270: 46032 | B270: 1 | C270: HW10052A | D270: HW10052A | E270: 27 | F270: 207 | G270: CONTENÇÃO | H270: 2 | I270: GLEUSA | J270: 0 | K270: 0 | L270: =VLOOKUP(C270,'Custo dos Produtos'!$D:$Q,14,0) -> 7.4821308 | M270: =IF(J270=0,ABS(L270*H270),ABS(K270)) -> 14.964262 | N270: =MONTH(A270) -> 1 | O270: =ABS(IF(M270=0,0,H270)) -> 2
A271: 46034 | B271: 1 | C271: FV10137A | D271: FV10137A | E271: 20 | F271: 314 | G271: PRN57 | H271: 1 | I271: LUCAS | J271: 0 | K271: 0 | L271: =VLOOKUP(C271,'Custo dos Produtos'!$D:$Q,14,0) -> 16.658545 | M271: =IF(J271=0,ABS(L271*H271),ABS(K271)) -> 16.658545 | N271: =MONTH(A271) -> 1 | O271: =ABS(IF(M271=0,0,H271)) -> 1
A272: 46034 | B272: 1 | C272: FV10138A | D272: FV10138A | E272: 8 | F272: 314 | G272: PRN57 | H272: 10 | I272: LUCAS | J272: 0 | K272: 0 | L272: =VLOOKUP(C272,'Custo dos Produtos'!$D:$Q,14,0) -> 13.672727 | M272: =IF(J272=0,ABS(L272*H272),ABS(K272)) -> 136.72727 | N272: =MONTH(A272) -> 1 | O272: =ABS(IF(M272=0,0,H272)) -> 10
... A500: 46038 | B500: 2 | C500: HW10058A | D500: HW10058A | E500: 36 | F500: 217 | G500: PON11 | H500: 16 | I500: VAL | J500: 0 | K500: 0 | L500: =VLOOKUP(C500,'Custo dos Produtos'!$D:$Q,14,0) -> 1.6376854 | M500: =IF(J500=0,ABS(L500*H500),ABS(K500)) -> 26.202966 | N500: =MONTH(A500) -> 1 | O500: =ABS(IF(M500=0,0,H500)) -> 16
A501: 46038 | B501: 3 | C501: VO10067B | D501: VO10067B | E501: 36 | F501: 217 | G501: PRN49 | H501: 1 | I501: CLAUDIO | J501: 0 | K501: 0 | L501: 0 | M501: =IF(J501=0,ABS(L501*H501),ABS(K501)) -> 0 | N501: =MONTH(A501) -> 1 | O501: =ABS(IF(M501=0,0,H501)) -> 0
A502: 46038 | B502: 1 | C502: PU10023A | D502: PU10023A | E502: 36 | F502: 217 | G502: PON04 | H502: 4 | I502: WILSON | J502: 0 | K502: 0 | L502: =VLOOKUP(C502,'Custo dos Produtos'!$D:$Q,14,0) -> 5.5965668 | M502: =IF(J502=0,ABS(L502*H502),ABS(K502)) -> 22.386267 | N502: =MONTH(A502) -> 1 | O502: =ABS(IF(M502=0,0,H502)) -> 4
A503: 46038 | B503: 2 | C503: VO10067B | D503: VO10067B | E503: 36 | F503: 217 | G503: PON04 | H503: 1 | I503: VAL | J503: 0 | K503: 0 | L503: 0 | M503: =IF(J503=0,ABS(L503*H503),ABS(K503)) -> 0 | N503: =MONTH(A503) -> 1 | O503: =ABS(IF(M503=0,0,H503)) -> 0
A504: 46038 | B504: 3 | C504: HW10058A | D504: HW10058A | E504: 36 | F504: 217 | G504: PON11 | H504: 16 | I504: CLAUDIO | J504: 0 | K504: 0 | L504: =VLOOKUP(C504,'Custo dos Produtos'!$D:$Q,14,0) -> 1.6376854 | M504: =IF(J504=0,ABS(L504*H504),ABS(K504)) -> 26.202966 | N504: =MONTH(A504) -> 1 | O504: =ABS(IF(M504=0,0,H504)) -> 16
A505: 46038 | B505: 1 | C505: HW10041A | D505: HW10041A | E505: 36 | F505: 217 | G505: PON10 | H505: 8 | I505: WILSON | J505: 0 | K505: 0 | L505: =VLOOKUP(C505,'Custo dos Produtos'!$D:$Q,14,0) -> 4.8558533 | M505: =IF(J505=0,ABS(L505*H505),ABS(K505)) -> 38.846827 | N505: =MONTH(A505) -> 1 | O505: =ABS(IF(M505=0,0,H505)) -> 8
A506: 46038 | B506: 1 | C506: HW10053A | D506: HW10053A | E506: 36 | F506: 217 | G506: PON10 | H506: 8 | I506: WS | J506: 0 | K506: 0 | L506: =VLOOKUP(C506,'Custo dos Produtos'!$D:$Q,14,0) -> 4.41 | M506: =IF(J506=0,ABS(L506*H506),ABS(K506)) -> 35.28 | N506: =MONTH(A506) -> 1 | O506: =ABS(IF(M506=0,0,H506)) -> 8
A507: 46038 | B507: 1 | C507: HW10118A | D507: HW10118A | E507: 36 | F507: 217 | G507: PON11 | H507: 16 | I507: WS | J507: 0 | K507: 0 | L507: 0 | M507: =IF(J507=0,ABS(L507*H507),ABS(K507)) -> 0 | N507: =MONTH(A507) -> 1 | O507: =ABS(IF(M507=0,0,H507)) -> 0
A508: 46038 | B508: 1 | C508: HW10119A | D508: HW10119A | E508: 44 | F508: 318 | G508: SOL34 | H508: 6 | I508: RAYNAN | J508: 0 | K508: 0 | L508: =VLOOKUP(C508,'Custo dos Produtos'!$D:$Q,14,0) -> 2.1993369 | M508: =IF(J508=0,ABS(L508*H508),ABS(K508)) -> 13.196021 | N508: =MONTH(A508) -> 1 | O508: =ABS(IF(M508=0,0,H508)) -> 6
A509: 46038 | B509: 1 | C509: FV10133A | D509: FV10133A | E509: 36 | F509: 217 | G509: PON09 | H509: 4 | I509: WILSON | J509: 0 | K509: 0 | L509: =VLOOKUP(C509,'Custo dos Produtos'!$D:$Q,14,0) -> 32.70066 | M509: =IF(J509=0,ABS(L509*H509),ABS(K509)) -> 130.80264 | N509: =MONTH(A509) -> 1 | O509: =ABS(IF(M509=0,0,H509)) -> 4
A510: 46038 | B510: 2 | C510: FV10144A | D510: FV10144A | E510: 36 | F510: 217 | G510: PON01 | H510: 2 | I510: VAL | J510: 0 | K510: 0 | L510: =VLOOKUP(C510,'Custo dos Produtos'!$D:$Q,14,0) -> 15.13088 | M510: =IF(J510=0,ABS(L510*H510),ABS(K510)) -> 30.26176 | N510: =MONTH(A510) -> 1 | O510: =ABS(IF(M510=0,0,H510)) -> 2
A511: 46038 | B511: 3 | C511: FV10144A | D511: FV10144A | E511: 36 | F511: 217 | G511: PON01 | H511: 1 | I511: CLAUDIO | J511: 0 | K511: 0 | L511: =VLOOKUP(C511,'Custo dos Produtos'!$D:$Q,14,0) -> 15.13088 | M511: =IF(J511=0,ABS(L511*H511),ABS(K511)) -> 15.13088 | N511: =MONTH(A511) -> 1 | O511: =ABS(IF(M511=0,0,H511)) -> 1
A512: 46038 | B512: 3 | C512: WH10355A | D512: WH10355A | E512: 2 | F512: 315 | G512: SOL02 | H512: 3 | I512: GENILSON | J512: 0 | K512: 0 | L512: =VLOOKUP(C512,'Custo dos Produtos'!$D:$Q,14,0) -> 3.6518 | M512: =IF(J512=0,ABS(L512*H512),ABS(K512)) -> 10.9554 | N512: =MONTH(A512) -> 1 | O512: =ABS(IF(M512=0,0,H512)) -> 3
A513: 46038 | B513: 2 | C513: CT10018A | D513: CT10018A | E513: 9 | F513: 313 | G513: PRN22 | H513: 5 | I513: AMANDA | J513: 0 | K513: 0 | L513: =VLOOKUP(C513,'Custo dos Produtos'!$D:$Q,14,0) -> 14.972824 | M513: =IF(J513=0,ABS(L513*H513),ABS(K513)) -> 74.86412 | N513: =MONTH(A513) -> 1 | O513: =ABS(IF(M513=0,0,H513)) -> 5
A514: 46038 | B514: 2 | C514: CT10010A | D514: CT10010A | E514: 7 | F514: 313 | G514: PRN28 | H514: 1 | I514: JOÃO | J514: 0 | K514: 0 | L514: =VLOOKUP(C514,'Custo dos Produtos'!$D:$Q,14,0) -> 10.757986 | M514: =IF(J514=0,ABS(L514*H514),ABS(K514)) -> 10.757986 | N514: =MONTH(A514) -> 1 | O514: =ABS(IF(M514=0,0,H514)) -> 1
A515: 46038 | B515: 2 | C515: CT10018A | D515: CT10018A | E515: 19 | F515: 313 | G515: PRN22 | H515: 1 | I515: ELIANE | J515: 0 | K515: 0 | L515: =VLOOKUP(C515,'Custo dos Produtos'!$D:$Q,14,0) -> 14.972824 | M515: =IF(J515=0,ABS(L515*H515),ABS(K515)) -> 14.972824 | N515: =MONTH(A515) -> 1 | O515: =ABS(IF(M515=0,0,H515)) -> 1
A516: 46038 | B516: 2 | C516: CT10018B | D516: CT10018B | E516: 6 | F516: 313 | G516: PRN22 | H516: 1 | I516: AMANDA | J516: 0 | K516: 0 | L516: =VLOOKUP(C516,'Custo dos Produtos'!$D:$Q,14,0) -> 8.81 | M516: =IF(J516=0,ABS(L516*H516),ABS(K516)) -> 8.81 | N516: =MONTH(A516) -> 1 | O516: =ABS(IF(M516=0,0,H516)) -> 1
A517: 46038 | B517: 2 | C517: CT10018B | D517: CT10018B | E517: 6 | F517: 313 | G517: PRN22 | H517: 1 | I517: JÉSSICA | J517: 0 | K517: 0 | L517: =VLOOKUP(C517,'Custo dos Produtos'!$D:$Q,14,0) -> 8.81 | M517: =IF(J517=0,ABS(L517*H517),ABS(K517)) -> 8.81 | N517: =MONTH(A517) -> 1 | O517: =ABS(IF(M517=0,0,H517)) -> 1
A518: 46038 | B518: 2 | C518: HW10077A | D518: HW10077A | E518: 20 | F518: 314 | G518: PRN52 | H518: 1 | I518: SILVANEX | J518: 0 | K518: 0 | L518: =VLOOKUP(C518,'Custo dos Produtos'!$D:$Q,14,0) -> 8.85255 | M518: =IF(J518=0,ABS(L518*H518),ABS(K518)) -> 8.85255 | N518: =MONTH(A518) -> 1 | O518: =ABS(IF(M518=0,0,H518)) -> 1
A519: 46038 | B519: 2 | C519: BR10061B | D519: BR10061B | E519: 31 | F519: 314 | G519: PRN35 | H519: 16 | I519: ALEXANDRE | J519: 0 | K519: 0 | L519: =VLOOKUP(C519,'Custo dos Produtos'!$D:$Q,14,0) -> 0.33851587 | M519: =IF(J519=0,ABS(L519*H519),ABS(K519)) -> 5.416254 | N519: =MONTH(A519) -> 1 | O519: =ABS(IF(M519=0,0,H519)) -> 16
... A525: 46038 | B525: 1 | C525: FV10192B | D525: FV10192B | E525: 20 | F525: 217 | G525: PRN54 | H525: 13 | I525: GLEUSA | J525: 0 | K525: 0 | L525: =VLOOKUP(C525,'Custo dos Produtos'!$D:$Q,14,0) -> 23.16 | M525: =IF(J525=0,ABS(L525*H525),ABS(K525)) -> 301.08 | N525: =MONTH(A525) -> 1 | O525: =ABS(IF(M525=0,0,H525)) -> 13
A526: 46038 | B526: 1 | C526: MR10029B | D526: MR10029B | E526: 32 | F526: 314 | G526: PRN52 | H526: 4 | I526: MARCOS | J526: 0 | K526: 0 | L526: 0 | M526: =IF(J526=0,ABS(L526*H526),ABS(K526)) -> 0 | N526: =MONTH(A526) -> 1 | O526: =ABS(IF(M526=0,0,H526)) -> 0
A527: 46038 | B527: 3 | C527: CT10010B | D527: CT10010B | E527: 20 | F527: 320 | G527: PRN50 | H527: 1 | I527: LUCAS | J527: 0 | K527: 0 | L527: =VLOOKUP(C527,'Custo dos Produtos'!$D:$Q,14,0) -> 6.7208333 | M527: =IF(J527=0,ABS(L527*H527),ABS(K527)) -> 6.7208333 | N527: =MONTH(A527) -> 1 | O527: =ABS(IF(M527=0,0,H527)) -> 1
A528: 46040 | B528: 1 | C528: FV10133A | D528: FV10133A | E528: 36 | F528: 217 | G528: PON09 | H528: 4 | I528: WILSON | J528: 0 | K528: 0 | L528: =VLOOKUP(C528,'Custo dos Produtos'!$D:$Q,14,0) -> 32.70066 | M528: =IF(J528=0,ABS(L528*H528),ABS(K528)) -> 130.80264 | N528: =MONTH(A528) -> 1 | O528: =ABS(IF(M528=0,0,H528)) -> 4
A529: 46041 | B529: 2 | C529: HW10061A | D529: HW10061A | E529: 36 | F529: 217 | G529: PON11 | H529: 14 | I529: VAL | J529: 0 | K529: 0 | L529: =VLOOKUP(C529,'Custo dos Produtos'!$D:$Q,14,0) -> 2.1285172 | M529: =IF(J529=0,ABS(L529*H529),ABS(K529)) -> 29.799241 | N529: =MONTH(A529) -> 1 | O529: =ABS(IF(M529=0,0,H529)) -> 14
A530: 46041 | B530: 3 | C530: FV10133A | D530: FV10133A | E530: 36 | F530: 217 | G530: PON09 | H530: 1 | I530: CLAUDIO | J530: 0 | K530: 0 | L530: =VLOOKUP(C530,'Custo dos Produtos'!$D:$Q,14,0) -> 32.70066 | M530: =IF(J530=0,ABS(L530*H530),ABS(K530)) -> 32.70066 | N530: =MONTH(A530) -> 1 | O530: =ABS(IF(M530=0,0,H530)) -> 1
A531: 46041 | B531: 3 | C531: HW10042A | D531: HW10042A | E531: 36 | F531: 217 | G531: PON10 | H531: 4 | I531: CLAUDIO | J531: 0 | K531: 0 | L531: =VLOOKUP(C531,'Custo dos Produtos'!$D:$Q,14,0) -> 4.8550723 | M531: =IF(J531=0,ABS(L531*H531),ABS(K531)) -> 19.420289 | N531: =MONTH(A531) -> 1 | O531: =ABS(IF(M531=0,0,H531)) -> 4
A532: 46041 | B532: 3 | C532: HW10061A | D532: HW10061A | E532: 36 | F532: 217 | G532: PON11 | H532: 16 | I532: CLAUDIO | J532: 0 | K532: 0 | L532: =VLOOKUP(C532,'Custo dos Produtos'!$D:$Q,14,0) -> 2.1285172 | M532: =IF(J532=0,ABS(L532*H532),ABS(K532)) -> 34.056276 | N532: =MONTH(A532) -> 1 | O532: =ABS(IF(M532=0,0,H532)) -> 16
A533: 46041 | B533: 3 | C533: CT10010A | D533: CT10010A | E533: 36 | F533: 217 | G533: PRN28 | H533: 2 | I533: GUSTAVO | J533: 0 | K533: 0 | L533: =VLOOKUP(C533,'Custo dos Produtos'!$D:$Q,14,0) -> 10.757986 | M533: =IF(J533=0,ABS(L533*H533),ABS(K533)) -> 21.515972 | N533: =MONTH(A533) -> 1 | O533: =ABS(IF(M533=0,0,H533)) -> 2
A534: 46041 | B534: 2 | C534: VO10011A | D534: VO10011A | E534: 36 | F534: 217 | G534: PON01 | H534: 1 | I534: VAL | J534: 0 | K534: 0 | L534: =VLOOKUP(C534,'Custo dos Produtos'!$D:$Q,14,0) -> 24.099259 | M534: =IF(J534=0,ABS(L534*H534),ABS(K534)) -> 24.099259 | N534: =MONTH(A534) -> 1 | O534: =ABS(IF(M534=0,0,H534)) -> 1
A535: 46041 | B535: 2 | C535: CT10031A | D535: CT10031A | E535: 20 | F535: 207 | G535: CONTENÇÃO | H535: 2 | I535: LUANA/FELIPE | J535: 0 | K535: 0 | L535: =VLOOKUP(C535,'Custo dos Produtos'!$D:$Q,14,0) -> 0.37613034 | M535: =IF(J535=0,ABS(L535*H535),ABS(K535)) -> 0.75226068 | N535: =MONTH(A535) -> 1 | O535: =ABS(IF(M535=0,0,H535)) -> 2
A536: 46041 | B536: 2 | C536: CT10031A | D536: CT10031A | E536: 34 | F536: 207 | G536: CONTENÇÃO | H536: 1 | I536: LUANA/FELIPE | J536: 0 | K536: 0 | L536: =VLOOKUP(C536,'Custo dos Produtos'!$D:$Q,14,0) -> 0.37613034 | M536: =IF(J536=0,ABS(L536*H536),ABS(K536)) -> 0.37613034 | N536: =MONTH(A536) -> 1 | O536: =ABS(IF(M536=0,0,H536)) -> 1
A537: 46041 | B537: 2 | C537: CT10031A | D537: CT10031A | E537: 8 | F537: 207 | G537: CONTENÇÃO | H537: 12 | I537: LUANA/FELIPE | J537: 0 | K537: 0 | L537: =VLOOKUP(C537,'Custo dos Produtos'!$D:$Q,14,0) -> 0.37613034 | M537: =IF(J537=0,ABS(L537*H537),ABS(K537)) -> 4.5135641 | N537: =MONTH(A537) -> 1 | O537: =ABS(IF(M537=0,0,H537)) -> 12
A538: 46041 | B538: 2 | C538: CT10034A | D538: CT10034A | E538: 1 | F538: 207 | G538: CONTENÇÃO | H538: 18 | I538: LUANA | J538: 0 | K538: 0 | L538: =VLOOKUP(C538,'Custo dos Produtos'!$D:$Q,14,0) -> 4.1205389 | M538: =IF(J538=0,ABS(L538*H538),ABS(K538)) -> 74.1697 | N538: =MONTH(A538) -> 1 | O538: =ABS(IF(M538=0,0,H538)) -> 18
... A577: 46041 | B577: 1 | C577: FV10193B | D577: FV10193B | E577: 31 | F577: 320 | G577: PRN40 | H577: 6 | I577: PAULO | J577: 0 | K577: 0 | L577: =VLOOKUP(C577,'Custo dos Produtos'!$D:$Q,14,0) -> 6.3155144 | M577: =IF(J577=0,ABS(L577*H577),ABS(K577)) -> 37.893086 | N577: =MONTH(A577) -> 1 | O577: =ABS(IF(M577=0,0,H577)) -> 6
A578: 46041 | B578: 1 | C578: HW10006B | D578: HW10006B | E578: 44 | F578: 318 | G578: SOL34 | H578: 4 | I578: RAYNAN | J578: 0 | K578: 0 | L578: 0 | M578: =IF(J578=0,ABS(L578*H578),ABS(K578)) -> 0 | N578: =MONTH(A578) -> 1 | O578: =ABS(IF(M578=0,0,H578)) -> 0
A579: 46041 | B579: 1 | C579: HW10149A | D579: HW10149A | E579: 33 | F579: 314 | G579: PRN58 | H579: 4 | I579: VIKTOR | J579: 0 | K579: 0 | L579: =VLOOKUP(C579,'Custo dos Produtos'!$D:$Q,14,0) -> 16.1454 | M579: =IF(J579=0,ABS(L579*H579),ABS(K579)) -> 64.5816 | N579: =MONTH(A579) -> 1 | O579: =ABS(IF(M579=0,0,H579)) -> 4
A580: 46041 | B580: 1 | C580: HW10149A | D580: HW10149A | E580: 11 | F580: 314 | G580: PRN58 | H580: 1 | I580: VIKTOR | J580: 0 | K580: 0 | L580: =VLOOKUP(C580,'Custo dos Produtos'!$D:$Q,14,0) -> 16.1454 | M580: =IF(J580=0,ABS(L580*H580),ABS(K580)) -> 16.1454 | N580: =MONTH(A580) -> 1 | O580: =ABS(IF(M580=0,0,H580)) -> 1
A581: 46041 | B581: 1 | C581: HW10039A | D581: HW10039A | E581: 33 | F581: 314 | G581: PRN53 | H581: 3 | I581: GUSTAVO | J581: 0 | K581: 0 | L581: =VLOOKUP(C581,'Custo dos Produtos'!$D:$Q,14,0) -> 11.199277 | M581: =IF(J581=0,ABS(L581*H581),ABS(K581)) -> 33.597831 | N581: =MONTH(A581) -> 1 | O581: =ABS(IF(M581=0,0,H581)) -> 3
A582: 46041 | B582: 1 | C582: CT10018A | D582: CT10018A | E582: 27 | F582: 313 | G582: PRN22 | H582: 1 | I582: MARRYLER/VALERIA | J582: 0 | K582: 0 | L582: =VLOOKUP(C582,'Custo dos Produtos'!$D:$Q,14,0) -> 14.972824 | M582: =IF(J582=0,ABS(L582*H582),ABS(K582)) -> 14.972824 | N582: =MONTH(A582) -> 1 | O582: =ABS(IF(M582=0,0,H582)) -> 1
A583: 46041 | B583: 1 | C583: CT10018A | D583: CT10018A | E583: 9 | F583: 313 | G583: PRN22 | H583: 3 | I583: MARRYLER/VALERIA | J583: 0 | K583: 0 | L583: =VLOOKUP(C583,'Custo dos Produtos'!$D:$Q,14,0) -> 14.972824 | M583: =IF(J583=0,ABS(L583*H583),ABS(K583)) -> 44.918472 | N583: =MONTH(A583) -> 1 | O583: =ABS(IF(M583=0,0,H583)) -> 3
A584: 46041 | B584: 1 | C584: FV10153A | D584: FV10153A | E584: 19 | F584: 313 | G584: PRN24 | H584: 1 | I584: VANESSA | J584: 0 | K584: 0 | L584: =VLOOKUP(C584,'Custo dos Produtos'!$D:$Q,14,0) -> 4.1948012 | M584: =IF(J584=0,ABS(L584*H584),ABS(K584)) -> 4.1948012 | N584: =MONTH(A584) -> 1 | O584: =ABS(IF(M584=0,0,H584)) -> 1
A585: 46041 | B585: 1 | C585: FV10153A | D585: FV10153A | E585: 20 | F585: 313 | G585: PRN24 | H585: 1 | I585: VANESSA | J585: 0 | K585: 0 | L585: =VLOOKUP(C585,'Custo dos Produtos'!$D:$Q,14,0) -> 4.1948012 | M585: =IF(J585=0,ABS(L585*H585),ABS(K585)) -> 4.1948012 | N585: =MONTH(A585) -> 1 | O585: =ABS(IF(M585=0,0,H585)) -> 1
A586: 46041 | B586: 1 | C586: CT10010B | D586: CT10010B | E586: 7 | F586: 313 | G586: PRN28 | H586: 11 | I586: STEFANY | J586: 0 | K586: 0 | L586: =VLOOKUP(C586,'Custo dos Produtos'!$D:$Q,14,0) -> 6.7208333 | M586: =IF(J586=0,ABS(L586*H586),ABS(K586)) -> 73.929167 | N586: =MONTH(A586) -> 1 | O586: =ABS(IF(M586=0,0,H586)) -> 11
A587: 46041 | B587: 1 | C587: MR10007B | D587: MR10007B | E587: 34 | F587: 314 | G587: PRN17 | H587: 15 | I587: JANATA | J587: 0 | K587: 0 | L587: =VLOOKUP(C587,'Custo dos Produtos'!$D:$Q,14,0) -> 17.44 | M587: =IF(J587=0,ABS(L587*H587),ABS(K587)) -> 261.6 | N587: =MONTH(A587) -> 1 | O587: =ABS(IF(M587=0,0,H587)) -> 15
A588: 46042 | B588: 1 | C588: MR10007B | D588: MR10007B | E588: 20 | F588: 314 | G588: PRN17 | H588: 63 | I588: JANATA | J588: 0 | K588: 0 | L588: =VLOOKUP(C588,'Custo dos Produtos'!$D:$Q,14,0) -> 17.44 | M588: =IF(J588=0,ABS(L588*H588),ABS(K588)) -> 1098.72 | N588: =MONTH(A588) -> 1 | O588: =ABS(IF(M588=0,0,H588)) -> 63
A589: 46042 | B589: 1 | C589: CT10034A | D589: CT10034A | E589: 2 | F589: 207 | G589: CONTENÇÃO | H589: 62 | I589: FRANCIELE/WAGNER | J589: 0 | K589: 0 | L589: =VLOOKUP(C589,'Custo dos Produtos'!$D:$Q,14,0) -> 4.1205389 | M589: =IF(J589=0,ABS(L589*H589),ABS(K589)) -> 255.47341 | N589: =MONTH(A589) -> 1 | O589: =ABS(IF(M589=0,0,H589)) -> 62
A590: 46042 | B590: 1 | C590: CT10034A | D590: CT10034A | E590: 9 | F590: 207 | G590: CONTENÇÃO | H590: 14 | I590: FRANCIELE/WAGNER | J590: 0 | K590: 0 | L590: =VLOOKUP(C590,'Custo dos Produtos'!$D:$Q,14,0) -> 4.1205389 | M590: =IF(J590=0,ABS(L590*H590),ABS(K590)) -> 57.687544 | N590: =MONTH(A590) -> 1 | O590: =ABS(IF(M590=0,0,H590)) -> 14
... A604: 46042 | B604: 1 | C604: CT10018A | D604: CT10018A | E604: 9 | F604: 313 | G604: PRN22 | H604: 5 | I604: VALÉRIA/MARRYLER | J604: 0 | K604: 0 | L604: =VLOOKUP(C604,'Custo dos Produtos'!$D:$Q,14,0) -> 14.972824 | M604: =IF(J604=0,ABS(L604*H604),ABS(K604)) -> 74.86412 | N604: =MONTH(A604) -> 1 | O604: =ABS(IF(M604=0,0,H604)) -> 5
A605: 46042 | B605: 1 | C605: CT10018A | D605: CT10018A | E605: 35 | F605: 313 | G605: PRN22 | H605: 1 | I605: VALÉRIA/MARRYLER | J605: 0 | K605: 0 | L605: 0 | M605: =IF(J605=0,ABS(L605*H605),ABS(K605)) -> 0 | N605: =MONTH(A605) -> 1 | O605: =ABS(IF(M605=0,0,H605)) -> 0
A606: 46042 | B606: 1 | C606: CT10018B | D606: CT10018B | E606: 9 | F606: 320 | G606: PRN50 | H606: 5 | I606: ALEX | J606: 0 | K606: 0 | L606: =VLOOKUP(C606,'Custo dos Produtos'!$D:$Q,14,0) -> 8.81 | M606: =IF(J606=0,ABS(L606*H606),ABS(K606)) -> 44.05 | N606: =MONTH(A606) -> 1 | O606: =ABS(IF(M606=0,0,H606)) -> 5
A607: 46042 | B607: 1 | C607: CT10018B | D607: CT10018B | E607: 11 | F607: 320 | G607: PRN50 | H607: 5 | I607: ALEX | J607: 0 | K607: 0 | L607: =VLOOKUP(C607,'Custo dos Produtos'!$D:$Q,14,0) -> 8.81 | M607: =IF(J607=0,ABS(L607*H607),ABS(K607)) -> 44.05 | N607: =MONTH(A607) -> 1 | O607: =ABS(IF(M607=0,0,H607)) -> 5
A608: 46042 | B608: 1 | C608: CT10010B | D608: CT10010B | E608: 35 | F608: 313 | G608: PRN28 | H608: 4 | I608: MAGDA/STEFANY | J608: 0 | K608: 0 | L608: =VLOOKUP(C608,'Custo dos Produtos'!$D:$Q,14,0) -> 6.7208333 | M608: =IF(J608=0,ABS(L608*H608),ABS(K608)) -> 26.883333 | N608: =MONTH(A608) -> 1 | O608: =ABS(IF(M608=0,0,H608)) -> 4
A609: 46042 | B609: 1 | C609: CT10010B | D609: CT10010B | E609: 19 | F609: 313 | G609: PRN28 | H609: 1 | I609: MAGDA/STEFANY | J609: 0 | K609: 0 | L609: =VLOOKUP(C609,'Custo dos Produtos'!$D:$Q,14,0) -> 6.7208333 | M609: =IF(J609=0,ABS(L609*H609),ABS(K609)) -> 6.7208333 | N609: =MONTH(A609) -> 1 | O609: =ABS(IF(M609=0,0,H609)) -> 1
A610: 46042 | B610: 1 | C610: CT10010B | D610: CT10010B | E610: 31 | F610: 320 | G610: PRN50 | H610: 15 | I610: ALEX | J610: 0 | K610: 0 | L610: =VLOOKUP(C610,'Custo dos Produtos'!$D:$Q,14,0) -> 6.7208333 | M610: =IF(J610=0,ABS(L610*H610),ABS(K610)) -> 100.8125 | N610: =MONTH(A610) -> 1 | O610: =ABS(IF(M610=0,0,H610)) -> 15
A611: 46042 | B611: 1 | C611: FV10192B | D611: FV10192B | E611: 2 | F611: 321 | G611: LAV05 | H611: 1 | I611: ADULDO | J611: 0 | K611: 0 | L611: =VLOOKUP(C611,'Custo dos Produtos'!$D:$Q,14,0) -> 23.16 | M611: =IF(J611=0,ABS(L611*H611),ABS(K611)) -> 23.16 | N611: =MONTH(A611) -> 1 | O611: =ABS(IF(M611=0,0,H611)) -> 1
A612: 46042 | B612: 1 | C612: MR10006B | D612: MR10006B | E612: 9 | F612: 322 | G612: INSULATION | H612: 1 | I612: JACIRA | J612: 0 | K612: 0 | L612: =VLOOKUP(C612,'Custo dos Produtos'!$D:$Q,14,0) -> 18.3335 | M612: =IF(J612=0,ABS(L612*H612),ABS(K612)) -> 18.3335 | N612: =MONTH(A612) -> 1 | O612: =ABS(IF(M612=0,0,H612)) -> 1
A613: 46042 | B613: 1 | C613: HW10061A | D613: HW10061A | E613: 20 | F613: 315 | G613: PON11 | H613: 1 | I613: EMERSON | J613: 0 | K613: 0 | L613: =VLOOKUP(C613,'Custo dos Produtos'!$D:$Q,14,0) -> 2.1285172 | M613: =IF(J613=0,ABS(L613*H613),ABS(K613)) -> 2.1285172 | N613: =MONTH(A613) -> 1 | O613: =ABS(IF(M613=0,0,H613)) -> 1
A614: 46042 | B614: 3 | C614: CT10010A | D614: CT10010A | E614: 36 | F614: 217 | G614: PRN28 | H614: 1 | I614: GUSTAVO | J614: 0 | K614: 0 | L614: =VLOOKUP(C614,'Custo dos Produtos'!$D:$Q,14,0) -> 10.757986 | M614: =IF(J614=0,ABS(L614*H614),ABS(K614)) -> 10.757986 | N614: =MONTH(A614) -> 1 | O614: =ABS(IF(M614=0,0,H614)) -> 1
A615: 46042 | B615: 1 | C615: FV10144A | D615: FV10144A | E615: 36 | F615: 217 | G615: PON12 | H615: 4 | I615: WILSON | J615: 0 | K615: 0 | L615: =VLOOKUP(C615,'Custo dos Produtos'!$D:$Q,14,0) -> 15.13088 | M615: =IF(J615=0,ABS(L615*H615),ABS(K615)) -> 60.52352 | N615: =MONTH(A615) -> 1 | O615: =ABS(IF(M615=0,0,H615)) -> 4
A616: 46042 | B616: 1 | C616: FV10133A | D616: FV10133A | E616: 36 | F616: 217 | G616: PON09 | H616: 4 | I616: WILSON | J616: 0 | K616: 0 | L616: =VLOOKUP(C616,'Custo dos Produtos'!$D:$Q,14,0) -> 32.70066 | M616: =IF(J616=0,ABS(L616*H616),ABS(K616)) -> 130.80264 | N616: =MONTH(A616) -> 1 | O616: =ABS(IF(M616=0,0,H616)) -> 4
A617: 46042 | B617: 1 | C617: HW10061A | D617: HW10061A | E617: 36 | F617: 217 | G617: PON11 | H617: 16 | I617: WILSON | J617: 0 | K617: 0 | L617: =VLOOKUP(C617,'Custo dos Produtos'!$D:$Q,14,0) -> 2.1285172 | M617: =IF(J617=0,ABS(L617*H617),ABS(K617)) -> 34.056276 | N617: =MONTH(A617) -> 1 | O617: =ABS(IF(M617=0,0,H617)) -> 16
... A764: 46044 | B764: 3 | C764: PU10004A | D764: PU10004A | E764: 8 | F764: 314 | G764: PRN29 | H764: 1 | I764: GUILHERME | J764: 0 | K764: 0 | L764: =VLOOKUP(C764,'Custo dos Produtos'!$D:$Q,14,0) -> 5.2860327 | M764: =IF(J764=0,ABS(L764*H764),ABS(K764)) -> 5.2860327 | N764: =MONTH(A764) -> 1 | O764: =ABS(IF(M764=0,0,H764)) -> 1
A765: 46044 | B765: 2 | D765: HW10067A | E765: 11 | F765: 313 | G765: PRN36 | H765: 7 | I765: RODRIGO F.
A766: 46044 | B766: 2 | D766: HW10067A | E766: 2 | F766: 313 | G766: PRN24 | H766: 3 | I766: DANILO/KAUA
A767: 46044 | B767: 2 | D767: HW10067A | E767: 11 | F767: 313 | G767: PRN24 | H767: 2 | I767: DANILO/KAUA
A768: 46044 | B768: 1 | D768: HW10060A | E768: 44 | F768: 318 | G768: PON11 | H768: 4 | I768: RAYNAN
A769: 46044 | B769: 1 | D769: WH10355B | E769: 36 | F769: 315 | G769: PRN36 | H769: 2 | I769: ANA
A770: 46044 | B770: 1 | D770: WH10352A | E770: 8 | F770: 315 | G770: PRN18 | H770: 1 | I770: ANA
A771: 46045 | B771: 2 | C771: HW10052A | D771: HW10052A | E771: 36 | F771: 217 | G771: PON10 | H771: 4 | I771: VAL | J771: 0 | K771: 0 | L771: =VLOOKUP(C771,'Custo dos Produtos'!$D:$Q,14,0) -> 7.4821308 | M771: =IF(J771=0,ABS(L771*H771),ABS(K771)) -> 29.928523 | N771: =MONTH(A771) -> 1 | O771: =ABS(IF(M771=0,0,H771)) -> 4
A772: 46045 | B772: 1 | C772: HW10119A | D772: HW10119A | E772: 36 | F772: 217 | G772: PON11 | H772: 16 | I772: WILSON | J772: 0 | K772: 0 | L772: =VLOOKUP(C772,'Custo dos Produtos'!$D:$Q,14,0) -> 2.1993369 | M772: =IF(J772=0,ABS(L772*H772),ABS(K772)) -> 35.18939 | N772: =MONTH(A772) -> 1 | O772: =ABS(IF(M772=0,0,H772)) -> 16
A773: 46045 | B773: 1 | C773: MR10019A | D773: MR10019A | E773: 36 | F773: 217 | G773: PON04 | H773: 2 | I773: WILSON | J773: 0 | K773: 0 | L773: =VLOOKUP(C773,'Custo dos Produtos'!$D:$Q,14,0) -> 5.4660584 | M773: =IF(J773=0,ABS(L773*H773),ABS(K773)) -> 10.932117 | N773: =MONTH(A773) -> 1 | O773: =ABS(IF(M773=0,0,H773)) -> 2
A774: 46045 | B774: 2 | C774: HW10071A | D774: HW10071A | E774: 36 | F774: 217 | G774: PON12 | H774: 2 | I774: VAL | J774: 0 | K774: 0 | L774: =VLOOKUP(C774,'Custo dos Produtos'!$D:$Q,14,0) -> 8.45852 | M774: =IF(J774=0,ABS(L774*H774),ABS(K774)) -> 16.91704 | N774: =MONTH(A774) -> 1 | O774: =ABS(IF(M774=0,0,H774)) -> 2
A775: 46045 | B775: 2 | C775: HW10051A | D775: HW10051A | E775: 36 | F775: 217 | G775: PON10 | H775: 4 | I775: VAL | J775: 0 | K775: 0 | L775: =VLOOKUP(C775,'Custo dos Produtos'!$D:$Q,14,0) -> 6.58 | M775: =IF(J775=0,ABS(L775*H775),ABS(K775)) -> 26.32 | N775: =MONTH(A775) -> 1 | O775: =ABS(IF(M775=0,0,H775)) -> 4
...

Sheet CUSTO CONTABIL Dez.24 A Dez.25
A1: PN ANTIGO | B1: CODIGO | C1: TP | D1: GRUPO | E1: DESCRICAO | F1: U.M. | G1: FL | H1: ARMZ | I1: SALDO_x000D_ EM ESTOQUE | J1: EMPENHO PARA_x000D_ REQ/PV/RESERVA | K1: ESTOQUE_x000D_ DISPONIVEL | L1: VALOR_x000D_ EM ESTOQUE | M1: VALOR_x000D_ EMPENHADO
A2: =LEFT(E2,9) -> ARV000020 | B2: FV10020A | C2: PA | D2: 0508 | E2: ARV000020-E4050051 - SCJ SUPORTE CAT ROCAM | F2: PC | G2: 0101 | H2: ** | I2: 579 | J2: =L2/I2 -> 1.7469085 | K2: 579 | L2: 1011.46 | M2: 0
A3: =LEFT(E3,9) -> ARV000030 | B3: FV10030A | C3: PA | D3: 0508 | E3: ARV000030-E4050336 - SEPARADOR B | F3: PC | G3: 0101 | H3: ** | I3: 31 | J3: =L3/I3 -> 2.8219355 | K3: 31 | L3: 87.48 | M3: 0
A4: =LEFT(E4,9) -> ARV000035 | B4: FV10035A | C4: PA | D4: 0508 | E4: ARV000035-229.712 - TAMPA DE ENTRADA/SAIDA | F4: PC | G4: 0101 | H4: ** | I4: 283 | J4: =L4/I4 -> 5.6061131 | K4: 283 | L4: 1586.53 | M4: 0
A5: =LEFT(E5,9) -> ARV000038 | B5: FV10038A | C5: PA | D5: 0508 | E5: ARV000038-E4042491 - TAMPA DE ENTRADA | F5: PC | G5: 0101 | H5: ** | I5: 501 | J5: =L5/I5 -> 18.771158 | K5: 501 | L5: 9404.35 | M5: 0
A6: =LEFT(E6,9) -> ARV000042 | B6: FV10042A | C6: PA | D6: 0508 | E6: ARV000042-E4042496 - SEPARADOR A | F6: PC | G6: 0101 | H6: ** | I6: 45 | J6: =L6/I6 -> 2.8824444 | K6: 45 | L6: 129.71 | M6: 0
A7: =LEFT(E7,9) -> ARV000043 | B7: FV10043A | C7: PA | D7: 0508 | E7: ARV000043-E4042497 - SEPARADOR B | F7: PC | G7: 0101 | H7: ** | I7: 94 | J7: =L7/I7 -> 2.8854255 | K7: 94 | L7: 271.23 | M7: 0
A8: =LEFT(E8,9) -> ARV000048 | B8: FV10048A | C8: PA | D8: 0508 | E8: ARV000048-E4060792 - FLANGE DE ENTRADA | F8: PC | G8: 0101 | H8: ** | I8: 369 | J8: =L8/I8 -> 7.5214634 | K8: 369 | L8: 2775.42 | M8: 0
A9: =LEFT(E9,9) -> ARV000050 | B9: FV10050A | C9: PA | D9: 0508 | E9: ARV000050-E4073955BR - DISCO | F9: PC | G9: 0101 | H9: ** | I9: 3288 | J9: =L9/I9 -> 2.9123114 | K9: 3288 | L9: 9575.68 | M9: 0
A10: =LEFT(E10,9) -> ARV000051 | B10: FV10051A | C10: PA | D10: 0508 | E10: ARV000051-E4074193BR - TAMPA | F10: PC | G10: 0101 | H10: ** | I10: 2280 | J10: =L10/I10 -> 3.3481096 | K10: 2280 | L10: 7633.69 | M10: 0
A11: =LEFT(E11,9) -> ARV000056 | B11: FV10056A | C11: PA | D11: 0508 | E11: ARV000056-E4079605 - CONE C/ FURO | F11: PC | G11: 0101 | H11: ** | I11: 99 | J11: =L11/I11 -> 98.400808 | K11: 99 | L11: 9741.68 | M11: 0
A12: =LEFT(E12,9) -> ARV000057 | B12: FV10057A | C12: PA | D12: 0508 | E12: ARV000057-E4079606 - CONE S/ FURO | F12: PC | G12: 0101 | H12: ** | I12: 99 | J12: =L12/I12 -> 98.400808 | K12: 99 | L12: 9741.68 | M12: 0
A13: =LEFT(E13,9) -> ARV000060 | B13: FV10060A | C13: PA | D13: 0508 | E13: ARV000060-E4079570 - FLANGE | F13: PC | G13: 0101 | H13: ** | I13: 58 | J13: =L13/I13 -> 5.0877586 | K13: 58 | L13: 295.09 | M13: 0
... A131: =LEFT(E131,9) -> BRO000090 | B131: BR10090A | C131: TP | D131: 0722 | E131: BRO000090-E43284-103 - REAR LH - ESTAMPADO C/ PARAFUSO | F131: PC | G131: 0101 | H131: ** | I131: 7560 | J131: =L131/I131 -> 1.0177024 | K131: 7560 | L131: 7693.83 | M131: 0
A132: =LEFT(E132,10) -> CFEL000603 | B132: VO10053B1 | C132: PP | D132: 0515 | E132: CFEL000603-21563761 - STABILIZER BAR - ESTAMPADO | F132: PC | G132: 0101 | H132: ** | I132: 195 | J132: =L132/I132 -> 9.3584615 | K132: 195 | L132: 1824.9 | M132: 0
A133: =LEFT(E133,10) -> CFEL000626 | B133: PU10018H | C133: PP | D133: 0508 | E133: CFEL000626-ESTAMPAGEM DA PECA 1 P/ E4078050 | F133: PC | G133: 0101 | H133: ** | I133: 250 | J133: =L133/I133 -> 1.197 | K133: 250 | L133: 299.25 | M133: 0
A134: =LEFT(E134,10) -> CFEL000693 | B134: BS10074B | C134: PP | D134: 0525 | E134: CFEL000693-F000.ZS4.001 - ABRACADEIRA - ESTAMPADA | F134: PC | G134: 0101 | H134: ** | I134: 667 | J134: =L134/I134 -> 3.7756672 | K134: 667 | L134: 2518.37 | M134: 0
A135: =LEFT(E135,10) -> CFEL000698 | B135: TN10084B | C135: PP | D135: 0514 | E135: CFEL000698-82092215 - CONCHA INFERIOR [OF TNC000084] | F135: PC | G135: 0101 | H135: ** | I135: 630 | J135: =L135/I135 -> 15.049841 | K135: 630 | L135: 9481.4 | M135: 0
A136: =LEFT(E136,10) -> CFEL000711 | B136: BR10052B1 | C136: PP | D136: 0722 | E136: CFEL000711-C80622-104 - FRONT RH - ESTAMPADO | F136: PC | G136: 0101 | H136: ** | I136: 919 | J136: =L136/I136 -> 0.29931447 | K136: 919 | L136: 275.07 | M136: 0
A137: =LEFT(E137,10) -> CFEL000712 | B137: BR10053B1 | C137: PP | D137: 0722 | E137: CFEL000712-C80623-104 - FRONT LH - ESTAMPADO | F137: PC | G137: 0101 | H137: ** | I137: 3160 | J137: =L137/I137 -> 0.29931646 | K137: 3160 | L137: 945.84 | M137: 0
A138: =LEFT(E138,10) -> CFEL000714 | B138: BR10054B | C138: PP | D138: 0722 | E138: CFEL000714-C80624-103 - REAR RH - ESTAMPADO | F138: PC | G138: 0101 | H138: ** | I138: 4570 | J138: =L138/I138 -> 0.26224289 | K138: 4570 | L138: 1198.45 | M138: 0
A139: =LEFT(E139,10) -> CFEL000730 | B139: BR10061B | C139: PP | D139: 0722 | E139: CFEL000730-C09089-102 GUIDE RAIL MANUAL POWER FRONT 2D RH - NF - ESTAMPADO | F139: PC | G139: 0101 | H139: ** | I139: 2219 | J139: =L139/I139 -> 0.37711131 | K139: 2219 | L139: 836.81 | M139: 0
A140: =LEFT(E140,10) -> CFEL000731 | B140: BR10062B | C140: PP | D140: 0722 | E140: CFEL000731-C09088-102 GUIDE RAIL MANUAL POWER FRONT 2D LH - NF - ESTAMPADO | F140: PC | G140: 0101 | H140: ** | I140: 2083 | J140: =L140/I140 -> 0.25086414 | K140: 2083 | L140: 522.55 | M140: 0
A141: =LEFT(E141,10) -> CFEL000756 | B141: HW10061B | C141: PP | D141: 0529 | E141: CFEL000756-64438-R1000 - BRKT WIPER PIVOT SIDE MTG - ESTAMPADO | F141: PC | G141: 0101 | H141: ** | I141: 1 | J141: =L141/I141 -> 1.58 | K141: -15643 | L141: 1.58 | M141: 24717.52
A142: =LEFT(E142,10) -> CFEL000769 | B142: HW10026B | C142: PP | D142: 0529 | E142: CFEL000769-BLANK P/ 65516-M4000 - HWS000026 - 0,70 X 212 X 806 | F142: PC | G142: 0101 | H142: ** | I142: 970 | J142: =L142/I142 -> 6.7594536 | K142: 970 | L142: 6556.67 | M142: 0
A143: =LEFT(E143,10) -> CFEL000774 | B143: HW10072B | C143: PP | D143: 0529 | E143: CFEL000774-64522-BV000 - PNL FNDR APRON INR FR RH | F143: PC | G143: 0101 | H143: ** | I143: 300 | J143: =L143/I143 -> 9.3320333 | K143: 284 | L143: 2799.61 | M143: 149.31
... A188: =LEFT(E188,10) -> CFSB000575 | B188: VO10079B | C188: PP | D188: 0515 | E188: CFSB000575-24512453 - BRACKET P/24484490 - PINTADO | F188: PC | G188: 0101 | H188: ** | I188: 2 | J188: =L188/I188 -> 54.215 | K188: 2 | L188: 108.43 | M188: 0
A189: =LEFT(E189,9) -> CNH000002 | B189: CN10002A | C189: PA | D189: 0535 | E189: CNH000002-47600200 - SUPPORT, CHAFF PAN, REAR | F189: PC | G189: 0101 | H189: ** | I189: 7 | J189: =L189/I189 -> 33.434286 | K189: 7 | L189: 234.04 | M189: 0
A190: =LEFT(E190,9) -> CNH000003 | B190: CN10003A | C190: PA | D190: 0535 | E190: CNH000003-47761377 - DEFLECTOR, STRAW SPREADER - FRONT | F190: PC | G190: 0101 | H190: ** | I190: 40 | J190: =L190/I190 -> 111.8005 | K190: 40 | L190: 4472.02 | M190: 0
A191: =LEFT(E191,9) -> CNH000004 | B191: CN10004A | C191: PA | D191: 0535 | E191: CNH000004-47761375 - DEFLECTOR, STRAW SPREADER - FRONT | F191: PC | G191: 0101 | H191: ** | I191: 65 | J191: =L191/I191 -> 110.98523 | K191: 65 | L191: 7214.04 | M191: 0
A192: =LEFT(E192,9) -> CNH000005 | B192: CN10005A | C192: PA | D192: 0535 | E192: CNH000005-47836795 - SUPPORT FRONT BEARING | F192: PC | G192: 0101 | H192: ** | I192: 128 | J192: =L192/I192 -> 238.22891 | K192: 128 | L192: 30493.3 | M192: 0
A193: =LEFT(E193,9) -> CON000010 | B193: CT10010A | C193: PA | D193: 0518 | E193: CON000010-20.5600-0040.2-95 - CARCACA DE VACUO CPL-PSA (SEM PINTURA) | F193: PC | G193: 0101 | H193: ** | I193: 7704 | J193: =L193/I193 -> 11.581665 | K193: 7704 | L193: 89225.15 | M193: 0
A194: =LEFT(E194,9) -> CON000013 | B194: CT10013A | C194: PA | D194: 0518 | E194: CON000013-20.5600-0029.2-95 - CARCACA CPL 9 (SEM PINTURA) | F194: PC | G194: 0101 | H194: ** | I194: 401 | J194: =L194/I194 -> 12.433067 | K194: 401 | L194: 4985.66 | M194: 0
A195: =LEFT(E195,9) -> CON000018 | B195: CT10018A | C195: PA | D195: 0518 | E195: CON000018-20.5600-0084.2-95 - CARCACA CPL (SEM PINTURA) | F195: PC | G195: 0101 | H195: ** | I195: 2738 | J195: =L195/I195 -> 14.892111 | K195: 2738 | L195: 40774.6 | M195: 0
A196: =LEFT(E196,9) -> CON000028 | B196: CT10028A | C196: PA | D196: 0518 | E196: CON000028-20.5300-2059.1 - CABLE GUIDE LH - ZINCADO | F196: PC | G196: 0101 | H196: ** | I196: 16278 | J196: =L196/I196 -> 0.60202236 | K196: 16278 | L196: 9799.72 | M196: 0
A197: =LEFT(E197,9) -> CON000029 | B197: CT10029A | C197: PA | D197: 0518 | E197: CON000029-20.5300-2060.1 - CABLE GUIDE RH - ZINCADO | F197: PC | G197: 0101 | H197: ** | I197: 7050 | J197: =L197/I197 -> 0.45393191 | K197: 7050 | L197: 3200.22 | M197: 0
A198: =LEFT(E198,9) -> CON000030 | B198: CT10030A | C198: PA | D198: 0518 | E198: CON000030-20.5320-8248.1 - PARKING BRAKE LEVER RH - ZINCADO | F198: PC | G198: 0101 | H198: ** | I198: 251 | J198: =L198/I198 -> 4.1482869 | K198: 251 | L198: 1041.22 | M198: 0
A199: =LEFT(E199,9) -> CON000031 | B199: CT10031A | C199: PA | D199: 0518 | E199: CON000031-20.5320-8247.1 - PARKING BRAKE LEVER LH - ZINCADO | F199: PC | G199: 0101 | H199: ** | I199: 2390 | J199: =L199/I199 -> 1.0247406 | K199: 2390 | L199: 2449.13 | M199: 0
A200: =LEFT(E200,9) -> CON000032 | B200: CT10032A | C200: PA | D200: 0518 | E200: CON000032-20.5320-7894.1 - BRAKE SHOE TABLE TRAIL | F200: PC | G200: 0101 | H200: ** | I200: 3765 | J200: =L200/I200 -> 1.3523718 | K200: 3765 | L200: 5091.68 | M200: 0
... A1987: =LEFT(E1987,9) -> VOL000079 | B1987: VO10079A | C1987: PA | D1987: 0536 | E1987: VOL000079-16.32.012.851.021A - 24484490 - HEAT SHIELD REAR - MONTADO | F1987: PC | G1987: 0101 | H1987: ** | I1987: 5 | J1987: =L1987/I1987 -> 153.764 | K1987: 5 | L1987: 768.82 | M1987: 0

Sheet Custo dos Produtos
A1: FILIAL | B1: TP MOVIMENTO | C1: Descrica | D1: Produto | E1: DESCRICAO | F1: TIPO | G1: UNIDADE | H1: QUANTIDADE | I1: TIPO RE/DE | J1: ARMAZEM | K1: SEQUENCIAL | L1: DOCUMENTO | M1: ORD PRODUCAO | N1: DT EMISSAO | O1: SEQ.RECALC. | P1: CUSTO | Q1: CUSTO UN
A2: 0101 | B2: 010 | C2: =LEFT(E2,9) -> ARV000176 | D2: FQ10176A | E2: ARV000176-1060312X - CUSHION PAN | F2: PA | G2: PC | H2: 1950 | I2: PR0 | J2: 40 | K2: 000133 | L2: 000004 | M2: 00000401001 | N2: 45870 | O2: 20250801038301 | P2: 28424.75 | Q2: 14.576795
A3: 0101 | B3: 010 | C3: =LEFT(E3,9) -> ARV000199 | D3: FV10199A | E3: ARV000199-331165606X - END CAP INLET BAFFLE ASSEMBLY | F3: PA | G3: PC | H3: 23 | I3: PR0 | J3: 40 | K3: 000966 | L3: 000002 | M3: 00000201001 | N3: 45870 | O3: 20250801038268 | P3: 3242.87 | Q3: 140.99435
A4: 0101 | B4: 010 | C4: =LEFT(E4,9) -> ARV000201 | D4: FV10201A | E4: ARV000201-338968204X - END CAP OUTLET BAFFLE ASSEMBLY | F4: PA | G4: PC | H4: 17 | I4: PR0 | J4: 40 | K4: 000814 | L4: 000003 | M4: 00000301001 | N4: 45870 | O4: 20250801038288 | P4: 2389.29 | Q4: 140.54647
A5: 0101 | B5: 010 | C5: =LEFT(E5,9) -> BOS000073 | D5: BS10073A | E5: BOS000073-F006.U20.201 - CARCACA WSM3 | F5: PA | G5: PC | H5: 900 | I5: PR0 | J5: 40 | K5: 001803 | L5: 000034 | M5: 00003401001 | N5: 45871 | O5: 20250801040465 | P5: 4273.09 | Q5: 4.7478778
A6: 0101 | B6: 010 | C6: =LEFT(E6,9) -> CON000034 | D6: CT10034A | E6: CON000034-20.5600-0206.1 DIAPHRAGM PLATE 225 SINGLE | F6: PA | G6: PC | H6: 1800 | I6: PR0 | J6: 40 | K6: 003860 | L6: 000095 | M6: 00009501001 | N6: 45873 | O6: 20250801042894 | P6: 7416.97 | Q6: 4.1205389
A7: 0101 | B7: 010 | C7: =LEFT(E7,9) -> ARV000137 | D7: FV10137A | E7: ARV000137-1981970X - OUTLET CONE UPPER HALF SHELL | F7: PA | G7: PC | H7: 550 | I7: PR0 | J7: 40 | K7: 003562 | L7: 000148 | M7: 00014801001 | N7: 45873 | O7: 20250801047961 | P7: 9162.2 | Q7: 16.658545
A8: 0101 | B8: 100 | C8: =LEFT(E8,9) -> ARV000138 | D8: FV10138A | E8: ARV000138-1981972X - OUTLET CONE LOWER HALF SHELL | F8: PA | G8: PC | H8: 550 | I8: PR0 | J8: 40 | K8: 003577 | L8: 000149 | M8: 00014901001 | N8: 45873 | O8: 20250801048033 | P8: 7520 | Q8: 13.672727
A9: 0101 | B9: 010 | C9: =LEFT(E9,9) -> ARV000165 | D9: FV10165A | E9: ARV000165-306954101X - CONE ASSY - SOLDADO | F9: PA | G9: PC | H9: 1200 | I9: PR0 | J9: 40 | K9: 003666 | L9: 000018 | M9: 00001801001 | N9: 45873 | O9: 20250801038580 | P9: 18432.24 | Q9: 15.3602
A10: 0101 | B10: 010 | C10: =LEFT(E10,9) -> ARV000193 | D10: FV10193A | E10: ARV000193-363417102X - CONE OUTLET | F10: PA | G10: PC | H10: 749 | I10: PR0 | J10: 40 | K10: 003809 | L10: 000051 | M10: 00005101001 | N10: 45873 | O10: 20250801040855 | P10: 5114.5 | Q10: 6.8284379
A11: 0101 | B11: 010 | C11: =LEFT(E11,9) -> ARV000211 | D11: FV10211A | E11: ARV000211-434347102X - INLET CONE | F11: PA | G11: PC | H11: 655 | I11: PR0 | J11: 40 | K11: 004160 | L11: 000171 | M11: 00017101001 | N11: 45873 | O11: 20250801048380 | P11: 6591.4 | Q11: 10.063206
A12: 0101 | B12: 010 | C12: =LEFT(E12,9) -> ARV000230 | D12: FV10230A | E12: ARV000230-488882301X - SUB ASSY MANIFOLD TOP AND BOTTOM SHELL | F12: PA | G12: PC | H12: 200 | I12: PR0 | J12: 40 | K12: 004069 | L12: 000038 | M12: 00003801001 | N12: 45873 | O12: 20250801040619 | P12: 8220.24 | Q12: 41.1012
A13: 0101 | B13: 010 | C13: =LEFT(E13,9) -> HWS000040 | D13: HW10040A | E13: HWS000040-65845-C9000 - SUPORTE EXTERNO DIR. UTILIZADO NO ASSOALHO TRASEIRO | F13: PA | G13: PC | H13: 400 | I13: PR0 | J13: 40 | K13: 003614 | L13: 000150 | M13: 00015001001 | N13: 45873 | O13: 20250801048069 | P13: 4476.96 | Q13: 11.1924
... A210: 0101 | B210: 010 | C210: =LEFT(E210,9) -> VOL000013 | D210: VO10013A | E210: VOL000013-20789328 - BRACKET ASSY GUARD PLATE | F210: PA | G210: PC | H210: 560 | I210: PR0 | J210: 40 | K210: 108497 | L210: 002502010 | M210: 00250201001 | N210: 45929 | O210: 20250901103955 | P210: 4073.59 | Q210: 7.2742679
A211: 0101 | B211: 100 | C211: =LEFT(E211,10) -> VOL000045- | D211: VO10045A | E211: VOL000045-82835067 - BRACKET, WATER RESERVOIR | F211: PA | G211: PC | H211: 964 | I211: PR0 | J211: 40 | K211: 108495 | L211: 002501010 | M211: 00250101001 | N211: 45929 | O211: 20250901103950 | P211: 28834.73 | Q211: 29.911546
A212: 0101 | B212: 010 | C212: =LEFT(E212,10) -> VOL000078- | D212: VO10078A | E212: VOL000078-78813916 - BRACKET REINFORCEMENT ASSY CAB | F212: PA | G212: PC | H212: 640 | I212: PR0 | J212: 40 | K212: 109324 | L212: 002509 | M212: 00250901001 | N212: 45930 | O212: 20250901103998 | P212: 3866.19 | Q212: 6.0409219
A213: 0101 | B213: 100 | C213: =LEFT(E213,10) -> CNH000002- | D213: CN10002A | E213: CNH000002-47600200 - SUPPORT, CHAFF PAN, REAR | F213: PA | G213: PC | H213: 115 | I213: PR0 | J213: 40 | K213: 112366 | L213: 002496 | M213: 00249601001 | N213: 45931 | O213: 20250901103884 | P213: 3046.62 | Q213: 26.492348
A214: 0101 | B214: 100 | C214: =LEFT(E214,10) -> PRM000015- | D214: PU10015A | E214: PRM000015-11.47.013.851.000B - HEAT SHIELD - SG551-C0020 | F214: PA | G214: PC | H214: 50 | I214: PR0 | J214: 40 | K214: 112303 | L214: 002529 | M214: 00252901001 | N214: 45931 | O214: 20250901105012 | P214: 222.71 | Q214: 4.4542
A215: 0101 | B215: 010 | C215: =LEFT(E215,10) -> VOL000023- | D215: VO10023A | E215: VOL000023-20743332 P03 - BRACKET COOLING COIL | F215: PA | G215: PC | H215: 2184 | I215: PR0 | J215: 40 | K215: 114267 | L215: 002543010 | M215: 00254301001 | N215: 45932 | O215: 20250901105692 | P215: 9050.47 | Q215: 4.1439881
A216: 0101 | B216: 010 | C216: =LEFT(E216,10) -> ARV000215- | D216: FV10215A | E216: ARV000215-470571701X - HALF SHELL EVAPORATOR TUBE UPPER | F216: PA | G216: PC | H216: 160 | I216: PR0 | J216: 40 | K216: 116736 | L216: 002562 | M216: 00256201001 | N216: 45933 | O216: 20250901106084 | P216: 4200.14 | Q216: 26.250875
A217: 0101 | B217: 010 | C217: =LEFT(E217,10) -> VOL000008- | D217: VO10008A | E217: VOL000008-20799745 P02 - UNDERCARRIAGE UPPER | F217: PA | G217: PC | H217: 113 | I217: PR0 | J217: 40 | K217: 117342 | L217: 002401 | M217: 00240101001 | N217: 45933 | O217: 20250901100799 | P217: 1098.16 | Q217: 9.7182301
A218: 0101 | B218: 100 | C218: =LEFT(E218,10) -> VOL000009- | D218: VO10009A | E218: VOL000009-20800122 P02 - UNDERCARRIAGE UPPER | F218: PA | G218: PC | H218: 113 | I218: PR0 | J218: 40 | K218: 117346 | L218: 002402 | M218: 00240201001 | N218: 45933 | O218: 20250901100815 | P218: 1098.16 | Q218: 9.7182301
A219: 0101 | B219: 010 | C219: =LEFT(E219,10) -> VOL000004- | D219: VO10004A | E219: VOL000004-20496946 P05 - SIDE PLATE FRAM RAIL LOWER LEFT | F219: PA | G219: PC | H219: 801 | I219: PR0 | J219: 40 | K219: 121077 | L219: 002570 | M219: 00257001001 | N219: 45936 | O219: 20250901106434 | P219: 2212.41 | Q219: 2.7620599
A220: 0101 | B220: 100 | C220: =LEFT(E220,10) -> VOL000005- | D220: VO10005A | E220: VOL000005-20496952 P05 - SIDE PLATE FRAM RAIL LOWER RIGHT | F220: PA | G220: PC | H220: 801 | I220: PR0 | J220: 40 | K220: 121371 | L220: 002571 | M220: 00257101001 | N220: 45936 | O220: 20250901106442 | P220: 2212.41 | Q220: 2.7620599
A221: 0101 | B221: 010 | C221: =LEFT(E221,10) -> ARV000226- | D221: FV10226A | E221: ARV000226-483854001X- JACKET OUTER UPPER VRT | F221: PA | G221: PC | H221: 90 | I221: PR0 | J221: 40 | K221: 135762 | L221: 002692 | M221: 00269201001 | N221: 45945 | O221: 20250901113516 | P221: 5893.96 | Q221: 65.488444
A222: 0101 | B222: 010 | C222: =LEFT(E222,10) -> 11.47.424. | D222: PU10020A | E222: 11.47.424.754.008A - FLANGE DE ENTRADA - 17443-21050 | F222: PA | G222: PC | H222: 1983 | I222: PR0 | J222: 40 | K222: 138004 | L222: 002684 | M222: 00268401001 | N222: 45946 | O222: 20250901112732 | P222: 7474.71 | Q222: 3.7693949
... A243: 0101 | B243: 100 | C243: =LEFT(E243,10) -> HWS000141- | D243: HW10141A | E243: HWS000141-86545-1S000 - STAY-FR BPR OTR, LH | F243: PA | G243: PC | H243: 1457 | I243: PR0 | J243: 40 | K243: 222697 | L243: G700003C4 | M243: 00326001001 | N243: 46010 | O243: 20250901137875 | P243: 1860.98 | Q243: 1.2772684
A244: 0101 | B244: 010 | C244: =LEFT(E244,10) -> HWS000142- | D244: HW10142A | E244: HWS000142-86546-1S000 - STAY-FR BPR OTR, RH | F244: PA | G244: PC | H244: 1311 | I244: PR0 | J244: 40 | K244: 224504 | L244: G700003SQ | M244: 00330101001 | N244: 46013 | P244: 1674.49 | Q244: 1.2772616
A245: 0101 | B245: 010 | C245: =LEFT(E245,10) -> ARV000199- | D245: FV10199B | E245: ARV000199-331165606X - END CAP INLET BAFFLE ASSEMBLY-CONSUMO | F245: PP | G245: PC | H245: 23 | I245: PR0 | J245: 20 | K245: 000125 | L245: 000002 | M245: 00000201002 | N245: 45870 | O245: 20250801015697 | P245: 2812.71 | Q245: 122.29174
A246: 0101 | B246: 010 | C246: =LEFT(E246,10) -> ARV000201- | D246: FV10201B | E246: ARV000201-338968204X - END CAP OUTLET BAFFLE ASSEMBLY-CONSUMO | F246: PP | G246: PC | H246: 17 | I246: PR0 | J246: 20 | K246: 000129 | L246: 000003 | M246: 00000301002 | N246: 45870 | O246: 20250801015703 | P246: 2075.1 | Q246: 122.06471
A247: 0101 | B247: 010 | C247: =LEFT(E247,10) -> BOS000073- | D247: BS10073B | E247: BOS000073-F006.U20.201 - CARCACA WSM3-CONSUMO | F247: PP | G247: PC | H247: 1400 | I247: PR0 | J247: 20 | K247: 001706 | L247: 000034 | M247: 00003401002 | N247: 45871 | O247: 20250801016861 | P247: 5932.57 | Q247: 4.23755
A248: 0101 | B248: 010 | C248: =LEFT(E248,10) -> ARV000137- | D248: FV10137B | E248: ARV000137-1981970X - OUTLET CONE UPPER HALF SHELL-CONSUMO | F248: PP | G248: PC | H248: 233 | I248: PR0 | J248: 20 | K248: 003551 | L248: 000148 | M248: 00014801002 | N248: 45873 | O248: 20250801021301 | P248: 2448.22 | Q248: 10.507382
A249: 0101 | B249: 010 | C249: =LEFT(E249,10) -> ARV000138- | D249: FV10138B | E249: ARV000138-1981972X - OUTLET CONE LOWER HALF SHELL-CONSUMO | F249: PP | G249: PC | H249: 317 | I249: PR0 | J249: 20 | K249: 003570 | L249: 000106 | M249: 00010601002 | N249: 45873 | O249: 20250801019481 | P249: 3330.68 | Q249: 10.506877
A250: 0101 | B250: 010 | C250: =LEFT(E250,10) -> CFEL000752 | D250: FV10165B | E250: CFEL000752-3069537 - CONE OUTER - ESTAMPADO P/ 3069541 | F250: PP | G250: PC | H250: 1200 | I250: PR0 | J250: 20 | K250: 003429 | L250: 000018 | M250: 00001801002 | N250: 45873 | O250: 20250801015829 | P250: 7990.26 | Q250: 6.65855
A251: 0101 | B251: 010 | C251: =LEFT(E251,10) -> CFEL000752 | D251: FV10165B1 | E251: CFEL000752-3069537 - CONE OUTER - ESTAMPADO P 3069541-CONSUMO | F251: PP | G251: PC | H251: 1200 | I251: PR0 | J251: 20 | K251: 003651 | L251: 000018 | M251: 00001801003 | N251: 45873 | O251: 20250801009827 | P251: 5167.42 | Q251: 4.3061833
A252: 0101 | B252: 010 | C252: =LEFT(E252,10) -> CFEL000753 | D252: FV10165C | E252: CFEL000753-3069542 - CONE INNER - ESTAMPADO P/ 3069541 | F252: PP | G252: PC | H252: 1200 | I252: PR0 | J252: 20 | K252: 003425 | L252: 000018 | M252: 00001801004 | N252: 45873 | O252: 20250801015847 | P252: 6962.92 | Q252: 5.8024333
A253: 0101 | B253: 010 | C253: =LEFT(E253,10) -> CFEL000753 | D253: FV10165C1 | E253: CFEL000753-3069542 - CONE INNER - ESTAMPADO P 3069541-CONSUMO | F253: PP | G253: PC | H253: 1200 | I253: PR0 | J253: 20 | K253: 003647 | L253: 000018 | M253: 00001801005 | N253: 45873 | O253: 20250801009844 | P253: 4604.39 | Q253: 3.8369917
A254: 0101 | B254: 010 | C254: =LEFT(E254,10) -> ARV000193- | D254: FV10193B | E254: ARV000193-363417102X - CONE OUTLET-CONSUMO | F254: PP | G254: PC | H254: 243 | I254: PR0 | J254: 20 | K254: 003813 | L254: 000051 | M254: 00005101002 | N254: 45873 | O254: 20250801017494 | P254: 1534.67 | Q254: 6.3155144
A255: 0101 | B255: 010 | C255: =LEFT(E255,10) -> ARV000211- | D255: FV10211B | E255: ARV000211-434347102X - INLET CONE-CONSUMO | F255: PP | G255: PC | H255: 540 | I255: PR0 | J255: 20 | K255: 004164 | L255: 000171 | M255: 00017101002 | N255: 45873 | O255: 20250801021659 | P255: 5237.12 | Q255: 9.6983704
A256: 0101 | B256: 010 | C256: =LEFT(E256,10) -> CFEL001062 | D256: FV10230B | E256: CFEL001062-4343468 - MANIFOLD UPPER PART HALF SHELL | F256: PP | G256: PC | H256: 200 | I256: PR0 | J256: 20 | K256: 004065 | L256: 000038 | M256: 00003801002 | N256: 45873 | O256: 20250801016980 | P256: 3963.97 | Q256: 19.81985
... A373: 0101 | B373: 010 | C373: =LEFT(E373,10) -> CFEL000656 | D373: FV10132C | E373: CFEL000656-1311713X - OUTLET CONE - ESTAMPADO P/ 1311709X | F373: PP | G373: PC | H373: 500 | I373: PR0 | J373: 20 | K373: 017921 | L373: 000596 | M373: 00059601004 | N373: 45880 | O373: 20250801026810 | P373: 9319.77 | Q373: 18.63954
A374: 0101 | B374: 010 | C374: =LEFT(E374,9) -> CFEL00065 | D374: FV10132C1 | E374: CFEL000656-1311713X - OUTLET CONE - ESTAMPADO P 1311709X-CONSUMO | F374: PP | G374: PC | H374: 500 | I374: PR0 | J374: 20 | K374: 017912 | L374: 000596 | M374: 00059601005 | N374: 45880 | O374: 20250801012431 | P374: 9207.41 | Q374: 18.41482
A375: 0101 | B375: 010 | C375: =LEFT(E375,9) -> CFEL00073 | D375: HW10051B | E375: CFEL000739-66754-R1000 - REINF-HOOD HINGE MTG LH P/ 66753-R1000 | F375: PP | G375: PC | H375: 1 | I375: PR0 | J375: 20 | K375: 017378 | L375: 000545 | M375: 00054501002 | N375: 45880 | O375: 20250801026683 | P375: 4.51 | Q375: 4.51
A376: 0101 | B376: 010 | C376: =LEFT(E376,9) -> CFEL00073 | D376: HW10051B1 | E376: CFEL000739-66754-R1000 - REINF-HOOD HINGE MTG LH P 66753-R1000-CONSUMO | F376: PP | G376: PC | H376: 1 | I376: PR0 | J376: 20 | K376: 017376 | L376: 000545 | M376: 00054501003 | N376: 45880 | O376: 20250801012358 | P376: 4.4 | Q376: 4.4
A377: 0101 | B377: 010 | C377: =LEFT(E377,9) -> HWS000114 | D377: HW10114B | E377: HWS000114-65618-Q6000 - BRKT FUEL TANK MTG FR LH-CONSUMO | F377: PP | G377: PC | H377: 1466 | I377: PR0 | J377: 20 | K377: 019567 | L377: 000071 | M377: 00007101002 | N377: 45880 | O377: 20250801018448 | P377: 2502.98 | Q377: 1.7073533
A378: 0101 | B378: 100 | C378: =LEFT(E378,9) -> HWS000116 | D378: HW10116B | E378: HWS000116-65819-BW000 - BRKT RR DR SCUFF MTG LH-CONSUMO | F378: PP | G378: PC | H378: 871 | I378: PR0 | J378: 20 | K378: 017836 | L378: 000073 | M378: 00007301002 | N378: 45880 | O378: 20250801018483 | P378: 404.65 | Q378: 0.46458094
A379: 0101 | B379: 100 | C379: =LEFT(E379,9) -> HWS000129 | D379: HW10129B | E379: HWS000129-64582-BX000 - PNL FENDER APRON UPR INR RH-CONSUMO | F379: PP | G379: PC | H379: 250 | I379: PR0 | J379: 20 | K379: 019837 | L379: 000318 | M379: 00031801002 | N379: 45880 | O379: 20250801024059 | P379: 1543.78 | Q379: 6.17512
A380: 0101 | B380: 100 | C380: =LEFT(E380,9) -> MRL000017 | D380: MR10017B | E380: MRL000017 - 18224T5NP52041 - TAMPA (CONSUMO) | F380: PP | G380: PC | H380: 123 | I380: PR0 | J380: 20 | K380: 016984 | L380: 000446 | M380: 00044601002 | N380: 45880 | O380: 20250801025852 | P380: 562.1 | Q380: 4.5699187
A381: 0101 | B381: 010 | C381: =LEFT(E381,9) -> CFEL00107 | D381: MR10019B | E381: CFEL001077 - 18216T5NP100H1 - FLANGE (LAVADA) | F381: PP | G381: PC | H381: 1370 | I381: PR0 | J381: 20 | K381: 016160 | L381: 000449 | M381: 00044901002 | N381: 45880 | O381: 20250801025877 | P381: 5835.76 | Q381: 4.2596788
A382: 0101 | B382: 010 | C382: =LEFT(E382,9) -> CFEL00107 | D382: MR10019B1 | E382: CFEL001077 - 18216T5NP100H1 - FLANGE ESTAMPADA (CONSUMO) | F382: PP | G382: PC | H382: 1370 | I382: PR0 | J382: 20 | K382: 016156 | L382: 000449 | M382: 00044901003 | N382: 45880 | O382: 20250801012216 | P382: 5686.66 | Q382: 4.1508467
A383: 0101 | B383: 010 | C383: =LEFT(E383,9) -> TNC000035 | D383: TN10035B | E383: TNC000035-82090758 - CONE-CONSUMO | F383: PP | G383: PC | H383: 135 | I383: PR0 | J383: 20 | K383: 017622 | L383: 000015 | M383: 00001501002 | N383: 45880 | O383: 20250801015799 | P383: 61.44 | Q383: 0.45511111
A384: 0101 | B384: 100 | C384: =LEFT(E384,9) -> CFEL00081 | D384: VO10074B1-1 | E384: CFEL000813-24738381 - BRACKET P/ 24738366 | F384: PP | G384: PC | H384: 0 | I384: PR0 | J384: 20 | K384: 016255 | L384: 000461 | M384: 00046101001 | N384: 45880 | O384: 20250801009615 | P384: 29.11 | Q384: 29.11
A385: 0101 | B385: 010 | C385: =LEFT(E385,9) -> CFEL00081 | D385: VO10074B1-1-1 | E385: CFEL000813-24083043 - BRACKET P 24083042-CONSUMO | F385: PP | G385: PC | H385: 2 | I385: PR0 | J385: 20 | K385: 016252 | L385: FV000002N | M385: 00026101004 | N385: 45880 | O385: 20250801009309 | P385: 28.78 | Q385: 14.39
... A464: 0101 | B464: 010 | C464: =LEFT(E464,9) -> CFSB00056 | D464: VO10076B1 | E464: CFSB000569-24739123 - BRACKET P/24736213 - SOLDADO | F464: PP | G464: PC | H464: 57 | I464: PR0 | J464: 40 | K464: 038398 | L464: 001107 | M464: 00110701013 | N464: 45889 | O464: 20250801014148 | P464: 2289.84 | Q464: 40.172632
C465: =LEFT(E465,9) -> CFSB00057 | D465: VO10076B1-1 | E465: CFSB000573-24739644-21731761 - BRACKET P/24484490-24484490 - PORCAS SOLDADAS | F465: PP | G465: PC | H465: 57 | I465: PR0 | J465: 20 | K465: 038390 | L465: 001107 | M465: 00110701016 | N465: 45889 | O465: 20250801009705 | P465: 1233.01 | Q465: 21.631754
C466: =LEFT(E466,9) -> CFEL00106 | D466: VO10076B1-1-1 | E466: CFEL001061-24739644-21731761 - BRACKET P/ 24736213-24484490 | F466: PP | G466: PC | H466: 57 | I466: PR0 | J466: 20 | K466: 038386 | L466: 001107 | M466: 00110701017 | N466: 45889 | O466: 20250801009440 | P466: 1028.92 | Q466: 18.051228
C467: =LEFT(E467,9) -> CFEL00106 | D467: VO10076BX1 | E467: CFEL001061-24739644 - BRACKET P 24736213-CONSUMO | F467: PP | G467: PC | H467: 57 | I467: PR0 | J467: 20 | K467: 038379 | L467: 001107 | M467: 00110701018 | N467: 45889 | O467: 20250801009268 | P467: 795.02 | Q467: 13.947719
C468: =LEFT(E468,9) -> CFEL00106 | D468: VO10077B | E468: CFEL001066-78813914 - ROOF COOLER TANK CAB (ESTAMPADO) | F468: PP | G468: PC | H468: 45 | I468: PR0 | J468: 20 | K468: 039399 | L468: 001165 | M468: 00116501002 | N468: 45889 | O468: 20250801032838 | P468: 633.31 | Q468: 14.073556
C469: =LEFT(E469,9) -> ARV000126 | D469: FV10126B | E469: ARV000126-1795910X - FLANGE BRIDE ECHEPPEMENT-CONSUMO | F469: PP | G469: PC | H469: 994 | I469: PR0 | J469: 20 | K469: 040276 | L469: 001176 | M469: 00117601002 | N469: 45890 | O469: 20250801033066 | P469: 2768.64 | Q469: 2.7853521
C470: =LEFT(E470,9) -> ARV000216 | D470: FV10216B | E470: ARV000216-470571601X - HALF SHELL EVAPORATOR TUBE LOWER-CONSUMO | F470: PP | G470: PC | H470: 56 | I470: PR0 | J470: 20 | K470: 041188 | L470: 001228 | M470: 00122801002 | N470: 45890 | O470: 20250801033190 | P470: 1577.98 | Q470: 28.178214
C471: =LEFT(E471,9) -> CFEL00079 | D471: HW10118B | E471: CFEL000792-65533-C9000 - BRKT ASSY REAR SEAT UPR SD MTG LH - ESTAMPADO | F471: PP | G471: PC | H471: 543 | I471: PR0 | J471: 20 | K471: 042030 | L471: 001227 | M471: 00122701002 | N471: 45890 | O471: 20250801033184 | P471: 763.09 | Q471: 1.4053223
C472: =LEFT(E472,9) -> CFEL00079 | D472: HW10118B1 | E472: CFEL000792-65533-C9000 - BRKT ASSY REAR SEAT UPR SD MTG LH - ESTAMPADO-CONSUMO | F472: PP | G472: PC | H472: 543 | I472: PR0 | J472: 20 | K472: 042026 | L472: 001227 | M472: 00122701003 | N472: 45890 | O472: 20250801014362 | P472: 565.8 | Q472: 1.041989
C473: =LEFT(E473,9) -> CFEL00079 | D473: HW10119B | E473: CFEL000793-65543-C9000 - BRKT ASSY REAR SEAT UPR SD MTG RH - ESTAMPADO | F473: PP | G473: PC | H473: 1880 | I473: PR0 | J473: 20 | K473: 039980 | L473: 001170 | M473: 00117001002 | N473: 45890 | O473: 20250801032966 | P473: 2638.26 | Q473: 1.4033298
C474: =LEFT(E474,9) -> CFEL00079 | D474: HW10119B1 | E474: CFEL000793-65543-C9000 - BRKT ASSY REAR SEAT UPR SD MTG RH - ESTAMPADO-CONSUMO | F474: PP | G474: PC | H474: 1880 | I474: PR0 | J474: 20 | K474: 039976 | L474: 001170 | M474: 00117001003 | N474: 45890 | O474: 20250801014283 | P474: 1956.81 | Q474: 1.0408564
C475: =LEFT(E475,9) -> ARV000208 | D475: FV10208B | E475: ARV000208-331982604X - JACKET OUTER LOWER VERTICAL-CONSUMO | F475: PP | G475: PC | H475: 232 | I475: PR0 | J475: 20 | K475: 044496 | L475: 001309 | M475: 00130901002 | N475: 45891 | O475: 20250801033530 | P475: 7981.82 | Q475: 34.404397
C476: =LEFT(E476,9) -> CFSB00056 | D476: HY10002B | E476: CFSB000567-39211-07FM0 - BRKT OXYGEN SNSR BINARY ZINCADO | F476: PP | G476: PC | H476: 6544 | I476: PR0 | J476: 40 | K476: 045079 | L476: FV00001MA | M476: 00091401002 | N476: 45891 | O476: 20250801031168 | P476: 9114.34 | Q476: 1.3927781
... C643: =LEFT(E643,9) -> TNC000019 | D643: TN10019A | E643: TNC000019-82090920 - SUPORTE | F643: TP | G643: PC | H643: 413 | I643: PR0 | J643: 40 | K643: 198835 | L643: 002405010 | M643: 00240501001 | N643: 45993 | O643: 20250901100854 | P643: 0 | Q643: 0
C644: =LEFT(E644,9)
C645: =LEFT(E645,9)
C646: =LEFT(E646,9)
C647: =LEFT(E647,9)
C648: =LEFT(E648,9)
C649: =LEFT(E649,9)
C650: =LEFT(E650,9)
C651: =LEFT(E651,9)
C652: =LEFT(E652,9)
C653: =LEFT(E653,9)
C654: =LEFT(E654,9)
C655: =LEFT(E655,9)
... C9081: =LEFT(E9081,9)

Sheet Planilha1
A1: Produto | B1: Descrição | C1: Código Protheus | D1: Descrição Protheus | E1: Un. | F1: Tipo | G1: Descrição Tipo | H1: Grupo | I1: Descrição Grupo | J1: Classe Prod. | K1: Classe | L1: Custo Final Auditado
A2: ARV000006 | B2: E4038272 - DISCO DE SAÍDA | C2: FV10006A | D2: ARV000006-E4038272 - DISCO DE SAIDA | E2: PC | F2: 700 | G2: PRODUTO ACABADO | H2: 508 | I2: COMPONENTES - FAURECIA FCM | J2: (A)cabado | K2: A | L2: 2.4351871
A3: ARV000020 | B3: E4050051 - SCJ SUPORTE CAT ROCAM | C3: FV10020A | D3: ARV000020-E4050051 - SCJ SUPORTE CAT ROCAM | E3: PC | F3: 700 | G3: PRODUTO ACABADO | H3: 508 | I3: COMPONENTES - FAURECIA FCM | J3: (A)cabado | K3: A | L3: 1.7469154
A4: ARV000028 | B4: E4050335 - SEPARADOR A | C4: FV10028A | D4: ARV000028-E4050335 - SEPARADOR A | E4: PC | F4: 700 | G4: PRODUTO ACABADO | H4: 508 | I4: COMPONENTES - FAURECIA FCM | J4: (A)cabado | K4: A | L4: 2.8220687
A5: ARV000030 | B5: E4050336 - SEPARADOR B | C5: FV10030A | D5: ARV000030-E4050336 - SEPARADOR B | E5: PC | F5: 700 | G5: PRODUTO ACABADO | H5: 508 | I5: COMPONENTES - FAURECIA FCM | J5: (A)cabado | K5: A | L5: 2.8219198
A6: ARV000034 | B6: 231.577 - TAMPA | C6: FV10034A | D6: ARV000034-231.577 - TAMPA | E6: PC | F6: 700 | G6: PRODUTO ACABADO | H6: 508 | I6: COMPONENTES - FAURECIA FCM | J6: (A)cabado | K6: A | L6: 4.319153
A7: ARV000035 | B7: 229.712 - TAMPA DE ENTRADA/SAÍDA | C7: FV10035A | D7: ARV000035-229.712 - TAMPA DE ENTRADA/SAIDA | E7: PC | F7: 700 | G7: PRODUTO ACABADO | H7: 508 | I7: COMPONENTES - FAURECIA FCM | J7: (A)cabado | K7: A | L7: 5.606096
A8: ARV000038 | B8: E4042491 - TAMPA DE ENTRADA | C8: FV10038A | D8: ARV000038-E4042491 - TAMPA DE ENTRADA | E8: PC | F8: 700 | G8: PRODUTO ACABADO | H8: 508 | I8: COMPONENTES - FAURECIA FCM | J8: (A)cabado | K8: A | L8: 18.771158
A9: ARV000042 | B9: E4042496 - SEPARADOR A | C9: FV10042A | D9: ARV000042-E4042496 - SEPARADOR A | E9: PC | F9: 700 | G9: PRODUTO ACABADO | H9: 508 | I9: COMPONENTES - FAURECIA FCM | J9: (A)cabado | K9: A | L9: 2.8824095
A10: ARV000043 | B10: E4042497 - SEPARADOR B | C10: FV10043A | D10: ARV000043-E4042497 - SEPARADOR B | E10: PC | F10: 700 | G10: PRODUTO ACABADO | H10: 508 | I10: COMPONENTES - FAURECIA FCM | J10: (A)cabado | K10: A | L10: 2.8853893
A11: ARV000047 | B11: E4060882 - FLANGE DE SAÍDA | C11: FV10047A | D11: ARV000047-E4060882 - FLANGE DE SAIDA | E11: PC | F11: 700 | G11: PRODUTO ACABADO | H11: 508 | I11: COMPONENTES - FAURECIA FCM | J11: (A)cabado | K11: A | L11: 2.4005296
A12: ARV000048 | B12: E4060792 - FLANGE DE ENTRADA | C12: FV10048A | D12: ARV000048-E4060792 - FLANGE DE ENTRADA | E12: PC | F12: 700 | G12: PRODUTO ACABADO | H12: 508 | I12: COMPONENTES - FAURECIA FCM | J12: (A)cabado | K12: A | L12: 7.5214583
A13: ARV000050 | B13: E4073955BR - DISCO | C13: FV10050A | D13: ARV000050-E4073955BR - DISCO | E13: PC | F13: 700 | G13: PRODUTO ACABADO | H13: 508 | I13: COMPONENTES - FAURECIA FCM | J13: (A)cabado | K13: A | L13: 2.9123127
... A2903: VOL000079 | B2903: 16.32.012.851.021A - 24484490 - HEAT SHIELD REAR - MONTADO | C2903: VO10079A | D2903: VOL000079-16.32.012.851.021A - 24484490 - HEAT SHIELD REAR - MONTADO | E2903: PC | F2903: 700 | G2903: PRODUTO ACABADO | H2903: 536 | I2903: COMPONENTES - PUREM | J2903: (A)cabado | K2903: A | L2903: 153.76308
